Workbook

Sheet How We Run
A1: Tage VC — How We Run
A2: Operating home · Deal Flow · Portfolio/Subs · Firm + SS · Portal: Architecture → Spec → Cursor Brief · Brand: Brand & Styling Guide · AI tickets: SS Model §7
A3: ⚠ DATA FRESHNESS (FIRM STANDARD) | B3: BD10 close → BD10–12 pack + Roll-up (Period B13) → BD15 Portfolio Active CORE $ + Health → Command Center must read FRESH. Same period everywhere. STALE = no firm review until Active $ = Roll-up E.
A4: 1 · PICK THE TRACK
A5: Situation | B5: Track | C5: Start here | D5: End state
A6: Startup / growth equity check | B6: VC Invest | C6: Pipeline Active | D6: Wired → Portfolio (investor)
A7: Build something new with us | B7: VC · Launch path | C7: Pipeline (Path=Launch) | D7: Same + heavy operator support
A8: Buy / merge / roll-up control | B8: M&A Buy | C8: M&A Pipeline Active | D8: Acquired → Integration → Portfolio
A9: Real estate asset (resi or CRE) | B9: RE Buy | C9: RE Pipeline Active | D9: Purchased → RE Portfolio
A10: 2 · WEEKLY RHYTHM
A11: When | B11: Ritual | C11: Owner | D11: Sheet | E11: Outcome
A12: Mon | B12: Triage inbound + next actions | C12: Associate | D12: Pipeline / M&A Pipeline | E12: No blank Next Action dates
A13: Tue / Thu | B13: DD + deal blockers standup | C13: Partner | D13: Needs Completed / Deal or M&A Tasks | E13: Unblock or escalate
A14: Wed | B14: IC / terms / LOI review | C14: Partners | D14: Scorecard + Model (+ M&A twins) | E14: Go / conditions / pass
A15: Fri | B15: Command Center pulse | C15: Partner | D15: Command Center | E15: Funnel health + $ in flight
A16: Biweekly | B16: Portfolio ops review | C16: COO | D16: Portfolio Active | E16: Health, risks, asks
A17: As needed | B17: Closing war room | C17: Counsel + Ops | D17: Deal or M&A Tasks | E17: CPs → wire / acquire
A18: Mon (RE) | B18: RE pipeline scrub by Route + sourcer | C18: RE Sourcer / Partner | D18: RE Pipeline Active | E18: Stale deals cleared
A19: 3 · DEAL FLOW (HAPPY PATH)
A20: VC Invest | B20: Source → Screen → Call → Partner → DD + Score + Model → IC → TS → Docs → Wire → Handoff → Portfolio
A21: M&A Buy | B21: Source → CIM → Mgmt → IOI → LOI → QoE/DD → Score + Model → SPA → Close → Integration → Portfolio
A22: RE Buy | B22: Source → Screen → Underwrite (Resi or CRE) → Offer → PSA → Diligence → Close → RE Portfolio
A23: 4 · ROLES
A24: Role | B24: Owns | C24: Does not auto-decide
A25: Associate | B25: Intake, research, tasks, memos, data room | C25: Pass tone; IC vote
A26: Partner | B26: Thesis fit, IC, terms/LOI, board | C26: — (final call on capital)
A27: Counsel / Ops | B27: Docs, CPs, wire, archive | C27: Commercial terms alone
A28: Subsidiary COO | B28: Post-close growth, KPIs, integration | C28: New buys without IC
A29: RE Sourcer (Resi / CRE) | B29: Find assets, underwrite, offer, diligence | C29: Capital commit without Partner
A30: 5 · GOLDEN RULES
A31: 1. One canonical Company name on every sheet (join key).
A32: 2. Every active row has Owner + Next Action + date — no zombies.
A33: 3. Libraries spawn work; humans score, negotiate, and wire.
A34: 4. Complete → archive (never delete history).
A35: 5. Blue = inputs. Black = formulas. Command Center = firm pulse.
A36: 6. VC check ≠ buy the company — pick the track on day one.
A37: 7. Business deals ≠ RE deals — separate pipelines and sourcers.
A38: 6 · WHERE TO CLICK
A39: Need… | B39: Go to…
A40: Firm pulse | B40: Command Center
A41: Map / colors / tracks | B41: Process Map
A42: New startup lead | B42: Pipeline Active → Lead Process Library
A43: New acquisition target | B43: M&A Pipeline Active → M&A Process Library
A44: IC package | B44: Scorecard + Financial Model (or M&A twins)
A45: Closing a check | B45: Deal Active / Deal Tasks
A46: Closing a buy | B46: M&A Tasks → M&A Integration
A47: Hand to operators | B47: Portfolio Handoff → Portfolio Active
A48: Build the portal | B48: Cursor Brief + Data Dictionary + Platform Spec
A49: New RE deal (resi/CRE) | B49: RE Pipeline Active → RE Process Library → RE Underwrite
A50: Print / PDF this tab as the wall chart. Detail lives in the colored phase tabs.
A51: Deep ops: Subsidiary Operating System · Firm Operations (end of workbook)
A53: THREE-LAYER MODEL
A54: Layer | B54: What it is | C54: Owner | D54: Primary tabs
A55: 1 · Deal Flow | B55: Source → diligence → close (VC / M&A / RE) | C55: Partners + Sourcers | D55: Pipelines, libraries, scorecards, Command Center
A56: 2 · Subsidiary Ops | B56: Post-handoff growth, KPIs, audits, Shared Svcs use | C56: COO of Subsidiaries | D56: Subsidiary Operating System · Portfolio Handoff · Portfolio Active
A57: 3 · Firm Ops | B57: Capital allocation, Shared Services, governance, compliance | C57: Visionary (+ COO on SS) | D57: Firm Operations · How We Run · Command Center
A58: Hand-off between layers: Wire/Acquire/Purchase → Portfolio Handoff → Portfolio Active → Subsidiary OS rhythm. Capital & SS live in Firm Operations.
A59: Shared Services: Shared Services Operating Model (cadences + Intuit/QBE automation). Audits: Annual Audit Master Checklist.
A60: Firm layer deep dive: Firm Operations. Sub layer deep dive: Subsidiary Operating System.
A61: DATA & DOCS
A62: Entities: Entity Master (ENT-*). P&L/KPI roll-up: Portfolio Roll-up. Docs/DocuSign: Document Management & Workflow.
A63: Shared Services cadences: Shared Services Operating Model (QBE automation). Annual audits: Annual Audit Master Checklist.
A64: Data model detail: Data Dictionary. Portal build: Cursor Brief + Platform Spec.
A65: SUBSIDIARY STANDARD
A66: Official standard: Core Subsidiary Structure (§1–11). CORE = required P&L, KPIs, rhythm, health, SS, handoff, roll-ups. FLEX = industry add-ons only.
A67: COO enforces on Portfolio Active. Roll-up math: Portfolio Roll-up. Ops playbook: Subsidiary Operating System. Exceptions to CORE: Visionary.
A68: Non-negotiable health enums: On Track | Watch | At Risk | Critical — definitions on Core Subsidiary Structure §12.
A69: Recruit 619: brand + KPI bridge on Recruit 619 Alignment tab (canonical name Recruit 619 only).
... A72: WORKBOOK MAP (TAB GROUPS)
A73: Group | B73: Tabs (left → right) | C73: Color cue
A74: Start here | B74: How We Run · Brand & Styling Guide · Process Map · Command Center | C74: Slate / stone
A75: Portal build | B75: Portal Architecture · Platform Spec · Cursor Brief · Data Dictionary · Entity Master | C75: Slate
A76: VC Deal Flow | B76: Pipeline · Lead Tasks · DD · Scorecard · Financial Model · Deal desk | C76: Slate + taupe + cool slate
A77: M&A Deal Flow | B77: M&A Pipeline · Tasks · Scorecard · Model · Integration | C77: Steel gray
A78: RE Deal Flow | B78: RE Pipeline · Tasks · Underwrite · RE Portfolio | C78: Brown
A79: Portfolio / Subs | B79: Core Subsidiary Structure · Sub OS · Recruit 619 Alignment · Handoff · Portfolio Active · Portfolio Roll-up | C79: Sage
A80: Firm + SS | B80: Shared Services Operating Model · Annual Audit · Firm Operations · Document Management | C80: Sage / slate
A81: Closed/logs | B81: All *Closed and *Done tabs | C81: Green
A83: Naming standards: Recruit 619 (not 619 Recruiting). Health: On Track | Watch | At Risk | Critical. Blue cells = inputs. Black = formulas.
A84: ✓ Final polish · Layer tab colors · Green = logs · ⚠ DATA FRESHNESS · Blue inputs · Black formulas · Health enums · Recruit 619 · Grok+Cursor: SS §7
A85: AI tickets: Shared Services Operating Model §7 (Grok + Cursor Ticketing) · Portal Architecture §9 · Cursor Brief automation policy.

Sheet Brand & Styling Guide
A1: Tage VC — Brand & Styling Guide
A2: Visual standards for all Tage VC and subsidiary workbooks. Apply tab colors and header styles from this guide.
A42: START HERE ORDER
A43: 1) How We Run 2) Brand & Styling Guide 3) Command Center 4) Core Subsidiary Structure 5) Deal / M&A / RE pipelines 6) Portfolio Roll-up 7) Firm + Shared Services
A44: Recruit 619 ops playbook must match this palette and Recruit 619 Alignment KPI names.

Sheet Process Map
A1: Tage VC — Process Map | End-to-End Operating System
A2: Orientation map. Start: How We Run. Build: Portal Architecture. Standards: Core Subsidiary Structure · Brand & Styling Guide.
A4: Phase | B4: Tab color | C4: Order | D4: What happens | E4: Sheets in this phase | F4: Exit to next phase when…
A5: 0 · Map | B5: Warm stone | C5: First | D5: Orientation — how the workbook fits together | E5: Process Map | F5: —
A6: 1 · Source & Evaluate | B6: Slate (brand primary) | C6: 1st | D6: Find leads, screen thesis, first calls, partner meeting | E6: Pipeline Active, Closed, Lead Tasks, Lead Library, Pipeline Notes | F6: Outcome = Advanced to DD (partner approved full DD)
A7: 2 · Due Diligence | B7: Taupe accent | C7: 2nd | D7: Full DD checklist across team, market, product, financials, legal… | E7: Needs Completed, Completed, Checklist Library, Notes | F7: Critical DD done (or waived) + ready for IC
A8: 3 · Execute & Close | B8: Cool slate | C8: 3rd | D8: IC → term sheet → confirmatory DD → docs → wire → post-close | E8: Deal Active, Closed, Deal Tasks, Deal Library, Deal Notes | F8: Outcome = Wired / Closed (portfolio handoff)
A10: End-to-end flow
A11: Step | B11: Action | C11: Primary sheet | D11: ID pattern
A12: 1 | B12: Log lead + source | C12: Pipeline Active | D12: LD-###
A13: 2 | B13: Screen → call → partner → Ready for DD | C13: Lead Tasks + Pipeline | D13: LT-###
A14: 3 | B14: Close pipeline as Advanced to DD | C14: Pipeline Closed | D14: —
A15: 4 | B15: Spawn DD checklist for same Company | C15: Needs Completed | D15: DD-###
A16: 5 | B16: Complete DD; archive tasks | C16: Completed | D16: —
A17: 6 | B17: IC approval | C17: Deal Active (new) | D17: DE-###
A18: 7 | B18: Term sheet negotiate + sign | C18: Deal Tasks Active | D18: DT-###
A19: 8 | B19: Docs + closing conditions + wire | C19: Deal Active / Tasks | D19: —
A20: 9 | B20: Close deal; post-close portfolio | C20: Deal Closed | D20: —
A22: How to read tab colors
A23: Slate = source. Taupe = DD. Cool slate = close. Brand neutrals from site OG/screenshot palette.
A25: Golden rule
A26: One Company name everywhere: Pipeline = DD Entity = Deal Company (join key).
A28: Brand palette (site)
A29: #3A414F | B29: Primary slate — Source tabs + main UI dark
A30: #9F957C | B30: Taupe accent — DD tabs
A31: #535C63 | B31: Cool slate — Execute/Close tabs
A32: #7C7871 | B32: Warm stone — Process Map
A33: #ECE9E6 | B33: Warm sand — page background on site
A34: #D7D3C3 | B34: Light sand — secondary surface
A36: SYSTEM LAYERS (new)
A37: Command Center — firm KPIs (slate tab near Map)
A38: Deal Scorecard + Financial Model — IC analytics (taupe with DD)
A39: Portfolio Handoff + Portfolio Active — COO ops (sage tabs)
A40: Data Dictionary + Platform Spec + Cursor Brief — build the portal (slate)
A41: Flow: Pipeline → Scorecard/Model → DD → Deal desk → Wire → Handoff → Portfolio → (app via Cursor Brief)
A43: TWO TRACKS
A44: A) VC INVEST (slate/taupe/cool) — startup or growth check → Deal desk → Portfolio as investor
A45: B) M&A BUY (steel gray #4A5568) — platform/add-on/merger → LOI → QoE → close → Integration → Portfolio as operator
A46: M&A sheets: M&A Pipeline, Tasks, Library, Scorecard, Model, Integration, Notes
A47: M&A stages: Sourced → CIM → Mgmt → IOI → LOI → DD → Docs → Closing → Integration
A49: THREE TRACKS (+ RE)
... A54: RE stages: Sourced → Screen → Underwriting → Offer → LOI/PSA → Diligence → Closing → Onboard

Sheet Command Center
A1: Tage VC — Command Center | Firm Funnel · Capital · Portfolio Pulse
A2: Read-mostly. Health ← Portfolio Active · Money ← Portfolio Roll-up · Funnel ← pipelines. Fix STALE before firm review. Nav: How We Run.
A3: ⚠ DATA FRESHNESS | B3: Roll-up Period | C3: Active Σ | D3: Roll-up E | E3: Status
A4: Calendar: BD10 close · BD10–12 pack · BD15 Active+Health | B4: =IFERROR('Portfolio Roll-up'!B13,"set B13") -> 2026-03 | C4: ← must match packs | D4: Finance sets period | E4: COO Health on Active only
A5: ARR ($k) | B5: must match → | C5: =IFERROR(SUM(TablePortfolio[ARR ($k)]),0) -> 600 | D5: =IFERROR('Portfolio Roll-up'!E17,0) -> 600 | E5: =IF(ABS(C5-D5)<0.05,"FRESH","STALE") -> FRESH
A6: Net Burn ($k) | B6: must match → | C6: =IFERROR(SUM(TablePortfolio[Net Burn ($k)]),0) -> 75 | D6: =IFERROR('Portfolio Roll-up'!E23,0) -> 75 | E6: =IF(ABS(C6-D6)<0.05,"FRESH","STALE") -> FRESH
A7: Cash ($k) | B7: must match → | C7: =IFERROR(SUM(TablePortfolio[Cash ($k)]),0) -> 1170 | D7: =IFERROR('Portfolio Roll-up'!E24,0) -> 1170 | E7: =IF(ABS(C7-D7)<0.05,"FRESH","STALE") -> FRESH
A8: OVERALL | B8: Health only on Portfolio Active (COO by BD15) | E8: =IF(COUNTIF(E5:E7,"STALE")=0,"✓ FRESH — OK for firm review","✗ STALE — fix before firm review") -> ✓ FRESH — OK for firm review
A9: Blocked DD tasks | B9: =IFERROR(COUNTIF(TableActive[Status],"Blocked"),0) -> 1 | C9: 2 | D9: =IF(B9<=C9,"OK","Escalate") -> OK
A10: FUNNEL SNAPSHOT
A11: Metric | B11: Count | C11: Target | D11: Status
A12: Active leads (pipeline) | B12: =IFERROR(COUNTA(TablePipeline[Lead ID]),0) -> 5 | C12: 25 | D12: =IF(B12>=C12,"On track",IF(B12>=C12*0.7,"Watch","Low")) -> Low
A13: Ready for DD | B13: =IFERROR(COUNTIF(TablePipeline[Pipeline Stage],"Ready for DD"),0) -> 1 | C13: 3 | D13: =IF(B13>=C13,"On track",IF(B13>=1,"Watch","Low")) -> Watch
A14: Open DD tasks | B14: =IFERROR(COUNTA(TableActive[ID]),0) -> 6 | C14: 40 | D14: =IF(B14<=C14,"On track","Heavy load") -> On track
A15: Blocked DD tasks | B15: =IFERROR(COUNTIF(TableActive[Status],"Blocked"),0) -> 1 | C15: 2 | D15: =IF(B15<=C15,"OK","Escalate") -> OK
A16: Active deals (TS→Close) | D16: =IF(B16>=1,"Active","Idle") -> Idle
A17: Deals in closing band | B17: =IFERROR(COUNTIF(TableDeal[Execution Stage],"Closing Conditions")+COUNTIF(TableDeal[Execution Stage],"Signing Ready"),0) -> 0 | C17: 1 | D17: =IF(B17>=C17,"On track",IF(B17=0,"None","Watch")) -> None
A18: Closed wins (log) | B18: =IFERROR(COUNTIF(TableDealClosed[Outcome],"Wired / Closed"),0) -> 1 | C18: 5 | D18: =IF(B18>=C18,"On track","Building") -> Building
A19: Pipeline passes (log) | B19: =IFERROR(COUNTIF(TablePipelineClosed[Outcome],"Pass"),0) -> 1 | D19: —
A20: Advanced to DD (log) | B20: =IFERROR(COUNTIF(TablePipelineClosed[Outcome],"Advanced to DD"),0) -> 1 | D20: —
A21: CONVERSION & QUALITY
A22: Metric | B22: Value | C22: Notes
A23: Screen→DD conversion (closed) | B23: =IFERROR(B20/MAX(B19+B20,1),0) -> 0.5 | C23: Advanced / (Advanced + Pass) from closed log
A24: Strong-fit share of active pipeline | C24: Quality of top of funnel
A25: Critical open DD items | B25: =IFERROR(COUNTIF(TableActive[Priority],"Critical"),0) -> 3 | C25: Must clear before IC
A26: Open lead eval tasks | B26: =IFERROR(COUNTA(TableLeadTasks[Task ID]),0) -> 4 | C26: Pre-DD work in flight
A27: Open deal exec tasks | B27: =IFERROR(COUNTA(TableDealTasks[Task ID]),0) -> 3 | C27: TS→close work in flight
A28: Closed wired check size ($k) | B28: =IFERROR(SUMIF(TableDealClosed[Outcome],"Wired / Closed",TableDealClosed[Check Size ($k)]),0) -> 750
A30: OPERATING CADENCE
A31: Ritual | B31: Owner | C31: Cadence | D31: Sheet
A32: Inbound triage + source ROI | B32: Associate | C32: Daily / Weekly | D32: Pipeline Active / Closed
A33: DD standup (blockers) | B33: Partner | C33: 2x week | D33: Needs Completed
A34: IC + term sheet review | B34: Partners | C34: Weekly | D34: Deal Scorecard + Deal Active
A35: Closing war room | B35: Counsel + Ops | C35: As needed | D35: Deal Tasks Active
A36: Portfolio ops review | B36: Subsidiary COO | C36: Biweekly | D36: Portfolio Active
A38: HOW TO USE THIS SYSTEM
A39: 1. Source in Pipeline → score in Deal Scorecard when serious → DD tasks + Financial Model → IC → Deal Active → wire → Portfolio Handoff.
A40: 2. One Company name everywhere. IDs: LD- / LT- / DD- / DE- / DT- / PH- / PF-.
A41: 3. Blue cells = targets and model inputs. Black = formulas. Command Center is read-mostly.
A42: 4. Platform build: see Platform Spec + Cursor Brief + Data Dictionary.
A43: PORTFOLIO HEALTH PULSE
A44: Source: Portfolio Active Health (live COUNTIF). Money block below pulls Portfolio Roll-up. If Active sums ≠ Roll-up $ → pack not synced — fix before firm review. | B44: =IFERROR(COUNTIF(TablePortfolio[Health],"On Track"),0) -> 3 | C44: Health status
A45: Health status | B45: Count | C45: % of portfolio | D45: Action cue | E45: Source
A46: On Track | B46: =IFERROR(COUNTIF(TablePortfolio[Health],"On Track"),0) -> 3 | C46: =IFERROR(B46/MAX(B50,1),0) -> 1 | D46: Standard monthly pack | E46: Portfolio Active
A47: Watch | B47: =IFERROR(COUNTIF(TablePortfolio[Health],"Watch"),0) -> 0 | C47: =IFERROR(B47/MAX(B50,1),0) -> 0 | D47: Mitigation + Top Risk required | E47: Portfolio Active
A48: At Risk | B48: =IFERROR(COUNTIF(TablePortfolio[Health],"At Risk"),0) -> 0 | C48: =IFERROR(B48/MAX(B50,1),0) -> 0 | D48: Recovery plan ≤10 bd · Partner | E48: Portfolio Active
A49: Critical | B49: =IFERROR(COUNTIF(TablePortfolio[Health],"Critical"),0) -> 0 | C49: =IFERROR(B49/MAX(B50,1),0) -> 0 | D49: War room 48h · Visionary | E49: Portfolio Active
A50: Active portfolio companies | B50: =IFERROR(COUNTA(TablePortfolio[PF ID]),0) -> 3 | C50: =1 -> 1 | D50: Must match Entity Master Active subs | E50: Portfolio Active
A51: Attention required (At Risk + Critical) | B51: =B48+B49 -> 0 | C51: =IFERROR(B51/MAX(B50,1),0) -> 0 | D51: =IF(B51=0,"Clear","OPEN — see Portfolio Active filter") -> Clear | E51: Derived
A53: PORTFOLIO FINANCIALS (FROM ROLL-UP)
A54: Metric | B54: Value | C54: Notes | D54: Source cell
A55: Portfolio Revenue / ARR ($k) | B55: =IFERROR('Portfolio Roll-up'!E17,0) -> 600 | C55: SUM of subsidiaries (not Firm) | D55: Portfolio Roll-up!E17
A56: Portfolio Gross Margin % | B56: =IFERROR('Portfolio Roll-up'!E20,0) -> 0.80833333 | C56: WEIGHTED = ΣGP/ΣRev | D56: Portfolio Roll-up!E20
A57: Portfolio Net Burn ($k) | B57: =IFERROR('Portfolio Roll-up'!E23,0) -> 75 | C57: SUM of sub burn | D57: Portfolio Roll-up!E23
A58: Portfolio Cash ($k) | B58: =IFERROR('Portfolio Roll-up'!E24,0) -> 1170 | C58: SUM of sub cash | D58: Portfolio Roll-up!E24
A59: Firm-only Cash ($k) | B59: =IFERROR('Portfolio Roll-up'!F24,0) -> 800 | C59: Tage mgmt treasury (col F) | D59: Portfolio Roll-up!F24
A60: Consolidated Cash ($k) | B60: =IFERROR('Portfolio Roll-up'!G24,0) -> 1970 | C60: Portfolio + Firm | D60: Portfolio Roll-up!G24
A61: Min runway (burning subs, mo) | B61: =IFERROR('Portfolio Roll-up'!E25,"n/a") -> 14 | C61: MIN of numeric runways; n/a if none burning | D61: Portfolio Roll-up!E25
A62: Runway breach any sub (<12)? | B62: =IFERROR('Portfolio Roll-up'!E26,"n/a") -> ok | C62: ok or REVIEW | D62: Portfolio Roll-up!E26
A63: Total portfolio ARR from Active ($k) | B63: =IFERROR(SUM(TablePortfolio[ARR ($k)]),0) -> 600 | C63: Should align with Roll-up Revenue when packs current | D63: TablePortfolio[ARR ($k)]
A64: Total portfolio Net Burn from Active ($k) | B64: =IFERROR(SUM(TablePortfolio[Net Burn ($k)]),0) -> 75 | C64: Ops UI sum — reconcile to Roll-up E23 | D64: TablePortfolio[Net Burn ($k)]
A65: Total portfolio Cash from Active ($k) | B65: =IFERROR(SUM(TablePortfolio[Cash ($k)]),0) -> 1170 | C65: Ops UI sum — reconcile to Roll-up E24 | D65: TablePortfolio[Cash ($k)]
A67: PORTFOLIO ATTENTION LIST
A68: Open Portfolio Active and filter Health = At Risk or Critical. Top Risk column is the narrative. This count drives escalation:
A69: Attention count | B69: =B51 -> 0 | C69: =IF(B69=0,"No open At Risk/Critical",IF(B49>0,"CRITICAL present — Visionary path",IF(B48>0,"At Risk present — Partner recovery","Watch only"))) -> No open At Risk/Critical
A70: DATA FRESHNESS CHECK: (1) Same period on Roll-up B13 and packs. (2) Active ARR/Burn/Cash totals should equal Roll-up E17/E23/E24. (3) Health only on Active — Command Center only counts it. (4) Stale if Active Last Update older than current pack month.
A72: M&A TRACK
A73: Active M&A targets | B73: =IFERROR(COUNTA(TableMAPipeline[MA ID]),0) -> 2 | C73: Buy/merge/roll-up pipeline
A74: In LOI / exclusivity | B74: =IFERROR(COUNTIF(TableMAPipeline[MA Stage],"LOI / Exclusivity"),0) -> 1 | C74: Clock running
A75: Open M&A tasks | B75: =IFERROR(COUNTA(TableMATasks[Task ID]),0) -> 2 | C75: Acquisition work in flight
A76: Acquired (log) | B76: =IFERROR(COUNTIF(TableMAClosed[Outcome],"Acquired"),0) -> 0 | C76: Closed buys
A77: Walked (log) | B77: =IFERROR(COUNTIF(TableMAClosed[Outcome],"Walked"),0) -> 1 | C77: Passed after work
A79: REAL ESTATE TRACK
A80: Active RE deals | B80: =IFERROR(COUNTA(TableREPipeline[RE ID]),0) -> 2 | C80: Resi + CRE pipeline
A81: Residential active | B81: =IFERROR(COUNTIF(TableREPipeline[Route],"Residential"),0) -> 1 | C81: Resi sourcer book
A82: Commercial active | B82: =IFERROR(COUNTIF(TableREPipeline[Route],"Commercial"),0) -> 1 | C82: CRE sourcer book
A83: Under contract band | B83: =IFERROR(COUNTIF(TableREPipeline[RE Stage],"LOI / PSA")+COUNTIF(TableREPipeline[RE Stage],"Diligence")+COUNTIF(TableREPipeline[RE Stage],"Closing"),0) -> 1 | C83: PSA through close
A84: Owned RE assets | B84: =IFERROR(COUNTA(TableREPortfolio[PFRE ID]),0) -> 1 | C84: RE Portfolio count
A85: RE purchased (log) | B85: =IFERROR(COUNTIF(TableREClosed[Outcome],"Purchased"),0) -> 0 | C85: Closed buys
A87: LINKS
A88: Portfolio health detail: Portfolio Active · Financial proof: Portfolio Roll-up · Standards: Core Subsidiary Structure §3/§6 · Nav: How We Run

Sheet Portal Architecture
A1: Tage VC — Portal Architecture
A2: High-level build reference from the Excel OS. Detail: Platform Spec · Cursor Brief · Data Dictionary · Core Subsidiary Structure · Portfolio Roll-up.
A4: 1 · OVERALL ARCHITECTURE
A5: Layer | B5: Responsibility | C5: Notes
A6: Frontend | B6: Role-based UI: Command Center, deal boards (VC/M&A/RE), entity/portfolio pages, SS tickets, docs | C6: Next.js + Brand & Styling Guide
A7: Backend / API | B7: Auth, RBAC, CRUD, workflows, roll-up jobs, webhooks, audit log | C7: Enforce enums + CORE/FLEX server-side
A8: Database | B8: Postgres: entities, deals, tasks, pnl, kpi, docs, tickets | C8: Seed from Excel tables
A9: Integrations | B9: QBE/Intuit, DocuSign, object storage, email/calendar, tickets | C9: Human gates on wire + capital DocuSign send
A10: Jobs / agents | B10: Monthly roll-up, SLA clocks, stale leads, draft memos | C10: Agents draft only — no silent capital actions
A12: End-to-end data flow
A13: Inbound → Deal track (VC / M&A / RE) → tasks from libraries → IC/close → issue ENT-* → Handoff → Portfolio Active → QBE monthly pack → entity_month_pnl/kpi → Portfolio Roll-up (SUM/WEIGHTED/MIN/FLAG/COUNT) → Command Center / Firm review. Docs attach at process steps; SS tickets run in parallel.
A15: 2 · CORE MODULES & NAVIGATION
A16: Nav area | B16: What users open | C16: Excel counterpart
A17: Home | B17: Command Center — funnel, portfolio health COUNT, capital pulse | C17: Command Center · Portfolio Roll-up §C–D
A18: Deal Flow · VC | B18: Pipeline, Lead Tasks, DD, Scorecard, Fin Model, Deal Desk | C18: Pipeline* · Lead Tasks* · Needs Completed* · Scorecard · Financial Model · Deal*
A19: Deal Flow · M&A | B19: Targets, tasks, scorecard, model, integration | C19: M&A* tabs
A20: Deal Flow · RE | B20: Resi/CRE pipeline, underwrite, PSA path, RE portfolio | C20: RE* tabs
A21: Portfolio | B21: Portfolio Active, Handoff, Roll-up, entity detail, Core Standard | C21: Portfolio* · Entity Master · Core Subsidiary Structure
A22: Shared Services | B22: Tickets by service, SLAs, close calendar, audits | C22: SS Operating Model · Annual Audit Master
A23: Firm | B23: Capital allocation, firm rhythm, governance | C23: Firm Operations · How We Run
A24: Documents | B24: Library by entity_id, templates, DocuSign status | C24: Document Management & Workflow
A25: Admin | B25: Users, roles, enums, task templates | C25: Data Dictionary · Brand Guide · libraries
A26: Post-close entity page tabs: Overview | Financials | CORE KPIs | FLEX KPIs | Tasks | Docs | SS tickets | Audit.
A28: 3 · ROLE-BASED ACCESS CONTROL (HIGH LEVEL)
A29: Role | B29: Can see / do | C29: Cannot (examples)
A30: Visionary | B30: Full read; capital allocation; CORE exceptions; Critical war rooms | C30: — final capital authority
A31: Partner | B31: Deal tracks; IC; thesis portfolio cos; recovery plans | C31: Change CORE standard alone
A32: Associate / VC Sourcer | B32: VC pipeline, DD, tasks, memos | C32: Wire; set Health; other tracks unless granted
A33: RE Sourcer / M&A Associate | B33: Own track boards + Command Center read | C33: Other tracks by default
A34: COO (Subsidiaries) | B34: Portfolio Active, Health, packs, SS priority, Roll-up | C34: IC approve; silent capital DocuSign
A35: Sub Lead | B35: Own entity ops, KPI inputs, Top Risk, weekly review | C35: Other entities; firm capital
A36: Service Lead (Fin/Legal/HR/IT/Mkt) | B36: Own SS queue, SLAs, QBE close (Finance) | C36: Change deal outcomes
A37: Counsel / Ops | B37: Docs, CPs, wire package, archive | C37: IC commercial decision alone
A38: Admin | B38: Users, templates, enums, seed | C38: Bypass dual-control wire
A40: 4 · KEY DATA MODELS
A41: Model | B41: Purpose | C41: Excel source
A42: entities (Entity Master) | B42: Canonical ENT-*; module; QBE key; parent; portfolio_id | C42: Entity Master
A43: leads / ma_targets / re_deals | B43: Pre-close deal objects by track | C43: Pipeline / M&A / RE Active
A44: deals | B44: VC post-IC execution (TS→wire) | C44: Deal Active/Closed
A45: tasks + task_templates | B45: Work items; spawn from process libraries | C45: *Tasks + *Process Library
A46: dd_items | B46: Diligence checklist instances | C46: Needs Completed / Completed
A47: portfolio_companies | B47: Post-close ops row; CORE KPI fields; Health | C47: Portfolio Active
A48: entity_month_pnl | B48: Monthly Core P&L by entity | C48: Portfolio Roll-up §A
A49: entity_month_kpi (CORE) | B49: Monthly CORE KPIs + roll-up method | C49: Core Structure §3
A50: entity_month_kpi_flex | B50: Industry KPIs (no portfolio money roll-up) | C50: Recruit 619 Alignment / playbooks
A51: portfolio_month_rollup / firm_month_rollup | B51: SUM / WEIGHTED / MIN_FLAG / COUNT outputs | C51: Portfolio Roll-up
A52: docs | B52: Library + DocuSign envelopes | C52: Document Management
A53: tickets | B53: Shared Services intake + SLA | C53: SS Operating Model
A54: Join: pre-close by canonical_name; post-close by entity_id. Enums exact from Data Dictionary.
A56: 5 · MAJOR WORKFLOWS
A57: Workflow | B57: Path | C57: Human gates
A58: VC source → Ready for DD | B58: Lead stages + task spawn → Advanced to DD | C58: Partner path decisions
A59: DD → IC package | B59: Checklist → scorecard + financial model | C59: IC vote
A60: VC close | B60: TS → docs → CPs → wire → Deal Closed | C60: Dual-control wire; DocuSign send
A61: M&A close | B61: LOI → QoE → SPA → Acquired → Integration | C61: LOI/IC authority; fund
A62: RE close | B62: Underwrite → offer/PSA → diligence → purchase → RE Portfolio | C62: Offer authority; wire
A63: Post-close handoff | B63: ENT-* → QBE → doc folders → Handoff Pack → Portfolio Active | C63: Partner + COO pack sign-off
A64: Monthly portfolio cycle | B64: QBE close → pack → Roll-up → Health/Top Risk → Command Center | C64: COO sets Health
A65: Health escalation | B65: Watch / At Risk / Critical per Core Structure §6 | C65: COO → Partner → Visionary by level
A66: Shared Services ticket (+ Grok/Cursor bands) | B66: Intake → diagnose AUTO/DRAFT/ESCALATE → resolve; forbid-list enforced server-side | C66: See SS Model §7; capital/Health/DocuSign capital always human
A67: Document / DocuSign | B67: Template → merge → send → webhook → /07_Signed | C67: Human send on capital docs
A68: Capital allocation review | B68: Bi-weekly view across VC / M&A / RE | C68: Visionary
A70: 6 · REUSE VS REBUILD
A71: Reuse from Excel OS (do not reinvent) | B71: Rebuild in portal software
A72: Stages, enums, process libraries, scorecard logic | B72: Multi-user auth, realtime boards, permissions
A73: CORE KPI definitions + roll-up methods (SUM/WEIGHTED/MIN/FLAG/COUNT) | B73: Monthly job engine + QBE connectors
A74: Health matrix + escalation ladder | B74: Notifications, SLA timers, mobile UX
A75: Entity Master field model | B75: Search, activity feed, concurrency
A76: Doc folder taxonomy + merge field catalog | B76: DocuSign API + secure object storage
A77: SS services, SLAs, P0–P3 priority | B77: Full ticket product UX
A78: CSV/table shapes for seed migrations | B78: Any legacy screens that fight Core Structure
A79: Brand palette + How We Run cadence | B79: Duplicate company masters or status synonyms
A80: Rule: Excel remains requirements SSOT until Cursor Brief acceptance tests pass for each feature.
A82: 7 · RECOMMENDED TECH STACK
A83: Area | B83: Recommendation
A84: Application | B84: Next.js (App Router) + TypeScript
A85: API / database | B85: Postgres + Prisma or Drizzle; REST/tRPC/server actions
A86: Auth | B86: SSO-ready auth with role claims (Auth.js / Clerk / WorkOS, etc.)
A87: Files | B87: S3-compatible storage; signed URLs
A88: Finance | B88: Intuit/QBE export or API; keep bank feed in QBE
A89: E-sign | B89: DocuSign eSignature API + webhooks
A90: Background jobs | B90: Queue worker (Inngest, BullMQ, etc.) for roll-ups and SLAs
A91: AI (optional) | B91: Constrained agent tools per Cursor Brief agent rules
A92: Observability | B92: Structured logs + immutable audit table for capital actions
A94: 8 · PHASED DEVELOPMENT ROADMAP
A95: Phase | B95: Scope | C95: Exit criteria
A96: P0 Foundation | B96: Auth/RBAC, entities (Entity Master), brand shell, Excel seed | C96: Login works; ENT-* CRUD; enums locked
A97: P1 VC Deal Flow + Home | B97: VC Pipeline, lead tasks spawn, DD, Command Center lite | C97: Associate can run a week in-app; CC counts match rules
A98: P2 Close path | B98: Scorecard, Fin Model, Deal Desk, Docs NDA + human DocuSign send | C98: IC package path live; NDA signed end-to-end
A99: P3 Portfolio | B99: Handoff, Portfolio Active, CORE KPIs, Health, monthly Roll-up job | C99: Close creates entity+portfolio; pack roll-up correct (WEIGHTED/MIN/FLAG)
A100: P4 Other tracks | B100: M&A + RE modules (separate models) | C100: Tracks run without polluting VC schema
A101: P5 Firm OS | B101: SS tickets + QBE close path, capital DocuSign, dual-control wire log, Firm Ops | C101: SLA clocks live; no wire without dual-control record
A102: P6 Harden | B102: Audit Master, agent drafts, mobile polish; Excel becomes backup SSOT only | C102: Cursor Brief acceptance tests green
A104: LINKS
A105: Build detail: Platform Spec · Cursor Brief · Data Dictionary · SS Model §7 (Grok+Cursor Ticketing)
A106: Domain rules: Core Subsidiary Structure · Portfolio Roll-up · Entity Master · Document Management
A107: Ops: How We Run · Command Center · Firm Operations · Shared Services Operating Model §7 · Recruit 619 Alignment · Brand & Styling Guide
A108: 9 · GROK + CURSOR TICKETING (SUMMARY)
A109: Full spec: Shared Services Operating Model §7. Bands: AUTO (allow-list only) · DRAFT (human approve) · ESCALATE (low confidence / high risk). Forbid-list: wires, Health, capital DocuSign send, CORE changes, unapproved external email, IC approve. All actions audit-logged with reasoning. Autonomy expands only via COO-signed allow-list promotions.
A110: Portal module: tickets + agent_runs + audit_log tables; policy engine must hard-block forbid-list regardless of model confidence.

Sheet Platform Spec
A1: Tage VC Portal — Platform Spec (Current)
A2: Product requirements for the internal portal. Excel workbook is the SSOT prototype. See also Portal Architecture + Cursor Brief.
A4: 1. PRODUCT VISION
A5: One portal for Tage VC: three deal tracks (VC Invest, M&A Buy, RE Buy) → close → Core Subsidiary operations (COO) → firm capital, Shared Services, and governance (Visionary). Operator system, not a pitch portal.
A7: 2. THREE-LAYER MODEL
A8: Layer | B8: Owner | C8: What it covers | D8: Excel SSOT tabs
A9: L1 Deal Flow | B9: Partners + Sourcers | C9: VC / M&A / RE sourcing → diligence → close | D9: Pipeline*, Deal*, M&A*, RE*, scorecards, models, libraries
A10: L2 Portfolio / Subsidiaries | B10: COO of Subsidiaries | C10: Handoff, CORE KPIs, Health, roll-up, sub playbooks | D10: Core Subsidiary Structure, Sub OS, Handoff, Portfolio Active, Portfolio Roll-up, Entity Master, Recruit 619 Alignment
A11: L3 Firm + Shared Services | B11: Visionary + COO (SS stack-rank) | C11: Command Center, capital, SS tickets/SLAs, audits, firm rhythm | D11: Command Center, Firm Operations, SS Model, Annual Audit Master, How We Run
A13: 3. PERSONAS (RBAC)
A14: Visionary · Partner · Associate/VC Sourcer · RE Sourcer · M&A Associate · COO · Sub Lead · Service Lead (Fin/Legal/HR/IT/Mkt) · Counsel/Ops · Admin. Detail can/cannot: Portal Architecture §3 + Cursor Brief.
A16: 4. MODULES (NAV + BUILD ORDER)
A17: ID | B17: Module / Nav | C17: Capabilities | D17: Excel sources
A18: M0 | B18: Identity & Admin | C18: entities, users, RBAC, enums, brand | D18: Entity Master, Data Dictionary, Brand Guide
A19: M1 | B19: Command Center (Home) | C19: Funnel counts, portfolio health COUNT, capital pulse | D19: Command Center, Portfolio Roll-up §C–D
A20: M2 | B20: Deal Flow · VC | C20: Pipeline, lead tasks, DD, scorecard, fin model, deal desk | D20: Pipeline*, Lead Tasks*, Needs Completed*, Scorecard, Financial Model, Deal*
A21: M3 | B21: Deal Flow · M&A | C21: Targets, LOI, QoE tasks, scorecard, model, integration | D21: M&A* tabs
A22: M4 | B22: Deal Flow · RE | C22: Resi/CRE pipeline, underwrite, PSA, RE portfolio | D22: RE* tabs
A23: M5 | B23: Portfolio | C23: Handoff, Portfolio Active, entity page, CORE KPIs, Health, Roll-up job | D23: Core Structure, Handoff, Portfolio Active, Roll-up
A24: M6 | B24: Shared Services | C24: Tickets P0–P3, SLAs, close calendar, audit checklists | D24: SS Operating Model, Annual Audit Master
A25: M7 | B25: Documents | C25: Library by entity_id, templates, DocuSign | D25: Document Management & Workflow
A26: M8 | B26: Firm Operations | C26: Capital allocation, firm rhythm, governance | D26: Firm Operations, How We Run
A27: M9 | B27: Automations / Agents | C27: Stage task spawn, roll-up job, SLA clocks, draft memos | D27: Cursor Brief agent rules
A29: 5. DATA MODEL (CURRENT)
A30: Table | B30: Grain | C30: Key fields / rules
A31: entities | B31: 1 / legal entity | C31: ENT-*, canonical_name, type, parent_id, industry_module, qbe_key, portfolio_id (Entity Master)
A32: leads | ma_targets | re_deals | B32: 1 / pre-close object | C32: LD-/MA-/RE-; join name until ENT issued at close
A33: deals | B33: 1 / VC execution | C33: DE-*; TS→wire stages
A34: tasks + task_templates | B34: 1 / task or library row | C34: LT/DD/DT/MT/RT; spawn from process libraries
A35: dd_items | B35: 1 / DD checklist item | C35: Archive on complete
A36: portfolio_companies | B36: 1 / post-close ops row | C36: PF-*; CORE KPI fields; Health enum
A37: entity_month_pnl | B37: entity × month | C37: Core P&L lines (Revenue…Cash)
A38: entity_month_kpi | B38: entity × month × kpi_key | C38: CORE only; method SUM|WEIGHTED|MIN_FLAG|COUNT|LIST (Core Structure §3)
A39: entity_month_kpi_flex | B39: entity × month × flex_key | C39: Never into portfolio money totals
A40: portfolio_month_rollup | B40: month | C40: SUM money; WEIGHTED % from sums; MIN runway; FLAG <12; health COUNT
A41: firm_month_rollup | B41: month | C41: Firm-only opex/cash + allocation; col F not mixed into sub cols
... A43: tickets | B43: 1 / SS ticket | C43: service, P0–P3, SLA clocks
A44: Join: pre-close canonical_name; post-close entity_id. Enums exact (Data Dictionary). Roll-up authority: Core §3 + Portfolio Roll-up How to Use.
A46: 6. MAJOR WORKFLOWS
A47: VC source→DD→IC→wire · M&A LOI→close→integration · RE underwrite→PSA→purchase · Close→ENT+Handoff+Portfolio · Monthly pack→Roll-up→Health→CC · SS tickets · DocuSign (human send on capital) · Capital allocation review. Detail: Portal Architecture §5.
A49: 7. AUTOMATION BOUNDARIES
A50: Automate: task spawn, roll-up job, QBE bank/recurring/close/pack export, SLA clocks, DocuSign status webhooks, draft memos.
A51: Human required: IC, Health judgment, wire/dual-control, DocuSign send on TS/SPA/PSA/wire docs, founder email send, CORE exceptions, capital allocation.
A53: 8. UX & BRAND
A54: Brand & Styling Guide. Pre-close: track boards. Post-close entity page: Overview | Financials | CORE KPIs | FLEX | Tasks | Docs | SS | Audit. Next action always visible. Health chips = forced enum.
A56: 9. TECH
A57: Next.js + TS · Postgres · RBAC SSO · object storage · QBE/Intuit · DocuSign · job queue · optional constrained agent. Seed CSV from Excel tables.
A59: 10. PHASES (summary)
A60: P0 Foundation (M0) → P1 VC+CC (M1–M2,M1-home) → P2 Close+Docs NDA → P3 Portfolio+Roll-up → P4 M&A/RE → P5 SS+QBE+capital DocuSign+Firm → P6 harden & Excel backup-only. Full criteria: Portal Architecture §8.
A62: LINKS: Portal Architecture · Cursor Brief · Data Dictionary · Entity Master · Core Subsidiary Structure · Portfolio Roll-up · Document Management · SS Model · Firm Operations · How We Run · Brand & Styling Guide

Sheet Cursor Brief
A1: CURSOR BUILD BRIEF — Tage VC Portal (paste into Cursor)
A2: Excel workbook = requirements SSOT. Keep enums exact. Ship modules in order. Brand: Brand & Styling Guide.
A4: ## ROLE
A5: Build the Tage VC internal portal covering Deal Flow (VC + M&A + RE), Portfolio/Core Subsidiary ops, Shared Services, Firm Operations, and Document/DocuSign workflows.
A7: ## READ FIRST (in this order)
A8: 1. Portal Architecture — high-level map, reuse vs rebuild, phases
A9: 2. Platform Spec — L1–L3, modules M0–M9, data model, automation boundaries
A10: 3. Data Dictionary — enums
A11: 4. Entity Master — ENT-* fields
A12: 5. Core Subsidiary Structure §3 — CORE KPI definitions + roll-up methods; §6 Health
A13: 6. Portfolio Roll-up — How to Use + SUM/WEIGHTED/MIN/FLAG/COUNT formulas
A14: 7. Document Management & Workflow — DocuSign human-send rules
... A77: Portal Architecture · Platform Spec · SS Model §7 Grok+Cursor Ticketing · Data Dictionary · Entity Master · Core Structure · Portfolio Roll-up · Document Management · How We Run · Brand & Styling Guide

Sheet Data Dictionary
A1: Tage VC Platform — Data Dictionary (Source of Truth for Build)
A2: Entities, fields, enums, and relationships. Spreadsheet tables map 1:1 to future DB models.
A4: Entity | B4: Sheet / Table | C4: Primary key | D4: Foreign keys | E4: Core fields | F4: Lifecycle
A5: Company | B5: Canonical name across all sheets | C5: company_id (slug) | D5: — | E5: name, website, sector, path, location | F5: Created at first lead
A6: Lead | B6: Pipeline Active / Closed · TablePipeline | C6: LD-### | D6: company_id | E6: source, stage, priority, owner, thesis_fit, score, check_size, next_action | F6: Active→Done
A7: LeadTask | B7: Lead Tasks · TableLeadTasks | C7: LT-### | D7: lead_id, company | E7: process_stage, task, status, owner, due
A8: DdItem | B8: Needs Completed / Completed · TableActive | C8: DD-### | D8: company as Entity | E8: category, item, priority, status, owner, evidence | F8: Open→Completed archive
A9: Deal | B9: Deal Active / Closed · TableDeal | C9: DE-### | D9: lead_id, company | E9: exec_stage, instrument, premoney, check, ownership, ts dates | F9: IC→Wired/Closed
A10: DealTask | B10: Deal Tasks · TableDealTasks | C10: DT-### | D10: deal_id | E10: process_stage, task, status, owner | F10: Active→Done
A11: Scorecard | B11: Deal Scorecard | C11: scorecard_id | D11: company, lead_id | E11: pillar weights/scores, recommendation, IC decision | F11: Versioned per IC
A12: FinancialModel | B12: Financial Model | C12: model_id | D12: company, deal_id | E12: ARR, UE, burn, growth path, MOIC/IRR | F12: Snapshot at IC + close
A13: HandoffPack | B13: Portfolio Handoff | C13: PH-### | D13: deal_id, company | E13: thesis, KPIs, checklist, 30-day plan | F13: At wire
A14: PortfolioCompany | B14: Portfolio Active · TablePortfolio | C14: PF-### | D14: deal_id, company | E14: ARR, burn, runway, health, COO, board lead | F14: Post-close forever
A16: KEY ENUMS (do not invent synonyms in code)
A17: pipeline_stage | B17: Sourced | Screened | First Call | Partner Meeting | Deep Dive Prep | Ready for DD
A18: lead_outcome | B18: Advanced to DD | Pass | Lost | Withdrawn | Nurture archive
A19: dd_status | B19: Not Started | In Progress | Blocked | Waiting on Company | Completed
A20: priority | B20: Critical | High | Medium | Low
A21: exec_stage | B21: IC Approved | Term Sheet | Confirmatory DD | Docs Drafting | Signing Ready | Closing Conditions | Wired / Closed | Post-Close
A22: deal_outcome | B22: Wired / Closed | Dead | Paused
A23: thesis_fit | B23: Strong | Medium | Weak | Unknown
A24: path | B24: Launch | Partner | Exit
A25: portfolio_health | B25: On Track | Watch | At Risk | Critical
A27: JOIN RULE
A28: company.name is the human join key until company_id exists. Never rename mid-flight without updating all child records.
A30: M&A ENTITIES
A31: MATarget | B31: M&A Pipeline · TableMAPipeline | C31: MA-### | D31: company | E31: deal_type, ma_stage, EV, revenue, EBITDA, exclusivity | F31: Active→Acquired/Walked
A32: MATask | B32: M&A Tasks · TableMATasks | C32: MT-### | D32: ma_id | E32: process_stage, task, status | F32: Active→Done
A33: ma_stage | B33: Sourced | CIM Review | Management Meeting | IOI / Indication | LOI / Exclusivity | Confirmatory DD | Definitive Docs | Closing | Integration
A34: ma_outcome | B34: Acquired | Walked | Lost | Paused
A35: ma_deal_type | B35: Platform acquisition | Add-on / roll-up | Merger | Asset purchase | Other
A37: RE ENTITIES
A38: REDeal | B38: RE Pipeline · TableREPipeline | C38: RE-### | D38: — | E38: route, asset_type, stage, ask, offer, NOI, sourcer | F38: Active→Purchased/Passed
A39: RETask | B39: RE Tasks · TableRETasks | C39: RT-### | D39: re_id | E39: route, stage, task, status | F39: Active→Done
A40: REAsset | B40: RE Portfolio · TableREPortfolio | C40: PFRE-### | D40: re_id | E40: basis, NOI, occ, health, PM | F40: Post-close
A41: re_route | B41: Residential | Commercial
A42: re_stage | B42: Sourced | Screen | Underwriting | Offer | LOI / PSA | Diligence | Closing | Onboard
A43: re_outcome | B43: Purchased | Passed | Lost | Paused
A45: DATA MODEL & ROLL-UPS (PORTAL SCHEMA)
A46: Table | B46: Grain | C46: Key fields | D46: Roll-up / notes
A47: entities | B47: 1 row / legal entity | C47: entity_id, canonical_name, type, parent_id, module, qbe_key | D47: Entity Master tab
A48: entity_month_pnl | B48: entity × month | C48: revenue, cogs, opex, ebitda, burn, cash | D48: SUM → portfolio_month; + firm → consolidated
A49: entity_month_kpi | B49: entity × month × kpi_key | C49: kpi_key, value, unit | D49: SUM or WEIGHTED or MIN per kpi_key rules
A50: portfolio_month_rollup | B50: month | C50: summed $; health counts | D50: Portfolio Roll-up + Command Center
A51: firm_month_rollup | B51: month | C51: firm opex, firm cash, allocation % | D51: Firm Operations review
A52: docs | B52: 1 row / document | C52: doc_id, entity_id, envelope_id, uri, status | D52: Document Management tab
A53: Hierarchy: ENT-FIRM → Subsidiaries / RE entities → monthly facts → Portfolio Active display → Firm KPIs
A54: LINKS: Entity Master · Portfolio Roll-up · Document Management · Cursor Brief

Sheet Entity Master
A1: Tage VC — Entity Master | Canonical Registry
A2: Single identity for every legal entity (ENT-*). Join key after close. Pre-close deals use canonical_name until ENT issued.
A4: entity_id | B4: canonical_name | C4: legal_name | D4: entity_type | E4: track_origin | F4: parent_entity_id | G4: status | H4: industry_module | I4: qbe_class_or_company | J4: portfolio_id | K4: coo_owner | L4: board_lead | M4: close_date | N4: notes
A5: ENT-FIRM | B5: Tage Venture Capital | C5: Tage Venture Capital LLC | D5: Firm | E5: Firm | F5: — | G5: Active | H5: Firm | I5: QBE: Tage Firm | J5: — | K5: — | L5: Visionary | N5: Parent firm entity
A6: ENT-001 | B6: Sample Closed Co | C6: Sample Closed Co Inc. | D6: Subsidiary | E6: VC Invest | F6: ENT-FIRM | G6: Active | H6: SaaS | I6: QBE: Sample Closed Co | J6: PF-001 | K6: COO — Ops Lead | L6: Partner | M6: 45993 | N6: Launch path
A7: ENT-002 | B7: Instant NDA | C7: Instant NDA LLC | D7: Subsidiary | E7: VC Invest | F7: ENT-FIRM | G7: Active | H7: SaaS | I7: QBE: Instant NDA | J7: PF-002 | K7: COO — Ops Lead | L7: Partner | M7: 45809 | N7: Legal tech
A8: ENT-RE-001 | B8: Sample Indy SFR | C8: Tage RE Holdco SPV 1 | D8: RE Asset Entity | E8: RE Buy | F8: ENT-FIRM | G8: Active | H8: Real Estate Resi | I8: QBE: RE Indy SFR | J8: PFRE-001 | K8: PM — Resi | L8: Partner | M8: 45915 | N8: Residential asset
A9: ENT-R619 | B9: Recruit 619 | C9: Recruit 619 LLC | D9: Subsidiary | E9: VC Invest | F9: ENT-FIRM | G9: Active | H9: Recruiting | I9: QBE: Recruit 619 | J9: PF-R619 | K9: COO — Ops Lead | L9: Partner | N9: Canonical brand Recruit 619 — not 619 Recruiting
A10: ENTITY TYPES
A11: Firm — Tage parent / management company
A12: Subsidiary — operating company (VC Launch/Partner or M&A control)
A13: RE Asset Entity — property SPV or propco
A14: Holdco — intermediate holding company (optional)
A15: Pipeline-only — not yet an owned entity (pre-close); use temporary name until ENT- issued at wire
A17: INDUSTRY MODULES (on top of core subsidiary structure)
A18: Module | B18: Extra KPI pack | C18: Extra playbooks
A19: SaaS / Software | B19: ARR, NRR, CAC, LTV, logo churn | C19: GTM, product ops
A20: Recruiting / Staffing | B20: Placements, GP per desk, fill time | C20: Desk ops, client SLAs
A21: Services / Ops | B21: Utilization, backlog, gross margin by job | C21: Delivery QA
A22: Real Estate Resi | B22: Occ, rent roll, yield on basis, repairs | C22: PM turn process
A23: Real Estate CRE | B23: NOI, occupancy, WALT, capex | C23: Lease abstract ops
A25: RULES
A26: 1. canonical_name never changes without updating all child records (pipelines, portfolio, docs).
A27: 2. At close: issue entity_id, link portfolio_id, create QBE class/company, create Doc library folder.
A28: 3. parent_entity_id defaults to ENT-FIRM unless Holdco structure.
A29: 4. Roll-ups only include status=Active subsidiaries/assets (or period filter).
A31: LINKS: Portfolio Roll-up · Data Dictionary · Portfolio Active · RE Portfolio · Subsidiary Operating System · Document Management & Workflow

Sheet Pipeline Active
A1: Tage VC — VC Pipeline Active | Z1: Sourced
A2: One row per company. Close to Pipeline Closed when Ready for DD or Pass. | Z2: Screened
Z3: First Call
A4: Summary | Z4: Partner Meeting
A5: Active leads | B5: =COUNTA(TablePipeline[Lead ID]) -> 5 | C5: Ready for DD | D5: =COUNTIF(TablePipeline[Pipeline Stage],"Ready for DD") -> 1 | E5: This week next actions | F5: =COUNTIFS(TablePipeline[Next Action Date],">="&TODAY(),TablePipeline[Next Action Date],"<"&TODAY()+7) -> 0 | G5: Strong fit | H5: =COUNTIF(TablePipeline[Thesis Fit],"Strong") -> 2 | Z5: Deep Dive Prep
Z6: Ready for DD
A7: Lead ID | B7: Added Date | C7: Company | D7: Website | E7: Sector | F7: Source | G7: Source Detail | H7: Pipeline Stage | I7: Priority | J7: Owner | K7: Next Action | L7: Next Action Date | M7: Thesis Fit | N7: Raise Stage | O7: Check Size ($k) | P7: Location | Q7: Last Touch | R7: Score (1-5) | S7: Notes | Z7: Critical
A8: LD-001 | B8: 46091 | C8: Acme AI | D8: acme.ai | E8: AI Infra | F8: Warm intro | G8: Jane Doe (portfolio CEO) | H8: Partner Meeting | I8: Critical | J8: Partner | K8: Partner debrief + go/no-go to DD | L8: 46105 | M8: Strong | N8: Seed | O8: 1500 | P8: SF Bay | Q8: 46101 | R8: 5 | S8: Strong team; competitive process — move fast | Z8: High
A9: LD-002 | B9: 46093 | C9: Nova Health | D9: novahealth.io | E9: Healthtech | F9: Inbound | G9: Deck via website | H9: First Call | I9: High | J9: Associate | K9: Founder call + send process email | L9: 46106 | M9: Medium | N9: Series A | O9: 3000 | P9: NYC | Q9: 46099 | R9: 3 | S9: Need clarity on regulatory path | Z9: Medium
A10: LD-003 | B10: 46096 | C10: Beacon Robotics | D10: beaconrobotics.com | E10: Robotics | F10: Event | G10: TechCrunch Disrupt | H10: Screened | I10: Medium | J10: Associate | K10: Desk research + thesis fit memo | L10: 46108 | M10: Unknown | N10: Seed | O10: 1000 | P10: Boston | Q10: 46096 | R10: 3 | S10: Hardware-heavy; confirm fund appetite | Z10: Low
A11: LD-004 | B11: 46099 | C11: Ledgerly | D11: ledgerly.co | E11: Fintech | F11: Cold outreach | G11: Associate outbound | H11: Sourced | I11: Low | J11: Associate | K11: Send intro note; request deck | L11: 46107 | M11: Unknown | N11: Pre-Seed | O11: 500 | P11: Remote | Q11: 46099 | R11: 2 | Z11: Inbound
A12: LD-005 | B12: 46089 | C12: Orbit Data | D12: orbitdata.com | E12: Data/Analytics | F12: Scout | G12: Scout network — Alex R. | H12: Ready for DD | I12: Critical | J12: Partner | K12: Hand off to DD tracker + open data room | L12: 46104 | M12: Strong | N12: Series A | O12: 4000 | P12: Austin | Q12: 46102 | R12: 5 | S12: Partner approved to full DD — spawn DD checklist | Z12: Warm intro
Z13: Cold outreach
Z14: Event
Z15: Scout
Z16: Portfolio
Z17: LP referral
Z18: Other
Z19: Strong
Z20: Medium
Z21: Weak
Z22: Unknown
Z23: Pre-Seed
Z24: Seed
... Z34: Completed

Sheet Pipeline Closed
A1: Tage VC — VC Pipeline Closed (Log) | Z1: Advanced to DD
A2: Leads that Advanced to DD, Passed, or Lost. Keep for source ROI and learning. | Z2: Pass
Z3: Lost
A4: Closed count | B4: =COUNTA(TablePipelineClosed[Lead ID]) -> 2 | C4: Advanced to DD | D4: =COUNTIF(TablePipelineClosed[Outcome],"Advanced to DD") -> 1 | E4: Passed | F4: =COUNTIF(TablePipelineClosed[Outcome],"Pass") -> 1 | Z4: Withdrawn
Z5: Nurture archive
A6: Lead ID | B6: Added Date | C6: Company | D6: Website | E6: Sector | F6: Source | G6: Source Detail | H6: Final Stage | I6: Priority | J6: Owner | K6: Thesis Fit | L6: Raise Stage | M6: Check Size ($k) | N6: Location | O6: Score (1-5) | P6: Outcome | Q6: Outcome Reason | R6: Date Closed | S6: Closed By | T6: Notes
A7: LD-000 | B7: 46042 | C7: Example Pass Co | D7: examplepass.com | E7: Consumer | F7: Inbound | G7: Cold deck | H7: Screened | I7: Low | J7: Associate | K7: Weak | L7: Seed | M7: 750 | N7: LA | O7: 1 | P7: Pass | Q7: Outside thesis — consumer social | R7: 46050 | S7: Associate | T7: Polite pass email sent
A8: LD-010 | B8: 46054 | C8: Example Advanced Co | D8: exampledd.com | E8: B2B SaaS | F8: Warm intro | G8: LP intro | H8: Ready for DD | I8: Critical | J8: Partner | K8: Strong | L8: Series A | M8: 2500 | N8: SF Bay | O8: 5 | P8: Advanced to DD | Q8: Partner approved; DD checklist opened | R8: 46073 | S8: Partner | T8: Link company name to Needs Completed Entity

Sheet Lead Tasks Active
A1: Tage VC — Lead Tasks Active | Z1: Sourced
A2: Pre-DD tasks per company. Move done rows to Lead Tasks Done. | Z2: Screened
Z3: First Call
A4: Open tasks | B4: =COUNTA(TableLeadTasks[Task ID]) -> 4 | C4: Critical / High | D4: =COUNTIFS(TableLeadTasks[Priority],"Critical")+COUNTIFS(TableLeadTasks[Priority],"High") -> 4 | E4: Blocked | F4: =COUNTIF(TableLeadTasks[Status],"Blocked") -> 0 | Z4: Partner Meeting
Z5: Deep Dive Prep
A6: Task ID | B6: Added Date | C6: Company | D6: Lead ID | E6: Process Stage | F6: Task | G6: Priority | H6: Status | I6: Owner | J6: Due Date | K6: Notes | L6: Evidence / Link | Z6: Ready for DD
A7: LT-001 | B7: 46101 | C7: Acme AI | D7: LD-001 | E7: Partner Meeting | F7: Write 1-pager + recommendation for partner | G7: Critical | H7: In Progress | I7: Associate | J7: 46104 | K7: Include comps and kill criteria | Z7: Sourcing Ops
A8: LT-002 | B8: 46099 | C8: Nova Health | D8: LD-002 | E8: First Call | F8: Prep call agenda; review deck + metrics | G8: High | H8: Not Started | I8: Associate | J8: 46106 | Z8: Critical
A9: LT-003 | B9: 46096 | C9: Beacon Robotics | D9: LD-003 | E9: Screened | F9: Thesis fit screen (stage, sector, geo, check size) | G9: Critical | H9: In Progress | I9: Associate | J9: 46108 | K9: Hardware may be edge of mandate | Z9: High
A10: LT-004 | B10: 46102 | C10: Orbit Data | D10: LD-005 | E10: Ready for DD | F10: Handoff: open DD checklist + request data room | G10: Critical | H10: Not Started | I10: Partner | J10: 46104 | K10: Match Entity name on Needs Completed | Z10: Medium
Z11: Low
Z12: Not Started
Z13: In Progress
Z14: Blocked
Z15: Completed

Sheet Lead Tasks Done
A1: Tage VC — Lead Tasks Done (Log)
A2: Completed evaluation tasks. Paste from Lead Tasks Active; set Date Completed.
A4: Done count | B4: =COUNTA(TableLeadTasksDone[Task ID]) -> 1
A6: Task ID | B6: Added Date | C6: Company | D6: Lead ID | E6: Process Stage | F6: Task | G6: Priority | H6: Status | I6: Owner | J6: Due Date | K6: Notes | L6: Evidence / Link | M6: Date Completed | N6: Completed By
A7: LT-000 | B7: 46058 | C7: Example Advanced Co | D7: LD-010 | E7: Screened | F7: Thesis fit screen (stage, sector, geo, check size) | G7: Critical | H7: Completed | I7: Associate | J7: 46059 | K7: Passed thesis screen | M7: 46059 | N7: Associate

Sheet Lead Process Library
A1: Tage VC — Lead Process Library
A2: Copy into Lead Tasks Active when a company enters a stage.
A4: Lib ID | B4: Process Stage | C4: Task | D4: Default Priority | E4: Owner Role | F4: What Good Looks Like
A5: LS-01 | B5: Sourced | C5: Log lead with source, sector, raise stage, owner | D5: Critical | E5: Associate | F5: Complete Pipeline Active row; unique Lead ID
A6: LS-02 | B6: Sourced | C6: Capture deck / one-pager / website in Evidence | D6: High | E6: Associate | F6: Materials linked same day as intake
A7: LS-03 | B7: Sourced | C7: Acknowledge inbound or thank referrer within 48h | D7: High | E7: Associate | F7: Referrer loop closed; founder knows next step
A8: LS-04 | B8: Sourced | C8: Outbound: personalized first touch + follow-up plan | D8: Medium | E8: Associate | F8: 2–3 touch sequence scheduled
A9: LS-05 | B9: Screened | C9: Thesis fit screen (stage, sector, geo, check size) | D9: Critical | E9: Associate | F9: Pass/fail vs fund mandate before deep time
A10: LS-06 | B10: Screened | C10: Quick market map: category, comps, timing | D10: High | E10: Associate | F10: 1-page view of space and positioning
A11: LS-07 | B11: Screened | C11: Team skim: founders LinkedIn, prior companies, signals | D11: High | E11: Associate | F11: Notable strengths/red flags noted
A12: LS-08 | B12: Screened | C12: Traction skim: revenue/users/growth if available | D12: High | E12: Associate | F12: Metrics logged; holes listed for call
A13: LS-09 | B13: Screened | C13: Decide: First Call / Pass / Nurture — update Stage | D13: Critical | E13: Associate | F13: Explicit decision + reason in Notes
A14: LS-10 | B14: Screened | C14: If Pass: send polite decline; close Pipeline row | D14: High | E14: Associate | F14: Outcome + reason on Pipeline Closed
A15: LS-11 | B15: First Call | C15: Prep call agenda; review deck + open questions | D15: High | E15: Associate | F15: Agenda covers problem, product, GTM, ask
... A34: LS-30 | B34: Sourcing Ops | C34: Stale lead sweep (no touch >14 or 30 days) | D34: High | E34: Associate | F34: Advance, nurture, or close — no zombie rows

Sheet Pipeline Notes
A1: Tage VC — Pipeline Notes
A3: Purpose
A4: Cover everything before formal due diligence: source leads, screen against thesis, run first conversations, partner review, then hand off to the DD tracker (Needs Completed).
A6: Sheet map
A7: Pipeline Active — one row per live company (funnel CRM).
A8: Pipeline Closed — Advanced to DD / Pass / Lost / Withdrawn (source ROI + learning).
A9: Lead Tasks Active — evaluation process tasks tied to Company + Lead ID.
A10: Lead Tasks Done — completed eval task archive.
A11: Lead Process Library — 30 standard sourcing/eval steps by stage.
A12: Pipeline Notes — this guide. Links to DD sheets: Needs Completed / Completed / Checklist Library.
A14: Funnel stages (Pipeline Stage)
A15: 1. Sourced — logged, materials requested, first touch.
... A44: Keep enum values exact (dropdowns) so scripts do not fork on synonyms.
A46: Last built | B46: 2026-03-22 — lead pipeline + pre-DD process

Sheet Needs Completed
A1: Tage VC — DD Needs Completed (Active) | Z1: Critical | AA1: Pre-Seed
A2: Open queue — move finished rows to Completed. Blue = inputs. | Z2: High | AA2: Seed
Z3: Medium | AA3: Series A
A4: Summary | Z4: Low | AA4: Series B
A5: Open items | B5: =COUNTA(TableActive[ID]) -> 6 | C5: Critical / High | D5: =COUNTIFS(TableActive[Priority],"Critical")+COUNTIFS(TableActive[Priority],"High") -> 6 | E5: Blocked | F5: =COUNTIF(TableActive[Status],"Blocked") -> 1 | G5: Entities | H5: {=IFERROR(SUMPRODUCT((TableActive[Entity]<>"")/COUNTIFS(TableActive[Entity],TableActive[Entity]&"")),0)} -> 2 | Z5: Not Started | AA5: Series C+
Z6: In Progress | AA6: Growth
A7: ID | B7: Added Date | C7: Entity | D7: Category | E7: Checklist Item | F7: Priority | G7: Status | H7: Owner | I7: Due Date | J7: Deal Stage | K7: Notes | L7: Evidence / Link | Z7: Blocked | AA7: Bridge
A8: DD-001 | B8: 46101 | C8: Acme AI | D8: Team | E8: Founder backgrounds, prior exits/failures, domain expertise | F8: Critical | G8: In Progress | H8: Partner | I8: 46109 | J8: Seed | K8: Reference calls scheduled with 2 prior co-founders | Z8: Waiting on Company | AA8: Other
A9: DD-002 | B9: 46101 | C9: Acme AI | D9: Market | E9: TAM / SAM / SOM and bottom-up market sizing | F9: High | G9: Not Started | H9: Associate | I9: 46116 | J9: Seed | Z9: Completed
A10: DD-003 | B10: 46101 | C10: Acme AI | D10: Product | E10: MVP / product demo; roadmap and tech stack review | F10: High | G10: Not Started | H10: Associate | I10: 46114 | J10: Seed | Z10: Team
A11: DD-004 | B11: 46099 | C11: Nova Health | D11: Legal | E11: Cap table, incorporation docs, shareholder agreements | F11: Critical | G11: Blocked | H11: Counsel | I11: 46106 | J11: Series A | K11: Waiting on data room access from founder | Z11: Market
A12: DD-005 | B12: 46099 | C12: Nova Health | D12: Financials | E12: Historical financials, burn rate, runway, use of funds | F12: Critical | G12: In Progress | H12: Associate | I12: 46111 | J12: Series A | K12: Received P&L through Feb; need cash flow bridge | Z12: Product
A13: DD-006 | B13: 46099 | C13: Nova Health | D13: Traction | E13: CAC, LTV, retention/churn, pipeline and concentration | F13: High | G13: Not Started | H13: Associate | I13: 46117 | J13: Series A | Z13: Traction
Z14: Financials
Z15: Legal
Z16: Tax
Z17: HR
Z18: IT / Security
Z19: Assets
Z20: Risk

Sheet Completed
A1: Tage VC — DD Completed (Log)
A2: Archive log — paste finished rows; set Date Completed.
A4: Completed count | B4: =COUNTA(TableCompleted[ID]) -> 1 | C4: Entities closed (distinct) | D4: {=IFERROR(SUMPRODUCT((TableCompleted[Entity]<>"")/COUNTIFS(TableCompleted[Entity],TableCompleted[Entity]&"")),0)} -> 1
A6: ID | B6: Added Date | C6: Entity | D6: Category | E6: Checklist Item | F6: Priority | G6: Status | H6: Owner | I6: Due Date | J6: Deal Stage | K6: Notes | L6: Evidence / Link | M6: Date Completed | N6: Completed By
A7: DD-000 | B7: 46063 | C7: Example Co | D7: Legal | E7: Confirm Delaware C-Corp formation and good standing | F7: Critical | G7: Completed | H7: Counsel | I7: 46068 | J7: Seed | K7: Certificate of good standing on file | M7: 46067 | N7: Counsel

Sheet Checklist Library
A1: Tage VC — DD Checklist Library
A2: Master list — copy items into Needs Completed per deal.
A4: Lib ID | B4: Category | C4: Checklist Item | D4: Default Priority | E4: Typical Stages | F4: What Good Looks Like / Notes
A5: LIB-01 | B5: Team | C5: Founder backgrounds, prior exits/failures, domain expertise | D5: Critical | E5: All | F5: Relevant operating or technical experience; referenceable track record
A6: LIB-02 | B6: Team | C6: Co-founder dynamics, equity split fairness, vesting & roles | D6: Critical | E6: Pre-Seed–A | F6: 4-year vest / 1-year cliff standard; clear decision rights
A7: LIB-03 | B7: Team | C7: Key hires plan, org chart, ability to recruit/retain | D7: High | E7: Seed+ | F7: Credible 12–18 mo hiring plan matched to use of funds
A8: LIB-04 | B8: Team | C8: Founder references (ex-colleagues, investors, customers) | D8: Critical | E8: All | F8: At least 3 independent references; probe integrity and grit
A9: LIB-05 | B9: Team | C9: Advisor / board composition and value-add | D9: Medium | E9: Seed+ | F9: Relevant domain advisors; no vanity-only boards
A10: LIB-06 | B10: Market | C10: TAM / SAM / SOM and bottom-up market sizing | D10: Critical | E10: All | F10: Bottom-up preferred; $1B+ path for classic VC
A11: LIB-07 | B11: Market | C11: Problem severity, urgency, and willingness to pay | D11: Critical | E11: Pre-Seed–A | F11: Evidence from customers, not only founder narrative
A12: LIB-08 | B12: Market | C12: Competitive landscape, substitutes, SWOT | D12: High | E12: All | F12: Clear differentiation vs direct and indirect competitors
A13: LIB-09 | B13: Market | C13: Market timing / why now (tech, regulation, behavior) | D13: High | E13: All | F13: Structural tailwind, not a fad
A14: LIB-10 | B14: Market | C14: Regulatory / industry structure risks | D14: High | E14: All | F14: Licenses, compliance path, policy exposure mapped
A15: LIB-11 | B15: Product | C15: MVP / product demo; current state vs roadmap | D15: Critical | E15: Pre-Seed–A | F15: Working product; roadmap prioritized by customer value
... A52: LIB-48 | B52: Legal | C52: Data room completeness vs request list; open DD Qs log | D52: High | E52: All | F52: Tracked open items; no silent gaps at IC

Sheet Notes
A1: Tage VC — Notes
A3: Purpose
A4: Track due-diligence work across deals (entities). Keep only open work on Needs Completed. Archive finished work on Completed for logging and audit. Use Checklist Library as the reusable master list when spinning up a new deal.
A6: Sheet map
A7: Needs Completed — live queue of open DD tasks (filter by Entity, Priority, Status, Owner).
A8: Completed — immutable-ish log. Paste finished rows here; set Date Completed + Completed By. Never delete history.
A9: Checklist Library — 48 standard VC DD items across Team, Market, Product, Traction, Financials, Tax, Legal, HR, IT/Security, Assets, Risk.
A10: Notes — this page (method, workflow, Cursor automation hints).
A12: Recommended workflow
A13: 1. Thesis screen first (LIB-45): stage, geo, sector, check size. Kill misfits before deep hours.
A14: 2. New deal: filter Library by stage → copy items into Needs Completed → set Entity, Added Date, Owner, Due Date, unique ID (DD-###).
A15: 3. Weight by stage: Pre-Seed/Seed = Team + Market + Product + basic Legal/Financial hygiene. Series A+ = add Traction unit economics, deeper Financials, Legal, HR, Security.
... A53: Common pillars also include traction, moat, and explicit risk assessment frameworks used by institutional VCs.
A55: Last built | B55: 2026-03-22 — initial VC checklist workbook

Sheet Deal Scorecard
A1: Tage VC — Deal Scorecard
A2: One scorecard per serious deal. Score 1–5. Weighted total drives IC go/no-go. Blue = inputs.
A4: DEAL IDENTITY
A5: Company | B5: Orbit Data | C5: Lead ID | D5: LD-005
A6: Path (Launch/Partner/Exit) | B6: Partner | C6: Raise stage | D6: Series A
A7: Sector | B7: Data/Analytics | C7: Scorer | D7: Partner
A8: Score date | B8: 46103 | C8: IC date | D8: 46109
A10: WEIGHTED SCORE (1=weak … 5=exceptional)
A11: Pillar | B11: Weight | C11: Score 1-5 | D11: Weighted | E11: Evidence / why
A12: Team / founders | B12: 0.2 | C12: 5 | D12: =B12*C12 -> 1 | E12: Prior exit + domain depth
A13: Market size & timing | B13: 0.15 | C13: 4 | D13: =B13*C13 -> 0.6 | E13: Bottom-up SAM credible
A14: Product / moat | B14: 0.15 | C14: 4 | D14: =B14*C14 -> 0.6 | E14: Data network effects early
A15: Traction / unit economics | B15: 0.2 | C15: 4 | D15: =B15*C15 -> 0.8 | E15: NRR >110%, CAC payback <12m
A16: Deal terms / ownership | B16: 0.1 | C16: 3 | D16: =B16*C16 -> 0.3 | E16: Competitive; still 10%+ path
A17: Tage thesis / path fit | B17: 0.1 | C17: 5 | D17: =B17*C17 -> 0.5 | E17: Operator leverage clear
A18: Risk / complexity | B18: 0.1 | C18: 3 | D18: =B18*C18 -> 0.3 | E18: Moderate concentration risk
A19: TOTAL | B19: =SUM(B12:B18) -> 1 | D19: =SUM(D12:D18) -> 4.1 | E19: =IF(ABS(B19-1)>0.001,"FIX WEIGHTS TO 100%","Weights OK") -> Weights OK
A21: DECISION
A22: Score / 5 | B22: =D19 -> 4.1
A23: Recommendation | B23: =IF(B22>=4,"Strong advance",IF(B22>=3.25,"Advance with conditions",IF(B22>=2.5,"Watch / more work","Pass"))) -> Strong advance
A24: IC decision | B24: Advance
A25: Conditions / kill criteria | B25: Confirm top-3 customer refs; ownership ≥10% post-money
A27: UPSIDE FRAME
A28: Base case | B28: Category leader; strategic exit 5–7y
A29: Bull case | B29: Multi-vertical platform; $100m+ ARR path
A30: Bear case | B30: Niche stall; secondary only
A31: Tage value-add | B31: GTM, recruiting, partnerships, board ops
A33: 5=top decile · 4=strong · 3=ok · 2=weak · 1=red flag. Risk: 5=clean, 1=severe. Launch weights Team/Market; Partner Traction/Terms; Exit Risk/Terms.

Sheet Financial Model
A1: Tage VC — Financial Model
A2: Per-deal model. Blue = company/assumptions inputs. Links to scorecard judgment; does not replace full quality of earnings.
A4: COMPANY & ROUND
A5: Company | B5: Orbit Data
A6: Instrument | B6: Priced Equity
A7: Pre-money ($m) | B7: 45
A8: Raise size ($m) | B8: 12
A9: Tage check ($m) | B9: 4
A10: Post-money ($m) | B10: =B7+B8 -> 57
A11: Tage ownership % | B11: =IFERROR(B9/B10,0) -> 0.070175439
A12: Option pool post % | B12: 0.1
A14: TRACTION & UNIT ECONOMICS (TTM / current)
A15: ARR ($k) | B15: 3200
A16: ARR growth YoY | B16: 0.85
A17: Gross margin | B17: 0.78
A18: Net revenue retention | B18: 1.15
A19: Logo churn (annual) | B19: 0.08
A20: CAC ($) | B20: 18000
A21: LTV ($) | B21: 95000
A22: LTV / CAC | B22: =IFERROR(B21/B20,0) -> 5.2777778
A23: CAC payback (months) | B23: 11
A24: Gross burn ($k/mo) | B24: 280
A25: Net burn ($k/mo) | B25: 140
A26: Cash ($k) | B26: 2100
A27: Runway months (pre-round) | B27: =IFERROR(B26/B25,0) -> 15
A28: Runway months (post Tage+round approx) | B28: =IFERROR((B26+B8*1000)/B25,0) -> 100.71429
A30: FORWARD ARR PATH ($k)
A31: Year | B31: 0 (now) | C31: 1 | D31: 2 | E31: 3 | F31: 4 | G31: 5
A32: Growth rate | B32: — | C32: 0.7 | D32: 0.55 | E32: 0.4 | F32: 0.3 | G32: 0.25
A33: ARR ($k) | B33: =B15 -> 3200 | C33: =B33*(1+C32) -> 5440 | D33: =C33*(1+D32) -> 8432 | E33: =D33*(1+E32) -> 11804.8 | F33: =E33*(1+F32) -> 15346.24 | G33: =F33*(1+G32) -> 19182.8
A35: RETURNS (simplified ownership held to exit)
A36: Exit year | B36: 5
A37: Exit ARR multiple | B37: 10
A38: Exit ARR ($k) | B38: =G33 -> 19182.8
A39: Exit enterprise value ($m) | B39: =B38*B37/1000 -> 191.828
A40: Dilution to exit (remaining ownership factor) | B40: 0.7
A41: Tage ownership at exit | B41: =B11*B40 -> 0.049122807
A42: Tage proceeds ($m) | B42: =B39*B41 -> 9.4231298
A43: MOIC | B43: =IFERROR(B42/B9,0) -> 2.3557825
A44: Approx gross IRR (simple) | B44: =IFERROR((B43)^(1/B36)-1,0) -> 0.18693527
A46: SENSITIVITY — Exit multiple vs ARR Y5 ($m EV)
A47: ARR Y5 \ Mult | B47: 6 | C47: 8 | D47: 10 | E47: 12 | F47: 15
A48: 0.7 | B48: =$G$33*B$47/1000*A48 -> 80.56776 | C48: =$G$33*C$47/1000*A48 -> 107.42368 | D48: =$G$33*D$47/1000*A48 -> 134.2796 | E48: =$G$33*E$47/1000*A48 -> 161.13552 | F48: =$G$33*F$47/1000*A48 -> 201.4194
A49: 1 | B49: =$G$33*B$47/1000*A49 -> 115.0968 | C49: =$G$33*C$47/1000*A49 -> 153.4624 | D49: =$G$33*D$47/1000*A49 -> 191.828 | E49: =$G$33*E$47/1000*A49 -> 230.1936 | F49: =$G$33*F$47/1000*A49 -> 287.742
A50: 1.3 | B50: =$G$33*B$47/1000*A50 -> 149.62584 | C50: =$G$33*C$47/1000*A50 -> 199.50112 | D50: =$G$33*D$47/1000*A50 -> 249.3764 | E50: =$G$33*E$47/1000*A50 -> 299.25168 | F50: =$G$33*F$47/1000*A50 -> 374.0646
A52: WHAT TO LOOK FOR (UPSIDE FILTERS)
A53: Filter | B53: Healthy signal | C53: This deal
A54: LTV/CAC | B54: > 3x | C54: =IF(B22>=3,"Pass","Fail") -> Pass
A55: NRR | B55: > 100% (prefer >110%) | C55: =IF(B18>=1.1,"Pass",IF(B18>=1,"OK","Fail")) -> Pass
A56: Gross margin | B56: > 70% software / path | C56: =IF(B17>=0.7,"Pass","Watch") -> Pass
A57: Post-round runway | B57: > 18 months | C57: =IF(B28>=18,"Pass",IF(B28>=12,"Watch","Fail")) -> Pass
A58: Ownership | B58: Meaningful (≥8–15% stage-dependent) | C58: =IF(B11>=0.08,"Pass","Watch") -> Watch
A59: MOIC base | B59: > 3x for venture path | C59: =IF(B43>=3,"Pass",IF(B43>=2,"Watch","Fail")) -> Watch

Sheet Deal Active
A1: Tage VC — Deal Active | Z1: IC Approved | AA1: Critical | AB1: Priced Equity
A2: One row per live deal post-DD. Close when Wired/Closed or Dead. | Z2: Term Sheet | AA2: High | AB2: SAFE
Z3: Confirmatory DD | AA3: Medium | AB3: Convertible Note
A4: Summary | Z4: Docs Drafting | AA4: Low | AB4: Other
A5: Active deals | B5: =COUNTA(TableDeal[Deal ID]) -> 2 | C5: In closing | D5: =COUNTIF(TableDeal[Execution Stage],"Closing Conditions")+COUNTIF(TableDeal[Execution Stage],"Signing Ready") -> 0 | E5: Term sheet out | F5: =COUNTIF(TableDeal[Execution Stage],"Term Sheet") -> 0 | G5: Critical priority | H5: =COUNTIF(TableDeal[Priority],"Critical") -> 2 | Z5: Signing Ready
Z6: Closing Conditions
A7: Deal ID | B7: Added Date | C7: Company | D7: Lead ID | E7: Execution Stage | F7: Priority | G7: Owner | H7: Counsel | I7: Instrument | J7: Pre-Money ($m) | K7: Check Size ($k) | L7: Target Own % | M7: TS Sent Date | N7: TS Signed Date | O7: Exclusivity End | P7: Target Close | Q7: Next Action | R7: Next Action Date | S7: Notes | Z7: Wired / Closed
A8: DE-001 | B8: 46103 | C8: Orbit Data | D8: LD-005 | E8: IC Approved | F8: Critical | G8: Partner | H8: Firm Counsel | I8: Priced Equity | J8: 45 | K8: 4000 | L8: 0.12 | P8: 46142 | Q8: Draft term sheet; partner approve economics | R8: 46106 | S8: DD complete; IC passed 3/21 | Z8: Post-Close
A9: DE-002 | B9: 46091 | C9: Example Advanced Co | D9: LD-010 | E9: Docs Drafting | F9: Critical | G9: Partner | H9: Firm Counsel | I9: Priced Equity | J9: 28 | K9: 2500 | L9: 0.1 | M9: 46086 | N9: 46093 | O9: 46124 | P9: 46127 | Q9: SPA markup round 2 with co counsel | R9: 46107 | S9: TS signed; board seat agreed

Sheet Deal Closed
A1: Tage VC — Deal Closed (Log) | Z1: Wired / Closed
A2: Wired/Closed or Dead deals. Keep for portfolio handoff and learning. | Z2: Dead
Z3: Paused
A4: Closed count | B4: =COUNTA(TableDealClosed[Deal ID]) -> 1 | C4: Wired/Closed | D4: =COUNTIF(TableDealClosed[Outcome],"Wired / Closed") -> 1 | E4: Dead | F4: =COUNTIF(TableDealClosed[Outcome],"Dead") -> 0
A6: Deal ID | B6: Added Date | C6: Company | D6: Lead ID | E6: Final Stage | F6: Instrument | G6: Pre-Money ($m) | H6: Check Size ($k) | I6: Final Own % | J6: TS Signed Date | K6: Close Date | L6: Outcome | M6: Outcome Reason | N6: Owner | O6: Notes
A7: DE-000 | B7: 45962 | C7: Sample Closed Co | D7: LD-099 | E7: Wired / Closed | F7: SAFE | H7: 750 | I7: 0 | J7: 45976 | K7: 45993 | L7: Wired / Closed | M7: Closed on SAFE; post-close portfolio kickoff done | N7: Partner | O7: Handed to portfolio ops

Sheet Deal Tasks Active
A1: Tage VC — Deal Tasks Active | Z1: IC Approved | AA1: Critical | AB1: Not Started
A2: IC → term sheet → docs → close tasks. Move done rows to Deal Tasks Done. | Z2: Term Sheet | AA2: High | AB2: In Progress
Z3: Confirmatory DD | AA3: Medium | AB3: Blocked
A4: Open tasks | B4: =COUNTA(TableDealTasks[Task ID]) -> 3 | C4: Critical / High | D4: =COUNTIFS(TableDealTasks[Priority],"Critical")+COUNTIFS(TableDealTasks[Priority],"High") -> 3 | E4: Blocked | F4: =COUNTIF(TableDealTasks[Status],"Blocked") -> 0 | Z4: Docs Drafting | AA4: Low | AB4: Waiting on Company
Z5: Signing Ready | AB5: Completed
A6: Task ID | B6: Added Date | C6: Company | D6: Deal ID | E6: Process Stage | F6: Task | G6: Priority | H6: Status | I6: Owner | J6: Due Date | K6: Notes | L6: Evidence / Link | Z6: Closing Conditions
A7: DT-001 | B7: 46103 | C7: Orbit Data | D7: DE-001 | E7: Term Sheet | F7: Draft term sheet economics and key rights | G7: Critical | H7: In Progress | I7: Partner | J7: 46106 | K7: IC approved economics band | Z7: Wired / Closed
A8: DT-002 | B8: 46095 | C8: Example Advanced Co | D8: DE-002 | E8: Docs Drafting | F8: SPA / investment docs markup and issue list | G8: Critical | H8: In Progress | I8: Counsel | J8: 46107 | K8: Round 2 open points on liability cap | Z8: Post-Close
A9: DT-003 | B9: 46095 | C9: Example Advanced Co | D9: DE-002 | E9: Docs Drafting | F9: Charter / COI amendments and board consents drafted | G9: High | H9: Not Started | I9: Counsel | J9: 46109

Sheet Deal Tasks Done
A1: Tage VC — Deal Tasks Done (Log)
A2: Completed execution tasks. Paste from Deal Tasks Active; set Date Completed.
A4: Done count | B4: =COUNTA(TableDealTasksDone[Task ID]) -> 1
A6: Task ID | B6: Added Date | C6: Company | D6: Deal ID | E6: Process Stage | F6: Task | G6: Priority | H6: Status | I6: Owner | J6: Due Date | K6: Notes | L6: Evidence / Link | M6: Date Completed | N6: Completed By
A7: DT-000 | B7: 46091 | C7: Example Advanced Co | D7: DE-002 | E7: Term Sheet | F7: Negotiate and sign term sheet | G7: Critical | H7: Completed | I7: Partner | J7: 46093 | K7: Signed 3/12 | M7: 46093 | N7: Partner

Sheet Deal Process Library
A1: Tage VC — Deal Process Library
A2: Copy into Deal Tasks Active when a deal enters each stage.
A4: Lib ID | B4: Process Stage | C4: Task | D4: Default Priority | E4: Owner Role | F4: What Good Looks Like
A5: DX-01 | B5: IC Approved | C5: Finalize IC memo with DD findings and recommendation | D5: Critical | E5: Partner | F5: Memo includes risks, kill criteria, return case
A6: DX-02 | B6: IC Approved | C6: Hold IC; record vote and any conditions | D6: Critical | E6: Partner | F6: Written approval + conditions logged
A7: DX-03 | B7: IC Approved | C7: Open Deal Active row (DE-###); link Lead ID + Company | D7: Critical | E7: Associate | F7: Same Company string as DD Entity
A8: DX-04 | B8: IC Approved | C8: Engage counsel; open matter and conflict check | D8: High | E8: Partner | F8: Counsel assigned on Deal Active
A9: DX-05 | B9: Term Sheet | C9: Draft term sheet economics and key rights | D9: Critical | E9: Partner | F9: Valuation, check, ownership, board, pool, pro rata
A10: DX-06 | B10: Term Sheet | C10: Internal review of TS vs IC authority | D10: Critical | E10: Partner | F10: Within IC band or re-approval noted
A11: DX-07 | B11: Term Sheet | C11: Send TS to founder / company counsel | D11: Critical | E11: Partner | F11: TS Sent Date set
A12: DX-08 | B12: Term Sheet | C12: Negotiate TS markups; track open commercial points | D12: Critical | E12: Partner | F12: Issue list current until signed
A13: DX-09 | B13: Term Sheet | C13: Sign term sheet; set exclusivity / no-shop end date | D13: Critical | E13: Partner | F13: TS Signed + Exclusivity End populated
A14: DX-10 | B14: Term Sheet | C14: Announce process timeline and working group | D14: High | E14: Associate | F14: Target Close agreed with company
A15: DX-11 | B15: Confirmatory DD | C15: Confirmatory legal DD request list to company counsel | D15: Critical | E15: Counsel | F15: Aligned with open DD tracker items
... A36: DX-32 | B36: Post-Close | C36: Archive data room + deal folder; lessons learned note | D36: Medium | E36: Associate | F36: Searchable archive for future deals

Sheet Deal Notes
A1: Tage VC — Deal Notes
A3: Purpose
A4: After DD + IC: TS → docs → close → portfolio handoff.
A6: Sheet map
A7: Deal Active — one row per live deal (economics + stage + dates).
A8: Deal Closed — Wired/Closed or Dead outcomes.
A9: Deal Tasks — execution checklist (lead/DD pattern).
A10: Deal Process Library — 32 standard IC→Close steps.
A12: Execution stages
A13: IC → Term Sheet → Confirmatory DD → Docs → Signing → CPs → Wire → Post-Close
A15: Workflow
A16: 1. IC approve → open Deal Active (DE-###); match Company name.
... A24: IDs DE/LD. Join on Company. See Data Dictionary.
A26: Last built | B26: 2026-03-22 — deal execution tracker

Sheet M&A Pipeline Active
A1: Tage VC — M&A Pipeline Active | Z1: Sourced | AA1: Critical | AB1: Platform acquisition | AC1: Strong
A2: One row per target company. Separate from VC check deals. Close when Closed or Walked. | Z2: CIM Review | AA2: High | AB2: Add-on / roll-up | AC2: Medium
Z3: Management Meeting | AA3: Medium | AB3: Merger | AC3: Weak
A4: Active targets | B4: =COUNTA(TableMAPipeline[MA ID]) -> 2 | C4: In exclusivity | D4: =COUNTIF(TableMAPipeline[MA Stage],"LOI / Exclusivity") -> 1 | E4: LOI out | F4: =COUNTIF(TableMAPipeline[MA Stage],"IOI / Indication")+COUNTIF(TableMAPipeline[MA Stage],"LOI / Exclusivity") -> 1 | Z4: IOI / Indication | AA4: Low | AB4: Asset purchase | AC4: Unknown
Z5: LOI / Exclusivity | AB5: Other
A6: MA ID | B6: Added Date | C6: Target Company | D6: Website | E6: Sector | F6: Deal Type | G6: Source | H6: MA Stage | I6: Priority | J6: Owner | K6: Enterprise Value ($m) | L6: Revenue ($m) | M6: EBITDA ($m) | N6: Next Action | O6: Next Action Date | P6: Exclusivity End | Q6: Strategic Fit | R6: Notes | Z6: Confirmatory DD
A7: MA-001 | B7: 46082 | C7: Midwest Ops Co | D7: midwestops.example | E7: Business services | F7: Platform acquisition | G7: Broker | H7: LOI / Exclusivity | I7: Critical | J7: Partner | K7: 18 | L7: 12 | M7: 2.4 | N7: Quality of earnings kickoff | O7: 46107 | P7: 46143 | Q7: Strong | R7: Owner retirement; add-on pipeline exists | Z7: Definitive Docs
A8: MA-002 | B8: 46093 | C8: Regional Add-On LLC | D8: regionaladdon.example | E8: Business services | F8: Add-on / roll-up | G8: Proprietary | H8: Management Meeting | I8: High | J8: Associate | K8: 4.5 | L8: 3.2 | M8: 0.7 | N8: Site visit + customer refs | O8: 46109 | Q8: Medium | R8: Bolt onto Midwest Ops platform thesis | Z8: Closing
Z9: Integration

Sheet M&A Pipeline Closed
A1: Tage VC — M&A Pipeline Closed (Log) | Z1: Acquired
A2: Acquired / Walked / Lost. Keep for thesis learning and broker ROI. | Z2: Walked
Z3: Lost
A4: Closed count | B4: =COUNTA(TableMAClosed[MA ID]) -> 1 | C4: Acquired | D4: =COUNTIF(TableMAClosed[Outcome],"Acquired") -> 0 | E4: Walked | F4: =COUNTIF(TableMAClosed[Outcome],"Walked") -> 1 | Z4: Paused
A6: MA ID | B6: Added Date | C6: Target Company | D6: Deal Type | E6: Final Stage | F6: EV ($m) | G6: Revenue ($m) | H6: EBITDA ($m) | I6: Outcome | J6: Outcome Reason | K6: Close Date | L6: Owner | M6: Notes
A7: MA-000 | B7: 45870 | C7: Example Walk Co | D7: Platform acquisition | E7: Confirmatory DD | F7: 22 | G7: 14 | H7: 1.1 | I7: Walked | J7: Customer concentration + QoE gaps | K7: 45945 | L7: Partner | M7: Lessons in QoE scope

Sheet M&A Tasks Active
A1: Tage VC — M&A Tasks Active | Z1: Sourced | AA1: Critical | AB1: Not Started
A2: Acquisition work items. Move done rows to M&A Tasks Done. | Z2: CIM Review | AA2: High | AB2: In Progress
Z3: Management Meeting | AA3: Medium | AB3: Blocked
A4: Open tasks | B4: =COUNTA(TableMATasks[Task ID]) -> 2 | C4: Critical / High | D4: =COUNTIFS(TableMATasks[Priority],"Critical")+COUNTIFS(TableMATasks[Priority],"High") -> 2 | Z4: IOI / Indication | AA4: Low | AB4: Completed
Z5: LOI / Exclusivity
A6: Task ID | B6: Added Date | C6: Target Company | D6: MA ID | E6: Process Stage | F6: Task | G6: Priority | H6: Status | I6: Owner | J6: Due Date | K6: Notes | Z6: Confirmatory DD
A7: MT-001 | B7: 46101 | C7: Midwest Ops Co | D7: MA-001 | E7: Confirmatory DD | F7: Engage QoE / quality of earnings provider | G7: Critical | H7: In Progress | I7: Partner | J7: 46108 | K7: Scope normalized EBITDA | Z7: Definitive Docs
A8: MT-002 | B8: 46099 | C8: Regional Add-On LLC | D8: MA-002 | E8: Management Meeting | F8: Management presentation + org chart review | G8: High | H8: Not Started | I8: Associate | J8: 46109 | Z8: Closing
Z9: Integration

Sheet M&A Tasks Done
A1: Tage VC — M&A Tasks Done (Log)
A2: Completed acquisition tasks. Paste from Active; set Date Completed.
A4: Done count | B4: =COUNTA(TableMATasksDone[Task ID]) -> 1
A6: Task ID | B6: Added Date | C6: Target Company | D6: MA ID | E6: Process Stage | F6: Task | G6: Priority | H6: Status | I6: Owner | J6: Due Date | K6: Notes | L6: Date Completed | M6: Completed By
A7: MT-000 | B7: 46086 | C7: Midwest Ops Co | D7: MA-001 | E7: LOI / Exclusivity | F7: Negotiate and sign LOI + exclusivity | G7: Critical | H7: Completed | I7: Partner | J7: 46096 | K7: 45-day exclusivity | L7: 46095 | M7: Partner

Sheet M&A Process Library
A1: Tage VC — M&A Process Library
A2: Copy into M&A Tasks Active when a target enters each stage.
A4: Lib ID | B4: Process Stage | C4: Task | D4: Default Priority | E4: Owner Role | F4: What Good Looks Like
A5: MA-01 | B5: Sourced | C5: Log target: type (platform/add-on/merger), source, teaser | D5: Critical | E5: Associate | F5: MA-### row complete
A6: MA-02 | B6: Sourced | C6: Strategic fit vs platform / roll-up thesis | D6: Critical | E6: Partner | F6: Fit Strong/Med/Weak set
A7: MA-03 | B7: CIM Review | C7: Review CIM / financials teaser; build first filter memo | D7: Critical | E7: Associate | F7: Pass/advance with reasons
A8: MA-04 | B8: CIM Review | C8: Normalize revenue/EBITDA; flag add-backs | D8: High | E8: Associate | F8: Bridge to M&A Model inputs
A9: MA-05 | B9: Management Meeting | C9: Management meeting / site visit agenda | D9: High | E9: Partner | F9: Org, customers, culture probed
A10: MA-06 | B10: Management Meeting | C10: Customer and employee reference plan | D10: High | E10: Associate | F10: Refs scheduled under NDA
A11: MA-07 | B11: IOI / Indication | C11: Draft non-binding IOI valuation range + structure | D11: Critical | E11: Partner | F11: Cash/earnout/rollover sketch
A12: MA-08 | B12: IOI / Indication | C12: IC soft circle on IOI before send | D12: Critical | E12: Partner | F12: Authority documented
A13: MA-09 | B13: LOI / Exclusivity | C13: Negotiate LOI: price, structure, exclusivity, key terms | D13: Critical | E13: Partner | F13: Signed LOI; exclusivity end dated
A14: MA-10 | B14: LOI / Exclusivity | C14: Engage counsel; open deal room + request list | D14: Critical | E14: Counsel | F14: Request list live
A15: MA-11 | B15: Confirmatory DD | C15: Quality of earnings (QoE) engagement | D15: Critical | E15: Partner | F15: Normalized EBITDA locked
... A28: MA-24 | B28: Integration | C28: Synergy tracking vs model; 90-day review | D28: High | E28: Partner + COO | F28: Variance explained

Sheet M&A Scorecard
A1: Tage VC — M&A Scorecard
A2: Score 1–5. Weights must sum to 100%. Blue = inputs.
A4: Target | B4: Midwest Ops Co | C4: MA ID | D4: MA-001
A5: Deal type | B5: Platform acquisition | C5: Scorer | D5: Partner
A7: Pillar | B7: Weight | C7: Score 1-5 | D7: Weighted | E7: Evidence
A8: Strategic fit / thesis | B8: 0.2 | C8: 5 | D8: =B8*C8 -> 1 | E8: Core platform for roll-up
A9: Financial quality (QoE) | B9: 0.2 | C9: 4 | D9: =B9*C9 -> 0.8 | E9: Stable margins; clean books path
A10: Customer quality / concentration | B10: 0.15 | C10: 3 | D10: =B10*C10 -> 0.45 | E10: Top 5 = 38% revenue
A11: Management / culture retain | B11: 0.15 | C11: 4 | D11: =B11*C11 -> 0.6 | E11: GM stays 24 months
A12: Integration complexity | B12: 0.1 | C12: 3 | D12: =B12*C12 -> 0.3 | E12: Moderate IT debt
A13: Valuation / returns | B13: 0.1 | C13: 4 | D13: =B13*C13 -> 0.4 | E13: ~7.5x EBITDA with synergies
A14: Legal / risk | B14: 0.1 | C14: 4 | D14: =B14*C14 -> 0.4 | E14: No material litigation known
A15: TOTAL | B15: =SUM(B8:B14) -> 1 | D15: =SUM(D8:D14) -> 3.95 | E15: =IF(ABS(B15-1)>0.001,"FIX WEIGHTS","Weights OK") -> Weights OK
A17: Score / 5 | B17: =D15 -> 3.95
A18: Recommendation | B18: =IF(B17>=4,"Strong pursue",IF(B17>=3.25,"Pursue with conditions",IF(B17>=2.5,"Re-trade / more DD","Walk"))) -> Pursue with conditions
A19: IC decision | B19: Pursue with conditions
A20: Conditions | B20: QoE confirms ≥$2.2m norm. EBITDA; escrow 10%; key man agreements

Sheet M&A Model
A1: Tage VC — M&A Model
A2: Purchase price, leverage sketch, synergies, simple returns. Blue = inputs.
A4: TARGET & PRICE
A5: Target | B5: Midwest Ops Co
A6: LTM revenue | B6: 12
A7: Reported EBITDA | B7: 2.4
A8: Norm. EBITDA (QoE) | B8: 2.2
A9: EV / norm. EBITDA multiple | B9: 7.5
A10: Enterprise value | B10: =B8*B9 -> 16.5
A11: Net debt / (cash) | B11: 1.5
A12: Equity value | B12: =B10-B11 -> 15
A13: Cash at close % | B13: 0.8
A14: Seller rollover % | B14: 0.15
A15: Earnout % (of EV) | B15: 0.05
A16: Cash to sellers | B16: =B12*B13 -> 12
A17: Rollover equity | B17: =B12*B14 -> 2.25
A18: Earnout max | B18: =B10*B15 -> 0.825
A20: SYNERGIES (annual run-rate)
A21: Cost synergies | B21: 0.35
A22: Revenue synergies (EBITDA impact) | B22: 0.15
A23: One-time integration cost | B23: 0.4
A24: Synergy-adj. EBITDA | B24: =B8+B21+B22 -> 2.7
A25: EV / synergy EBITDA | B25: =IFERROR(B10/B24,0) -> 6.1111111
A27: SIMPLE RETURNS (5-yr hold sketch)
A28: Exit year | B28: 5
A29: EBITDA CAGR | B29: 0.08
A30: Exit EBITDA | B30: =B24*((1+B29)^B28) -> 3.9671858
A31: Exit multiple | B31: 7
A32: Exit EV | B32: =B30*B31 -> 27.770301
A33: Tage equity in at close (ex-rollover) | B33: =B12-B17 -> 12.75
A34: Net debt at exit (assume constant) | B34: 1.5
A35: Exit equity value | B35: =B32-B34 -> 26.270301
A36: Tage ownership of equity % | B36: 0.85
A37: Tage exit proceeds | B37: =B35*B36 -> 22.329756
A38: MOIC (gross equity) | B38: =IFERROR(B37/B33,0) -> 1.7513534
A39: Approx IRR | B39: =IFERROR(B38^(1/B28)-1,0) -> 0.11859985
A41: FILTERS
A42: Multiple on norm. EBITDA ≤ 8x? | B42: =IF(B9<=8,"Pass","Watch") -> Pass
A43: Synergy multiple ≤ 7x? | B43: =IF(B25<=7,"Pass","Watch") -> Pass
A44: MOIC ≥ 2.0x? | B44: =IF(B38>=2,"Pass","Fail") -> Fail

Sheet M&A Integration
A1: Tage VC — M&A Integration
A2: After close. One plan per acquired company. Blue = inputs.
A4: Company | B4: Midwest Ops Co | C4: MA ID | D4: MA-001
A5: Close date | C5: Integration lead (COO) | D5: COO — Ops Lead
A7: WORKSTREAM | B7: Day-1 | C7: Day-30 | D7: Day-100 | E7: Owner | F7: Status
A8: People & comms | B8: All-hands; retain key staff | C8: Roles clear; offer letters done | D8: Culture survey; org final | E8: COO + HR | F8: Not Started
A9: Customers | B9: Top-20 outreach | C9: No unexpected churn | D9: Cross-sell pilot live | E9: GM / Sales | F9: Not Started
A10: Finance / reporting | B10: Banking + cash controls | C10: Monthly pack in Tage format | D10: Budget locked; audit trail | E10: Finance | F10: Not Started
A11: Systems / IT | B11: Access + security baseline | C11: Critical systems mapped | D11: Cutover plan executed | E11: IT / COO | F11: Not Started
A12: Synergies | B12: Synergy owners named | C12: 25% run-rate captured | D12: 75%+ vs model | E12: Partner + COO | F12: Not Started
A13: Legal / compliance | B13: Entity filings; insurance | C13: Contracts assignment done | D13: Open issues closed | E13: Counsel | F13: Not Started
A15: After Day-100: add company to Portfolio Active with health KPIs (same COO cadence as Launch cos).

Sheet M&A Notes
A1: Tage VC — M&A Notes
A3: Purpose
A4: Buy / merge / roll-up whole companies. Not the same as writing a VC check (Deal Active).
A6: When to use which track
A7: VC invest track (slate/taupe/cool): minority or growth equity; startup diligence; term sheet; portfolio as investor.
A8: M&A track (steel gray tabs): control or platform buy; QoE; LOI; SPA/APA; integration into ops under COO.
A10: M&A stages
A11: Sourced → CIM Review → Management Meeting → IOI → LOI/Exclusivity → Confirmatory DD → Definitive Docs → Closing → Integration
A13: IDs
A14: MA-### targets · MT-### tasks. After close → M&A Integration then Portfolio Active.
A16: Sheets
A17: Pipeline Active/Closed · Tasks Active/Done · Process Library · Scorecard · Model · Integration · Notes
A19: Do not mix Company rows across VC Deal ID and MA ID without labeling deal type.

Sheet RE Pipeline Active
A1: Tage VC — RE Pipeline Active | Z1: Sourced | AA1: Residential | AB1: Critical
A2: RE sourcers live here. Route = Residential or Commercial. Separate from VC/M&A business tracks. | Z2: Screen | AA2: Commercial | AB2: High
Z3: Underwriting | AB3: Medium
A4: Active deals | B4: =COUNTA(TableREPipeline[RE ID]) -> 2 | C4: Residential | D4: =COUNTIF(TableREPipeline[Route],"Residential") -> 1 | E4: Commercial | F4: =COUNTIF(TableREPipeline[Route],"Commercial") -> 1 | G4: Under contract | H4: =COUNTIF(TableREPipeline[RE Stage],"LOI / PSA")+COUNTIF(TableREPipeline[RE Stage],"Diligence")+COUNTIF(TableREPipeline[RE Stage],"Closing") -> 1 | Z4: Offer | AB4: Low
Z5: LOI / PSA
A6: RE ID | B6: Added Date | C6: Asset / Address | D6: Route | E6: Asset Type | F6: Market / City | G6: Source | H6: RE Stage | I6: Priority | J6: Sourcer | K6: Ask Price ($k) | L6: Offer ($k) | M6: NOI or Rent ($k/yr) | N6: Cap / Yield signal | O6: Next Action | P6: Next Action Date | Q6: Notes | Z6: Diligence
A7: RE-001 | B7: 46091 | C7: 1842 Maple St, Indianapolis | D7: Residential | E7: SFR value-add | F7: Indianapolis, IN | G7: Off-market / agent | H7: Underwriting | I7: High | J7: RE Sourcer — Resi | K7: 285 | L7: 265 | M7: 28.8 | N7: ARV path | O7: Finish rehab budget + comps | P7: 46106 | Q7: 3bd/2ba; light value-add | Z7: Closing
A8: RE-002 | B8: 46086 | C8: Carmel Flex — 12k SF | D8: Commercial | E8: Flex / industrial | F8: Carmel, IN | G8: Broker CIM | H8: LOI / PSA | I8: Critical | J8: RE Sourcer — CRE | K8: 2400 | L8: 2250 | M8: 168 | N8: 7.5% cap on offer | O8: Order Phase I + rent roll audit | P8: 46107 | Q8: 90% occupied; 2 tenants roll in 14 mo | Z8: Onboard

Sheet RE Pipeline Closed
A1: Tage VC — RE Pipeline Closed (Log) | Z1: Purchased | AA1: Residential
A2: Purchased / Passed / Lost. Track sourcer hit rate by Route. | Z2: Passed | AA2: Commercial
Z3: Lost
A4: Closed | B4: =COUNTA(TableREClosed[RE ID]) -> 1 | C4: Purchased | D4: =COUNTIF(TableREClosed[Outcome],"Purchased") -> 0 | E4: Passed | F4: =COUNTIF(TableREClosed[Outcome],"Passed") -> 1 | Z4: Paused
A6: RE ID | B6: Added Date | C6: Asset / Address | D6: Route | E6: Asset Type | F6: Market / City | G6: Sourcer | H6: Final Stage | I6: Close Price ($k) | J6: Outcome | K6: Outcome Reason | L6: Close Date | M6: Notes
A7: RE-000 | B7: 45962 | C7: Sample Passed Duplex | D7: Residential | E7: 2–4 unit | F7: Indy | G7: RE Sourcer — Resi | H7: Underwriting | J7: Passed | K7: Rehab risk > underwrite hurdle | L7: 45981 | M7: Good source; wrong basis

Sheet RE Tasks Active
A1: Tage VC — RE Tasks Active | Z1: Sourced | AA1: Residential | AB1: Critical | AC1: Not Started
A2: Work for RE sourcers + underwriting. Move done rows to RE Tasks Done. | Z2: Screen | AA2: Commercial | AB2: High | AC2: In Progress
Z3: Underwriting | AB3: Medium | AC3: Blocked
A4: Open | B4: =COUNTA(TableRETasks[Task ID]) -> 2 | Z4: Offer | AB4: Low | AC4: Completed
Z5: LOI / PSA
A6: Task ID | B6: Added Date | C6: Asset / Address | D6: RE ID | E6: Route | F6: Process Stage | G6: Task | H6: Priority | I6: Status | J6: Owner | K6: Due Date | L6: Notes | Z6: Diligence
A7: RT-001 | B7: 46101 | C7: 1842 Maple St, Indianapolis | D7: RE-001 | E7: Residential | F7: Underwriting | G7: Comps + ARV + rehab budget (resi) | H7: High | I7: In Progress | J7: RE Sourcer — Resi | K7: 46106 | Z7: Closing
A8: RT-002 | B8: 46099 | C8: Carmel Flex — 12k SF | D8: RE-002 | E8: Commercial | F8: Diligence | G8: Phase I ESA + rent roll / T-12 audit (CRE) | H8: Critical | I8: Not Started | J8: RE Sourcer — CRE | K8: 46109 | Z8: Onboard

Sheet RE Tasks Done
A1: Tage VC — RE Tasks Done (Log)
A2: Completed RE tasks. Paste from Active; set Date Completed.
A4: Done | B4: =COUNTA(TableRETasksDone[Task ID]) -> 1
A6: Task ID | B6: Added Date | C6: Asset / Address | D6: RE ID | E6: Route | F6: Process Stage | G6: Task | H6: Priority | I6: Status | J6: Owner | K6: Due Date | L6: Notes | M6: Date Completed | N6: Completed By
A7: RT-000 | B7: 46087 | C7: Carmel Flex — 12k SF | D7: RE-002 | E7: Commercial | F7: LOI / PSA | G7: Submit LOI with cap-rate basis | H7: Critical | I7: Completed | J7: RE Sourcer — CRE | K7: 46093 | L7: Accepted to PSA | M7: 46093 | N7: RE Sourcer — CRE

Sheet RE Process Library
A1: Tage VC — RE Process Library
A2: Copy tasks into RE Tasks Active. Route = Both, Residential, or Commercial.
A4: Lib ID | B4: Route | C4: Process Stage | D4: Task | E4: Priority | F4: Owner Role | G4: What Good Looks Like
A5: RE-01 | B5: Both | C5: Sourced | D5: Log asset: address, route, type, source, ask | E5: Critical | F5: RE Sourcer | G5: RE-### complete
A6: RE-02 | B6: Both | C6: Sourced | D6: Thesis fit: market, size, hold thesis | E6: Critical | F6: RE Sourcer | G6: In/out of box stated
A7: RE-03 | B7: Residential | C7: Screen | D7: Pull comps (sold/active); condition photos | E7: High | F7: RE Sourcer — Resi | G7: 3+ comps within 0.5–1 mi
A8: RE-04 | B8: Commercial | C8: Screen | D8: Review OM/CIM: rent roll, T-12, occupancy | E8: Critical | F8: RE Sourcer — CRE | G8: NOI bridge started
A9: RE-05 | B9: Both | C9: Screen | D9: Title / tax / flood / zoning quick flags | E9: High | F9: RE Sourcer | G9: Red flags listed
A10: RE-06 | B10: Residential | C10: Underwriting | D10: ARV, rehab budget, all-in basis, exit yield | E10: Critical | F10: RE Sourcer — Resi | G10: RE Underwrite Resi block filled
A11: RE-07 | B11: Commercial | C11: Underwriting | D11: NOI, cap rate, debt sketch, sensitivity | E11: Critical | F11: RE Sourcer — CRE | G11: RE Underwrite CRE block filled
A12: RE-08 | B12: Both | C12: Underwriting | D12: IC / partner go-no-go on offer price | E12: Critical | F12: Partner | G12: Authority to offer
A13: RE-09 | B13: Both | C13: Offer | D13: Submit offer / LOI; track response | E13: Critical | F13: RE Sourcer | G13: Offer $ on pipeline
A14: RE-10 | B14: Both | C14: LOI / PSA | D14: Negotiate PSA; earnest money; contingencies | E14: Critical | F14: Counsel + Sourcer | G14: PSA fully executed
A15: RE-11 | B15: Residential | C15: Diligence | D15: Home inspection, pest, sewer/septic as needed | E15: Critical | F15: RE Sourcer — Resi | G15: Repair credit or walk
... A22: RE-18 | B22: Both | C22: Sourcing Ops | D22: Broker/agent scorecard (close rate) | E22: Low | F22: RE Sourcer | G22: Double down on channels that convert

Sheet RE Underwrite
A1: Tage VC — RE Underwrite
A2: Use the block that matches Route. Blue = inputs.
A4: RESIDENTIAL | D4: COMMERCIAL
A5: RE ID / Address | B5: RE-001 · 1842 Maple | D5: RE ID / Asset | E5: RE-002 · Carmel Flex
A6: Purchase (offer) $k | B6: 265 | D6: Offer price $k | E6: 2250
A7: Closing costs $k | B7: 8 | D7: Closing + capex yr1 $k | E7: 75
A8: Rehab $k | B8: 35 | D8: All-in $k | E8: =E6+E7 -> 2325
A9: All-in basis $k | B9: =B6+B7+B8 -> 308 | D9: In-place NOI $k | E9: 168
A10: ARV $k | B10: 340 | D10: Stabilized NOI $k | E10: 185
A11: Equity cushion vs ARV | B11: =IFERROR(1-B9/B10,0) -> 0.094117647 | D11: Going-in cap (on offer) | E11: =IFERROR(E9/E6,0) -> 0.074666667
A12: Gross monthly rent $ | B12: 2400 | D12: Stabilized cap (on all-in) | E12: =IFERROR(E10/E8,0) -> 0.079569892
A13: Annual rent $k | B13: =B12*12/1000 -> 28.8 | D13: Occupancy | E13: 0.9
A14: OpEx ratio | B14: 0.35 | D14: LTV | E14: 0.65
A15: NOI $k | B15: =B13*(1-B14) -> 18.72 | D15: Debt $k | E15: =E6*E14 -> 1462.5
A16: Going-in yield on all-in | B16: =IFERROR(B15/B9,0) -> 0.060779221 | D16: Equity $k | E16: =E8-E15 -> 862.5
A17: Hurdle yield | B17: 0.08 | D17: Interest rate | E17: 0.065
A18: Resi filter | B18: =IF(AND(B11>=0.15,B16>=B17),"Pass",IF(OR(B11>=0.1,B16>=B17*0.9),"Watch","Fail")) -> Fail | D18: Interest-only yr1 $k | E18: =E15*E17 -> 95.0625
D19: Cash flow after IO $k | E19: =E9-E18 -> 72.9375
D20: Cash-on-cash | E20: =IFERROR(E19/E16,0) -> 0.084565217
D21: Hurdle going-in cap | E21: 0.07
D22: CRE filter | E22: =IF(AND(E11>=E21,E13>=0.85),"Pass",IF(E11>=E21*0.95,"Watch","Fail")) -> Pass

Sheet RE Portfolio
A1: Tage VC — RE Portfolio | Z1: On Track | AA1: Residential
A2: Post-close property book. PM/sourcer updates monthly. Blue = inputs. | Z2: Watch | AA2: Commercial
Z3: At Risk
A4: Assets | B4: =COUNTA(TableREPortfolio[PFRE ID]) -> 1 | C4: Resi | D4: =COUNTIF(TableREPortfolio[Route],"Residential") -> 1 | E4: CRE | F4: =COUNTIF(TableREPortfolio[Route],"Commercial") -> 0 | Z4: Critical
A6: PFRE ID | B6: Asset / Address | C6: RE ID | D6: Route | E6: Asset Type | F6: Close Date | G6: Basis $k | H6: NOI $k | I6: Occ % | J6: Yield on basis | K6: PM / Owner | L6: Health | M6: Top Issue | N6: Last Update
A7: PFRE-001 | B7: Sample Indy SFR | C7: RE-100 | D7: Residential | E7: SFR | F7: 45915 | G7: 210 | H7: 18.5 | I7: 1 | J7: =IFERROR(H7/G7,0) -> 0.088095238 | K7: PM — Resi | L7: On Track | M7: None | N7: 46082

Sheet RE Notes
A1: Tage VC — RE Notes
A3: Team split
A4: Business sourcers → Pipeline Active (VC) or M&A Pipeline (buys). Never put real estate on those sheets.
A5: RE sourcers → RE Pipeline only. Tag Route = Residential or Commercial. Owner field = RE Sourcer — Resi or CRE.
A7: Why separate
A8: Different diligence (comps/ARV vs QoE/leases), different close docs (PSA vs SPA), different ops (PM vs COO of opco).
A10: Shared firm layer
A11: Command Center KPIs · Partner capital approval · Counsel/Ops on PSA wire · How We Run weekly scrub includes RE Mon triage.
A13: Stages
A14: Sourced → Screen → Underwriting → Offer → LOI/PSA → Diligence → Closing → Onboard (RE Portfolio)
A16: IDs: RE-### deals · RT-### tasks · PFRE-### owned assets.
A18: Resi vs CRE in library: filter RE Process Library column Route. Spawn Both + route-specific tasks.

Sheet Core Subsidiary Structure
A1: Tage VC — Core Subsidiary Structure | Official Standard
A2: Mandatory CORE for every subsidiary · FLEX = add-ons only · COO enforces · Visionary exceptions · Day-to-day: Subsidiary Operating System · §3 KPIs · §6 Health · §7 SS · §8 Handoff · §9 Governance
A4: CONTENTS
A5: §1 CORE vs FLEX · §2 P&L · §3 KPIs · §4 Roll-up · §5 Rhythm · §6 Health · §7 Shared Services · §8 Handoff · §9 Governance · §10 FLEX modules · §11 Go-live | B5: Requirement
A6: Purpose | B6: One operating foundation so every sub is comparable, auditable, and roll-up ready for Portfolio + Firm.
A7: §1 TWO LAYERS
A8: Layer | B8: Code | C8: Requirement | D8: Who controls changes
A9: Core Standardized | B9: CORE | C9: Required every reporting cycle for every Subsidiary | D9: Firm sets; Visionary approves any CORE reduction
A10: Industry-Specific | B10: FLEX | C10: Add-on KPIs/playbooks only; never remove CORE | D10: COO + Sub Lead; Entity Master.industry_module
A11: Non-compliance: missing CORE P&L, CORE KPI, monthly pack, or Health for >1 cycle without written exception → Health must be At Risk or Critical.
A12: Core KPIs | B12: CORE | C12: Same keys + definitions | D12: See §3 kpi_key list
A13: §2 CORE P&L (MONTHLY $k)
A14: Line | B14: Definition | C14: QBE map | D14: Portfolio roll-up | E14: Owner
A15: Revenue | B15: Recognized revenue or ARR-run-rate locked in Handoff Pack | C15: 4xxx | D15: SUM | E15: Finance + Sub Lead
A16: COGS | B16: Direct cost of delivering revenue only | C16: 5xxx | D16: SUM | E16: Finance
A17: Gross Profit | B17: Revenue − COGS | C17: Calc | D17: SUM | E17: Finance
A18: Gross Margin % | B18: Gross Profit ÷ Revenue | C18: Calc | D18: ΣGP ÷ ΣRevenue (not avg of %) | E18: Finance
A19: OpEx | B19: All operating expense excluding COGS | C19: 6xxx–7xxx | D19: SUM | E19: Finance
A20: Op. Income / EBITDA proxy | B20: Gross Profit − OpEx (add-backs only if Finance documents) | C20: Calc | D20: SUM | E20: Finance
A21: Net Burn | B21: Net cash used by operations in month; 0 if cash generative | C21: Cash bridge | D21: SUM | E21: Finance
A22: Ending Cash | B22: Operating bank cash EOM (flag restricted separately) | C22: BS Cash | D22: SUM | E22: Finance
A23: Runway (mo) | B23: If Net Burn>0 then Ending Cash÷Net Burn else n/a | C23: Calc | D23: Report MIN among burning entities; list any <12 | E23: COO + Finance
A24: Close timing: Shared Services Finance completes books by business day 10; pack published BD10–12.
A25: COGS / Direct costs | B25: Costs directly tied to delivery of revenue | C25: 5xxx COGS | D25: SUM | E25: CORE
A26: §3 CORE KPIs — DEFINITIONS & PORTFOLIO ROLL-UP
A27: Authoritative list for every Subsidiary. Portal table: entity_month_kpi. Do not invent alternate names. FLEX KPIs: §3C only.
A28: KPI Name | B28: Definition | C28: Calculation Method | D28: Owner | E28: Reporting Frequency | F28: Roll-up Method to Portfolio
A29: Revenue / ARR | B29: Entity top-line for the reporting month, in $ thousands. | C29: Lock one method at Handoff; never switch without Finance+COO written approval. Method A: ARR = MRR × 12. Method B: recognized accounting revenue for the month ($k). | D29: Sub Lead + Finance | E29: Monthly (pack by BD12) | F29: SUM — Portfolio_Revenue = Σ entity Revenue/ARR (same period)
A30: MoM Growth % | B30: Percent change in the same top-line used for Revenue / ARR versus the prior month. | C30: Entity: (Rev_t − Rev_t−1) ÷ Rev_t−1. If Rev_t−1 = 0, leave blank (n/a). Do not substitute 0% or 100%. | D30: Finance | E30: Monthly with pack | F30: WEIGHTED — Portfolio_MoM = (ΣRev_t − ΣRev_t−1) ÷ ΣRev_t−1 (never average entity %)
A31: Gross Margin % | B31: Share of revenue remaining after direct delivery costs (COGS only), before operating expenses. | C31: Entity: (Revenue − COGS) ÷ Revenue. COGS = direct cost of delivery only (Core P&L). Do not include G&A in COGS. | D31: Finance | E31: Monthly with pack | F31: WEIGHTED — Portfolio_GM = ΣGrossProfit ÷ ΣRevenue (never average entity %)
A32: Net Burn $k | B32: Net operating cash consumed in the month (cash need), not accounting net loss. | C32: From the monthly cash bridge reconciling to bank movement. If ops are net cash-positive, report 0 (not negative burn). | D32: Finance | E32: Monthly with pack | F32: SUM — Portfolio_NetBurn = Σ entity Net Burn $k
A33: Ending Cash $k | B33: Unrestricted operating cash at month-end ($ thousands). | C33: Sum of operating bank balances on the last calendar day of the month. Restricted cash in pack notes only — excluded here. | D33: Finance | E33: Monthly with pack | F33: SUM — Portfolio_Cash = Σ entity Ending Cash $k
A34: Runway months | B34: How many months cash lasts if Net Burn continues at the current rate. | C34: IF Net_Burn > 0 THEN Ending_Cash ÷ Net_Burn ELSE n/a. When numeric, round to 1 decimal. | D34: COO + Finance | E34: Monthly with pack | F34: MIN / FLAG — Min numeric runway where burn>0; FLAG each entity with runway < 12 (never average)
A35: Health | B35: Forced operating status of the subsidiary for portfolio oversight. | C35: Exactly one of: On Track | Watch | At Risk | Critical. Set by COO using Health Matrix §6. Free text is invalid. | D35: COO | E35: Monthly; ad hoc ≤48h if Critical | F35: COUNT — Count entities in each Health status (feeds Command Center)
A36: Top Risk | B36: The single most important risk facing the subsidiary right now. | C36: One sentence + named owner. Required when Health ≠ On Track. Optional when On Track. | D36: Sub Lead | E36: Monthly with pack | F36: LIST — List Top Risk for entities with Health = At Risk or Critical
A37: Customer concentration % | B37: Revenue dependence on the largest customer/client. | C37: Largest_customer_revenue ÷ Total_revenue for the period. Also disclose top-5 % in pack notes. | D37: Sub Lead | E37: Monthly with pack | F37: FLAG — Flag each entity with single-customer concentration > 25% (never average %)
A38: Headcount FTE | B38: Employed workforce size at period end. | C38: Full-time equivalents on the last calendar day of the month. Contractors in pack notes only — not in FTE. | D38: HR + Sub Lead | E38: Monthly with pack | F38: SUM — Portfolio_FTE = Σ entity FTE
A39: Pipeline coverage (GTM only) | B39: Whether commercial pipeline supports next-quarter revenue plan. Required for GTM businesses; otherwise n/a. | C39: Weighted_pipeline_$ ÷ Next_quarter_revenue_target. Document weighting rules in the pack. | D39: Sub Lead | E39: Monthly with pack (if GTM) | F39: FLAG — Flag each GTM entity with coverage < 1.0x (never average ratios)
A41: §3A ROLL-UP METHOD RULES (IMPLEMENT EXACTLY)
A42: Method | B42: Use when | C42: Portfolio formula (precise) | D42: Why not a simple average | E42: Forbidden
A43: SUM | B43: Dollar amounts and headcount (Revenue, COGS, OpEx, Burn, Cash, FTE) | C43: Portfolio_X = X_sub1 + X_sub2 + … + X_subN (same period) | D43: N/A — totaling is correct | E43: Mixing $ with % in one sum
A44: WEIGHTED | B44: Percentages that scale with revenue (Gross Margin %, MoM Growth %) | C44: Rebuild % from portfolio sums. GM: ΣGP/ΣRev. MoM: (ΣRev_t − ΣRev_t−1)/ΣRev_t−1. | D44: Example: Sub A $10k @ 10% GM and Sub B $1,000k @ 50% GM. Simple avg GM = 30%. True portfolio GM ≈ 49.5%. Simple average misstates the business. | E44: AVERAGE(entity_GM%) or AVERAGE(entity_MoM%)
A45: MIN / FLAG | B45: Risk metrics: Runway; thresholds for concentration and pipeline coverage | C45: Runway: Min_Runway = MIN({runway_i | burn_i > 0}). Also emit FLAG list where runway_i < 12. Concentration: FLAG each entity where conc_i > 0.25. Coverage: FLAG each GTM entity where coverage_i < 1.0. | D45: A sub at 4 months runway next to one at 24 months averages to 14 — that hides distress. | E45: AVERAGE(runway) or AVERAGE(concentration%)
A46: COUNT | B46: Health status (categorical enum) | C46: For each status S in {On Track, Watch, At Risk, Critical}: Count = number of subsidiaries with Health = S | D46: Health is a category, not a numeric score | E46: Map statuses to 1–4 and average
A47: LIST | B47: Text fields (Top Risk) | C47: Return a filtered list of {entity, top_risk, owner} for Health in {At Risk, Critical} | D47: Text cannot be averaged | E47: Concatenate all risks into one cell
A49: §3B RUNWAY & CONCENTRATION — STEP BY STEP
A50: Metric | B50: Entity calculation | C50: Portfolio outputs (both required) | D50: Excel (Portfolio Roll-up) / portal job
A51: Runway | B51: If Net_Burn ≤ 0 → store n/a (exclude from MIN). Else Cash ÷ Burn. | C51: (1) Min_Runway among burning entities. (2) Breach_List = entities with numeric runway < 12. | D51: Entity formulas return n/a or number. Portfolio MIN ignores text n/a (COUNT/MIN pattern). FLAG row marks breaches.
A52: Concentration | B52: Largest customer $ ÷ total revenue $. | C52: No portfolio-wide average %. Output Breach_List = entities with conc > 25%. | D52: Not on P&L grid; pack field + risk job returns flags + entity_ids.
A53: Link to Health | B53: Entity triggers in §6 may reference these metrics | C53: System may suggest Health; COO remains owner of Health enum | D53: Do not auto-overwrite Health without COO action
A55: §3C CORE vs FLEX — DIFFERENT TREATMENT
A56: Type | B56: What | C56: Required every month? | D56: Storage | E56: Portfolio Total (money / firm roll-up)?
A57: CORE | B57: KPI Name rows in §3 table above | C57: Yes — every Subsidiary | D57: entity_month_kpi + Portfolio Active fields | E57: Yes — apply Roll-up Method column exactly
A58: FLEX | B58: Industry-only metrics (e.g. Recruit 619: placements, fill_time_days, gp_per_desk; SaaS: NRR, CAC, LTV) | C58: Only if industry_module requires them | D58: entity_month_kpi_flex or subsidiary playbook | E58: No — never SUM or WEIGHTED into Portfolio Revenue, Burn, or Cash. Entity-detail UI only.
A59: Adding a FLEX KPI | B59: Define it with the same six columns as §3 in the playbook; set Entity Master.industry_module | C59: Optional | D59: Playbook + flex table | E59: Excluded from portfolio_month_rollup money fields
A60: Changing a CORE KPI | B60: Visionary written exception required | C60: N/A | D60: Change log | E60: Missing CORE >1 cycle without exception → Health ≤ At Risk
A62: §3D PORTAL IMPLEMENTATION CHECKLIST
A63: 1. entity_month_kpi columns: entity_id, period, kpi_key, value_num, value_text, method ∈ {SUM, WEIGHTED, MIN_FLAG, COUNT, LIST}.
A64: 2. Monthly job order: load entity_month_pnl → SUM money lines → compute WEIGHTED % from those sums → run MIN/FLAG for runway & concentration → COUNT Health from portfolio_companies.health.
A65: 3. Portfolio Active = ops UI (includes Health/Top Risk). Portfolio Roll-up = numeric proof. Same period CORE values must match.
A66: 4. Reject any helper that averages entity margins, growth rates, runways, or concentration percentages.
A67: 5. Worked Excel formulas live on Portfolio Roll-up. This §3 is the rules authority.
A69: §6 HEALTH MATRIX (CORE — AUTHORITATIVE)
A70: Forced enum on Portfolio Active. COO sets. Worst matching row wins. Not optional guidelines.
A71: Health | B71: Definition | C71: Hard triggers (any one) | D71: Required actions | E71: Notify by | F71: Audience
A72: On Track | B72: On plan; no material open risk | C72: Rev & burn within ±15% of plan; runway ≥12 or n/a; no open compliance failure | D72: File monthly pack; continue weekly review; Top Risk optional | E72: With pack | F72: COO
A73: Watch | B73: Early warning; manageable | C73: 1-month plan miss >15%; OR runway 9–<12; OR concentration ≥20% rising; OR key hire slip >30 days | D73: Top Risk required; mitigation owner + due date; track weekly | E73: With pack | F73: COO + Partner
A74: At Risk | B74: Material risk; recovery mandatory | C74: 2 months plan miss; OR runway 6–<9; OR single customer >30% with churn risk; OR no pack 2 cycles | D74: Written recovery plan in 10 bd; biweekly COO check; milestones until Watch+ | E74: Within 48 hours | F74: Partner + COO; Visionary informed
A75: Critical | B75: Existential or control failure | C75: Runway <6; OR fraud/control failure; OR regulatory breach; OR CEO exit without interim plan | D75: War room 48h; options paper; daily stand-up until contained | E75: Same day | F75: Visionary + Partner + COO
A76: Health may improve only one step per month unless COO files written evidence (e.g. capital closed, material contract signed).
A77: Escalation: L1 Sub Lead → L2 COO (owns Health on Portfolio Active) → L3 Partner (At Risk, or Watch >60 days) → L4 Visionary (Critical, capital, CORE exception).
A79: §7 SHARED SERVICES REQUIREMENTS (CORE)
A80: Every Subsidiary must use Tage Shared Services. No shadow GL. No side counsel on material contracts. Cadences: Shared Services Operating Model.
A81: Service | B81: Subsidiary MUST | C81: Shared Services MUST | D81: SLA | E81: If SLA breached
A82: Finance | B82: Source docs by close calendar; approve bills in system; review pack by BD12; no second books | C82: Close books; bank recs; publish pack; maintain QBE entity | D82: Close BD10; pack BD10–12 | E82: Miss BD12 → COO same day; 2nd miss → Health ≤ At Risk + Visionary informed
A83: Legal | B83: Ticket with deadline before any material signature | C83: Draft/negotiate; risk flag | D83: 5 bd std; 48h P0 | E83: Missed P0 → Counsel → Partner same day
A84: HR | B84: Role brief before search; no off-process offers | C84: Recruiting support; compliant packets | D84: Offer pack within 5 bd of decision | E84: Process bypass → HR Lead → COO
A85: IT | B85: Report incidents same day; no shadow admin | C85: Access, security, tools; offboarding with HR | D85: P1 in 4h; access in 2 bd | E85: Incident → COO immediately; breach → Visionary
A86: Marketing | B86: Approved brand only (e.g. Recruit 619); ticket/brief for work | C86: Brand, site, campaigns per firm stack | D86: Per quarterly plan | E86: Marketing Lead → COO
A87: Priority order for all tickets: P0 firm/reg/closing → P1 live deal CP → P2 subsidiary ops → P3 projects.
A89: §8 HANDOFF / ONBOARDING (CORE — DAY 0–30)
A90: Starts at wire/close. Incomplete handoff blocks Health = On Track. Owners own exit criteria, not just activity.
A91: # | B91: Step | C91: Timing | D91: RACI | E91: Exit criteria (done when) | F91: System updated
A92: 1 | B92: Issue entity identity | C92: At wire (same day) | D92: R: Associate · A: Partner | E92: entity_id, canonical_name, legal_name, industry_module, parent_id on file | F92: Entity Master
A93: 2 | B93: Open books in QBE | C93: Day 0–3 | D93: R: Finance · A: Finance Lead | E93: QBE company/class live; bank feed on; CORE P&L accounts exist | F93: QBE
A94: 3 | B94: Create document library | C94: Day 0–3 | D94: R: Counsel/Ops · A: Counsel | E94: Folders 01–07 exist per Document Management standard | F94: Doc store
A95: 4 | B95: Complete Handoff Pack | C95: Wire → Day 7 | D95: R: Partner + COO · A: Partner | E95: Thesis, 90-day plan, baseline CORE KPIs, and revenue method (ARR vs recognized) locked in writing | F95: Portfolio Handoff
A96: 5 | B96: Create Portfolio Active row | C96: Day 0–7 | D96: R: Associate · A: COO | E96: All CORE KPI fields present; initial Health set (default Watch until first full pack) | F96: Portfolio Active
A97: 6 | B97: Stand up weekly rhythm | C97: By Day 14 | D97: R: Sub Lead · A: COO | E97: First Operating Review held; action log has ≥1 dated item | F97: Calendar + action log
A98: 7 | B98: Enable Shared Services access | C98: By Day 30 | D98: R: COO · C: Service Leads | E98: Ticket access live; close calendar received; SS briefing completed | F98: Tickets / SS Model
A99: 8 | B99: First full monthly pack + roll-up | C99: First BD12 after wire | D99: R: Finance + Sub Lead · A: COO | E99: CORE P&L + CORE KPIs published; Portfolio Roll-up column filled for entity | F99: Pack + Portfolio Roll-up
A100: Gates: (A) Steps 1–5 complete before Health may be On Track. (B) Any of steps 6–8 late → Health ≤ Watch until cured. (C) Partner confirms Handoff Pack before step 5 is marked done.
A102: §9 GOVERNANCE & REPORTING (CORE)
A103: Who decides what, how often, and what artifact must exist. Missed cadence without COO waiver is a control failure.
A104: 9A · Decision rights
A105: Decision | B105: Decides (A) | C105: Must consult | D105: Must inform | E105: Required artifact
A106: Set / change Health | B106: COO | C106: Sub Lead (facts); Partner if At Risk+ | D106: Partner always on At Risk/Critical | E106: Portfolio Active Health + Top Risk
A107: Approve recovery plan (At Risk) | B107: Thesis Partner | C107: COO + Sub Lead | D107: Visionary (summary) | E107: Written recovery plan ≤10 bd
A108: Critical war room / options | B108: Visionary | C108: Partner + COO | D108: Firm leadership as needed | E108: Options paper within 48h
A109: Parent capital to a sub | B109: Visionary | C109: COO (runway math); Finance | D109: Partner | E109: Capital memo + runway bridge
...

Sheet Subsidiary Operating System
A1: Tage VC — Subsidiary Operating System | Day-to-Day Guide | Z1: Not Started
A2: For COO & Sub Leads · Rules: Core Structure · Numbers: Portfolio Active + Roll-up · Pulse: Command Center · SS: Shared Services Operating Model | Z2: In Progress
A3: DATA FRESHNESS | B3: Pack BD10–12 · Portfolio Active + Health by BD15 · same period as Portfolio Roll-up B13 · Active $ must match Roll-up entity column · Command Center is read-only formulas. | Z3: Complete
A4: 0 · HOW TO USE | Z4: N/A
A5: Role | B5: Use this tab for | C5: Go elsewhere for
A6: Sub Lead | B6: Weekly agenda, pack prep, risk habits, SS tickets | C6: KPI definitions → Core Structure §3
A7: COO | B7: Cadence, Health, multi-co pulse, escalations | C7: Deal flow / IC → pipelines
A8: Finance (SS) | B8: Close calendar + pack SLA with Sub Lead | C8: Health (COO only)
A10: 1 · ROLES
A11: Role | B11: Owns | C11: Hard deadline | D11: Escalates to
A12: Sub Lead | B12: Weekly ops, action log, Top Risk draft, pack narrative | C12: Action log every week; pack inputs by BD8 | D12: COO
A13: COO | B13: Health, Portfolio Active, recovery plans, SS priority | C13: Portfolio Active by BD15 | D13: Partner / Visionary (Core §6–§9)
A14: Finance (SS) | B14: Close, recs, pack publish, Roll-up column | C14: Pack BD10–12 | D14: COO same day if SLA miss
A15: Thesis Partner | B15: Recovery approval, quarterly strategy | C15: At Risk plan by day 10 | D15: Visionary if Critical/capital
A17: 2 · WEEKLY OPERATING REVIEW (REAL-WORLD)
A18: Cadence: weekly, 30–45 min. Owner: Sub Lead. COO joins if Health ≠ On Track, or at least biweekly for Watch. Required artifact: action log (owner + due date).
A19: # | B19: Block | C19: Min | D19: Example prompt / what good looks like | E19: Required output
A20: 1 | B20: CORE KPI flash | C20: 8 | D20: Example: “ARR $480k (+8% MoM), burn $30k, cash $540k, runway 18. Red? None. Watch: concentration 22%.” | E20: Name any red metric
A21: 2 | B21: Customers / pipeline or delivery | C21: 8 | D21: SaaS: top 5 pipeline + stuck stage. Recruit 619: placements this week + fill-time slips. Services: backlog vs capacity. | E21: One weekly priority
A22: 3 | B22: People & capacity | C22: 5 | D22: Example: “AE role open 34 days → raise to SS HR. No attrition.” | E22: Hire/SS ask or none
A23: 4 | B23: Risks & Health triggers | C23: 8 | D23: Check Core §6: plan miss, runway bands, concentration, pack miss. Example Top Risk: “Enterprise cycle slip — Owner: CRO — due Fri.” | E23: Top Risk draft if not On Track
A24: 5 | B24: Shared Services blockers | C24: 5 | D24: Example: “Legal ticket #442 MSA — SLA day 4 of 5. Escalate tomorrow if no mark-up.” | E24: Escalate or close ticket
A25: 6 | B25: Decisions & actions | C25: 6 | D25: Close prior actions or re-date once. New actions only with owner+date. | E25: Updated action log
A26: Hygiene rules: (1) No log = meeting didn’t happen. (2) At Risk/Critical → COO attends or gets same-day notes. (3) Do not debate CORE definitions in this meeting — escalate definition issues to COO offline.
A28: 3 · MONTHLY PACK PROCESS (END-TO-END)
A29: Day | B29: Activity | C29: Owner | D29: Example / checklist | E29: System
A30: BD1–8 | B30: Sub Lead pack inputs | C30: Sub Lead | D30: Checklist: bank access ok? payroll changes listed? revenue method unchanged? top customer % calculated? open SS tickets listed? | E30: Pack folder
A31: BD1–10 | B31: Finance close + bank recs | C31: Finance (SS) | D31: Example fail: missing credit card feed → flag Sub Lead day 3, not day 10. | E31: QBE
A32: BD10–12 | B32: Publish CORE pack + fill Roll-up column | C32: Finance + Sub Lead | D32: Pack must include CORE P&L lines + CORE KPIs (Core §3). FLEX (e.g. placements) in appendix only. | E32: Pack + Portfolio Roll-up
A33: BD12–15 | B33: Health + Top Risk + Active $ fields | C33: COO | D33: Compare pack to plan ±15%. Apply Core §6. Example: 2nd month miss → At Risk even if team “feels fine.” | E33: Portfolio Active
A34: BD15 | B34: Performance Review meeting | C34: COO hosts | D34: Agenda: pack vs plan · Health · Top Risk · SS asks · recovery if needed. 45–60 min. | E34: Action log
A35: BD15 | B35: Firm pulse visible | C35: COO / Partner read | D35: Command Center Portfolio Health Pulse + financials refresh via formulas | E35: Command Center
A36: SLA miss: Pack not available BD12 → Finance notifies COO same day. 2nd consecutive miss → Health ≤ At Risk (Core §9C).
A38: 4 · RISK & HEALTH MANAGEMENT (EXAMPLES)
A39: Authority: Core §6 Health matrix. Below = how it shows up in real life.
A40: Situation (example) | B40: Likely Health | C40: Sub Lead does now | D40: COO does now
A41: ARR +6% vs plan, runway 16, top customer 18% | B41: On Track | C41: Normal weekly; Top Risk optional | D41: Confirm pack; no special cadence
A42: Missed plan month 1 by 18%; runway 11 | B42: Watch | C42: Top Risk + mitigation owner+date this week | D42: Attend next weekly; Partner informed
A43: Missed plan 2 months; top client 32% with churn signal | B43: At Risk | C43: Draft recovery milestones in 5 bd | D43: Plan approved ≤10 bd; biweekly checks; Partner engaged
A44: Runway 5 months; or payroll dual-control broken | B44: Critical | C44: Notify COO same day; pause non-essential spend if directed | D44: War room ≤48h; Visionary; options paper
A45: Pack missed two months running | B45: At Risk (control) | C45: Support Finance immediately | D45: Set Health; notify Visionary path per §9C
A46: Hard rules: Only COO sets Health. Sub Lead never self-clears to On Track after incomplete handoff. Health improves max 1 step/month unless COO files evidence.
A48: 5 · SHARED SERVICES — PRACTICAL PLAYBOOK
A49: Full SLA table: Core §7 + SS Operating Model. Below = examples Sub Leads use every week.
A50: Service | B50: Good intake example | C50: Bad habit (do not) | D50: Escalate when
A51: Finance | B51: “Close week: CC feed linked; 3 new vendors with W-9s attached; need pack by BD11.” | C51: Shadow P&L in a private Google Sheet | D51: Pack late or cash unclear
A52: Legal | B52: Ticket: “Customer MSA — $180k ARR — need mark-up by Fri — redlines attached.” | C52: Sign MSA on DocuSign without ticket | D52: P0 day overdue or deal blocked
A53: HR | B53: “AE role brief attached; target start 6/1; budget approved in plan.” | C53: Verbal offer before packet | D53: Process bypass
A54: IT | B54: “P1: CRM down for sales team — started 09:12.” | C54: Shared admin password in Slack | D54: Any security incident same day
A55: Marketing | B55: “Campaign brief: Recruit 619 employer brand — budget $X — Q2.” | C55: Using old “619 Recruiting” brand assets | D55: Brand conflict / blocked launch
A56: Capacity rule: P0 firm/reg/closing → P1 live deal → P2 sub ops → P3 projects. COO stack-ranks firm-wide when queues collide.
A58: 6 · CORE KPI TOUCHPOINTS (SUB LEAD)
A59: Definitions/calc/roll-up: Core Structure §3 only. This table = when you look at each number.
A60: KPI Name | B60: Weekly flash | C60: Monthly pack | D60: Portfolio Active | E60: If off-plan, do this
A61: Revenue / ARR | B61: Yes | C61: Yes | D61: ARR ($k) | E61: Confirm Handoff method still locked
A62: MoM Growth % | B62: If available | C62: Yes | D62: MoM Growth | E62: Write 1–2 driver sentences in pack
A63: Gross Margin % | B63: Optional | C63: Yes | D63: Pack / Roll-up | E63: Investigate COGS spike with Finance
A64: Net Burn $k | B64: Yes | C64: Yes | D64: Net Burn ($k) | E64: Finish cash bridge before pack
A65: Ending Cash $k | B65: Yes | C65: Yes | D65: Cash ($k) | E65: Reconcile with Finance bank list
A66: Runway months | B66: Yes | C66: Yes | D66: Runway Mo | E66: If <12 → Top Risk same week
A67: Health | B67: Discuss triggers only | C67: COO sets | D67: Health | E67: Bring facts; never self-set
A68: Top Risk | B68: Draft if needed | C68: Required if not On Track | D68: Top Risk | E68: One sentence + named owner
A69: Customer concentration % | B69: Watch | C69: Yes | D69: Pack notes | E69: If >25% → FLAG path + Top Risk
A70: Headcount FTE | B70: As needed | C70: Yes | D70: Pack | E70: Open roles must match plan
A71: FLEX (module) | B71: Per playbook | C71: Appendix | D71: Not money totals | E71: e.g. Recruit 619 placements — Alignment tab
A73: 7 · ONBOARDING (FIRST 30 DAYS) — PRACTICAL
A74: Full RACI/gates: Core §8. Lightweight summary for leaders in seat:
A75: Week | B75: Must be true | C75: Example “done” evidence
A76: Wire day | B76: ENT-* exists; Partner on Handoff | C76: Entity Master row ENT-R619 / PF-R619 style
A77: Days 0–3 | B77: QBE + bank feed; doc folders 01–07 | C77: Can post a test expense; folders visible
A78: Days 0–7 | B78: Handoff Pack complete; Portfolio Active row; Health starts Watch | C78: Revenue method locked in writing; Active shows CORE fields
A79: By Day 14 | B79: First weekly Operating Review + action log | C79: Calendar invite + log with ≥1 dated action
A80: By Day 30 | B80: SS access + briefing | C80: Sub Lead can file Finance/Legal tickets
A81: First BD12 | B81: First full CORE pack + Roll-up column | C81: Pack PDF/sheet + Roll-up entity column non-blank
A82: Gate: Steps through Active row (Core §8 steps 1–5) before any On Track Health.
A84: 8 · QUARTERLY / ANNUAL
A85: Cadence | B85: Meeting | C85: Owner | D85: Output
A86: Quarterly | B86: Strategy & Planning | C86: COO + Partner | D86: Written 90-day plan + resource/capital asks
A87: Annual | B87: Business Review + Audit | C87: COO | D87: Annual Audit Master + SA findings into firm risk
A89: 9 · COO MULTI-COMPANY PULSE (15 MIN WEEKLY)
A90: 1) Command Center → Portfolio Health Pulse (counts + attention). 2) Portfolio Active → filter At Risk/Critical → read Top Risk. 3) Ask Finance: any pack SLA breach this month? 4) SS queue: any P0/P1 > SLA? 5) Book yourself into next weekly for any non-On Track co.
A92: 10 · ACTION LOG TEMPLATE (COPY PER COMPANY)
A93: Date | B93: Action | C93: Owner | D93: Due | E93: Status
E94: Open
E95: Open
E96: Open
A98: LINKS
A99: Core Subsidiary Structure (rules) · Portfolio Active · Portfolio Roll-up · Command Center · Shared Services Operating Model · Entity Master · Portfolio Handoff · Annual Audit Master · Recruit 619 Alignment · How We Run

Sheet Recruit 619 Alignment
A1: Recruit 619 — Alignment to Tage VC Operating System
A2: Canonical brand: Recruit 619 (never “619 Recruiting”). This tab bridges the Recruit 619 playbook to Tage Core Subsidiary Structure, Portfolio, Shared Services, and roll-ups.
A4: 1 · IDENTITY (CANONICAL)
A5: Field | B5: Value | C5: Where stored
A6: Brand / display name | B6: Recruit 619 | C6: Entity Master.canonical_name · all playbooks
A7: Do not use | B7: 619 Recruiting, Recruit619, R619 (except IDs) | C7: Search-replace in playbook file
A8: entity_id | B8: ENT-R619 | C8: Entity Master
A9: portfolio_id | B9: PF-R619 | C9: Portfolio Active
A10: entity_type | B10: Subsidiary | C10: Entity Master
A11: industry_module | B11: Recruiting | C11: FLEX module on Core Structure §10
A12: track_origin | B12: VC Invest / Launch | C12: Deal Flow history
A13: qbe_class_or_company | B13: QBE: Recruit 619 | C13: Shared Services Finance
A14: Website | B14: recruit619.com | C14: Public / marketing
A16: 2 · CORE + FLEX KPI MAP (PLAYBOOK ↔ TAGE)
A17: Tage kpi_key / Name | B17: Type | C17: Recruit 619 playbook label (use this name) | D17: Calculation (align to Core Structure §3) | E17: Roll-up to Portfolio | F17: Report to
A18: Revenue / ARR | B18: CORE | C18: Recruit 619 Revenue ($k) | D18: Recognized recruiting revenue for period (lock method in Handoff) | E18: SUM | F18: Portfolio Active ARR ($k)
A19: MoM Growth % | B19: CORE | C19: Recruit 619 MoM Growth | D19: (Rev_t − Rev_t−1) ÷ Rev_t−1 | E19: Portfolio weighted via ΣRev | F19: Portfolio Active MoM Growth
A20: Gross Margin % | B20: CORE | C20: Recruit 619 Gross Margin | D20: (Revenue − direct placement/COGS) ÷ Revenue | E20: ΣGP ÷ ΣRev | F20: Monthly pack → Roll-up
A21: Net Burn $k | B21: CORE | C21: Recruit 619 Net Burn | D21: Cash bridge; 0 if cash generative | E21: SUM | F21: Portfolio Active Net Burn
A22: Ending Cash $k | B22: CORE | C22: Recruit 619 Cash | D22: Operating bank EOM | E22: SUM | F22: Portfolio Active Cash
A23: Runway months | B23: CORE | C23: Recruit 619 Runway | D23: Cash ÷ Net Burn if burn>0 else n/a | E23: MIN flag if <12 | F23: Portfolio Active Runway
A24: Health | B24: CORE | C24: Recruit 619 Health | D24: On Track|Watch|At Risk|Critical per Core §6 | E24: COUNT by status | F24: Portfolio Active Health
A25: Top Risk | B25: CORE | C25: Recruit 619 Top Risk | D25: One sentence + owner | E25: LIST if not On Track | F25: Portfolio Active Top Risk
A26: Customer concentration % | B26: CORE | C26: Recruit 619 Client Concentration | D26: Largest client revenue ÷ total (flag >25%) | E26: FLAG not average | F26: Monthly pack
A27: Headcount FTE | B27: CORE | C27: Recruit 619 Headcount FTE | D27: FTE last calendar day | E27: SUM | F27: Monthly pack
A28: placements | B28: FLEX | C28: Recruit 619 Placements | D28: Count of filled roles in period | E28: SUM (module) | F28: Pack notes / module
... A30: gp_per_desk | B30: FLEX | C30: Recruit 619 GP per Desk | D30: Gross profit ÷ producing recruiter FTE | E30: Module only | F30: Pack notes
A31: Playbook naming rule: always prefix operational metrics with “Recruit 619 …” so exports map 1:1 to this table.
A33: 3 · SHARED SERVICES (ALIGN TO TAGE SS MODEL)
A34: Service | B34: Recruit 619 must | C34: Shared Services provides | D34: SLA (Tage standard) | E34: Playbook reference
A35: Finance | B35: Source docs; bill approves; review pack BD12; no shadow books | C35: QBE: Recruit 619 close, bank feed, pack | D35: Close BD10 | E35: Use name Recruit 619 on all finance packs
A36: Legal | B36: Ticket client/MSAs; no unsigned material client terms | C36: Templates, negotiation, risk flags | D36: 5 bd / 48h rush | E36: Client contract playbook
A37: HR | B37: Role briefs for recruiters; compliant offers only | C37: Recruiting support, packets, policies | D37: Offer pack 5 bd post-decision | E37: Hiring playbook
A38: IT | B38: Same-day incident report; ATS/access via IT | C38: Access, security, core tools | D38: P1 4h; access 2 bd | E38: Tools stack list
A39: Marketing | B39: Brand as Recruit 619; campaigns via ticket | C39: Brand, site, campaigns | D39: Quarterly plan | E39: Always Recruit 619 not 619 Recruiting
A40: Escalate: Sub Lead → Service Lead → COO → Visionary (capital only). Same path as Core Structure §7 / SS Model.
A42: 4 · OPERATING RHYTHM (MATCHES CORE §5)
A43: Cadence | B43: Recruit 619 meeting | C43: Feeds Tage
A44: Weekly | B44: Recruit 619 Operating Review (placements, desk, blockers) | C44: Action log; flash CORE KPIs
A45: Monthly | B45: Recruit 619 Performance Pack | C45: Portfolio Active PF-R619 + Portfolio Roll-up column
A46: Quarterly | B46: Recruit 619 90-day plan with COO + Partner | C46: Thesis check vs Launch path
A47: Annual | B47: Audit using SA library + Master Audit | C47: Firm annual review
A49: 5 · CONNECTION TO TAGE OS
A50: Tage tab | B50: Recruit 619 relationship
A51: Core Subsidiary Structure | B51: Mandatory CORE; Recruiting = FLEX module only
A52: Subsidiary Operating System | B52: COO rhythms, SA audit, playbooks apply to Recruit 619
A53: Entity Master | B53: ENT-R619 · canonical_name = Recruit 619
A54: Portfolio Active | B54: PF-R619 row; CORE fields only on grid; FLEX in pack notes
A55: Portfolio Roll-up | B55: Column for Recruit 619 Core P&L lines
A56: Shared Services Operating Model | B56: SLAs and Intuit/QBE automation for Recruit 619 entity
A57: Command Center | B57: Health counts include Recruit 619
A58: How We Run | B58: Subsidiary standard references Core Structure
A59: Separate Recruit 619 playbook file | B59: Detailed desk ops; must use brand Recruit 619 + KPI names in §2
A61: 6 · PLAYBOOK FILE SYNC CHECKLIST
A62: Item | B62: Done | C62: Notes
A63: Replace all “619 Recruiting” → “Recruit 619” in playbook | C63: Including titles, headers, diagrams
A64: KPI section uses §2 labels exactly | C64: CORE + FLEX names
A65: Health enum matches Core §6 | C65: On Track|Watch|At Risk|Critical
A66: SS section points to Tage Shared Services Operating Model | C66: No conflicting SLAs
A67: Monthly pack exports to Portfolio Active PF-R619 | C67: Owner: Sub Lead + Finance
A68: Link/URL to this Alignment tab noted in playbook cover | C68: Source of truth = Tage OS
A70: LINKS: Core Subsidiary Structure · Subsidiary Operating System · Entity Master · Portfolio Active · Portfolio Roll-up · Shared Services Operating Model · How We Run

Sheet Portfolio Handoff
A1: Tage VC — Portfolio Handoff Pack | Investment → Subsidiary COO
A2: Complete at wire. One pack per closed company. COO owns growth system after Day 0.
A4: COMPANY BRIEF
A5: Company | B5: Sample Closed Co
A6: Deal ID / Lead ID | B6: DE-000 / LD-099
A7: Close date | B7: 45993
A8: Tage path | B8: Launch
A9: Check / ownership | B9: $750k SAFE; ownership TBD at priced round
A10: Board / observer | B10: Board seat — Partner Name
A11: Investment thesis | B11: Operator-led GTM + compliance wedge in fragmented buyer workflow.
A12: Why we won / why now | B12: Founder-market fit; early design partners; clear 90-day milestones.
A14: WHAT GOOD LOOKS LIKE (12 MONTHS)
A15: KPI | B15: Baseline | C15: 12-mo target | D15: Owner
A16: ARR / revenue | B16: $0 pre | C16: $600k ARR | D16: CEO
A17: Customers / logos | B17: 3 design partners | C17: 25 paying | D17: CEO/GTM
A18: Gross margin | B18: n/a | C18: >70% | D18: CEO
A19: Cash runway | B19: 18 mo post-close | C19: >12 mo always | D19: CEO/Ops
A20: Key hire | B20: None | C20: Head of GTM | D20: COO support
A22: HANDOFF CHECKLIST
A23: Item | B23: Status | C23: Owner | D23: Link / notes
A24: Executed docs + cap table final | B24: Done | C24: Counsel
A25: Data room archive access for COO | B25: Done | C25: Associate
A26: Scorecard + Financial Model snapshot saved | B26: Done | C26: Partner
A27: 90-day operating plan agreed | B27: In Progress | C27: COO + CEO
A28: Reporting pack template (monthly) | B28: Not Started | C28: COO | D28: ARR, burn, runway, pipeline, hires, risks
A29: Board calendar + materials process | B29: Not Started | C29: Partner
A30: Intro to Tage operator bench | B30: Not Started | C30: COO
A31: Risk register + open DD follow-ups | B31: In Progress | C31: Partner
A32: Added to Portfolio Active tracker | B32: Done | C32: Associate
A34: COO FIRST 30 DAYS
A35: 1. Validate metrics with CEO (ARR, burn, pipeline stages).
A36: 2. Install weekly operating rhythm (metrics, blockers, decisions).
A37: 3. Map GTM system: ICP, funnel, conversion, capacity.
A38: 4. Identify 1–2 leverage projects Tage operators can run in 90 days.
A39: 5. Confirm cash controls, hiring plan, and next financing trigger.

Sheet Portfolio Active
A1: Tage VC — Portfolio Active | Subsidiary Ops Dashboard | Z1: On Track
A2: One row per company · COO owns Health + Top Risk · Blue = CORE inputs · Match Roll-up by BD15 · Command Center counts Health live | Z2: Watch
A3: ⚠ DATA FRESHNESS | B3: DEADLINES | C3: MATCH RULE | D3: OWNER | Z3: At Risk
A4: CORE $ = same-period pack / Roll-up by BD15. Health+Top Risk COO only (≤48h if Critical). Set Last Update each refresh. | B4: BD15 monthly | C4: ARR/Burn/Cash/Runway must = Portfolio Roll-up entity col for Period B13. If not → STALE (Command Center will flag). | D4: COO | E4: At risk | F4: =COUNTIF(TablePortfolio[Health],"At Risk")+COUNTIF(TablePortfolio[Health],"Critical") -> 0 | Z4: Critical
A5: Companies | B5: =COUNTA(TablePortfolio[PF ID]) -> 3 | C5: On track | D5: =COUNTIF(TablePortfolio[Health],"On Track") -> 3 | E5: At risk+ | F5: =COUNTIF(TablePortfolio[Health],"At Risk")+COUNTIF(TablePortfolio[Health],"Critical") -> 0
A6: PF ID | B6: Company | C6: Deal ID | D6: Path | E6: Close Date | F6: COO Owner | G6: Board Lead | H6: ARR ($k) | I6: MoM Growth | J6: Net Burn ($k) | K6: Runway Mo | L6: Cash ($k) | M6: Health | N6: Top Risk | O6: Next Milestone | P6: Last Update | Q6: Notes
A7: PF-001 | B7: Sample Closed Co | C7: DE-000 | D7: Launch | E7: 45993 | F7: COO — Ops Lead | G7: Partner | H7: 120 | I7: 0.12 | J7: 45 | K7: 14 | L7: 630 | M7: On Track | N7: Early GTM conversion | O7: 10 paying logos | P7: 46096 | Q7: Need Head of GTM search
A8: PF-002 | B8: Instant NDA | C8: DE-LAU-01 | D8: Launch | E8: 45809 | F8: COO — Ops Lead | G8: Partner | H8: 480 | I8: 0.08 | J8: 30 | K8: 18 | L8: 540 | M8: On Track | N8: Enterprise sales cycle | O8: First 5 enterprise logos | P8: 46091 | Q8: Legal tech — portfolio disclosure OK
A9: PF-R619 | B9: Recruit 619 | C9: DE-R619 | D9: Launch | F9: COO — Ops Lead | G9: Partner | H9: 0 | I9: 0 | J9: 0 | K9: 0 | L9: 0 | M9: On Track | N9: Client concentration | O9: Hit placement plan | Q9: Recruit 619 — use Alignment tab

Sheet Portfolio Roll-up
A1: Tage VC — Portfolio Roll-up | Subsidiary → Portfolio → Firm
A2: Monthly money proof · Core §3 methods · Blue inputs · Black formulas · E Portfolio · F Firm · G Consolidated · Sync CORE $ to Active after pack
A3: ⚠ DATA FRESHNESS | B3: 1) Set Period B13 2) Blue inputs = that month only 3) After pack: copy CORE $ → Portfolio Active 4) COO Health by BD15 5) Command Center must show FRESH on ARR/Burn/Cash 6) Never mix months or put FLEX in E–G
A4: 0 · HOW TO USE (READ FIRST)
A5: Step | B5: What you do | C5: Result
A6: 1 | B6: Set Period (B13). Finance closes each sub in QBE for that month. | C6: Clean books by entity_id
A7: 2 | B7: Enter blue cells only under each sub column (Revenue, COGS, OpEx, Net Burn, Cash). Firm OpEx/Cash go in column F only. | C7: Section A inputs filled
A8: 3 | B8: Leave black cells alone. E = SUM of B:D for money. Gross Margin E20 = E19/E17 (WEIGHTED). Runway E25 = MIN of numeric B25:D25. Row 26 FLAGs any runway under 12 months. | C8: Portfolio math correct
A9: 4 | B9: Copy each sub Revenue/Burn/Cash/Runway into Portfolio Active for same period. COO sets Health + Top Risk on Portfolio Active (not calculated here). | C9: Ops dashboard current
A10: 5 | B10: Use Section C health COUNTs and Section D Firm Snapshot in Command Center / Visionary monthly review. | C10: Firm pulse ready
A11: 6 | B11: FLEX KPIs (placements, NRR, etc.) stay in sub packs — never enter columns E–G. | C11: CORE vs FLEX respected
A12: Legend: SUM=$ · WEIGHTED=% from totals · MIN/FLAG=risk · COUNT=health on Active · FLEX not in E–G
A13: Period (YYYY-MM) | B13: 2026-03 | C13: Currency | D13: USD $k
A14: ⚠ Period B13 = pack month for ALL blue cells below. Mixing months breaks Command Center FRESH checks.
A15: A · CORE P&L BY ENTITY ($k)
A16: Line | B16: Sample Closed Co | C16: Instant NDA | D16: Recruit 619 | E16: PORTFOLIO TOTAL | F16: FIRM (mgmt only) | G16: CONSOLIDATED | H16: Method | I16: Note
A17: Revenue / ARR | B17: 120 | C17: 480 | D17: 0 | E17: =B17+C17+D17 -> 600 | F17: 0 | G17: =E17+F17 -> 600 | H17: SUM | I17: → Portfolio Active ARR ($k) | N17: Runway helper (burn>0 only)
A18: COGS | B18: 25 | C18: 90 | D18: 0 | E18: =B18+C18+D18 -> 115 | F18: 0 | G18: =E18+F18 -> 115 | H18: SUM | I18: Direct costs only | N18: =IF(B23>0,B24/B23,NA()) -> 14
A19: Gross Profit | B19: =B17-B18 -> 95 | C19: =C17-C18 -> 390 | D19: =D17-D18 -> 0 | E19: =E17-E18 -> 485 | F19: =F17-F18 -> 0 | G19: =G17-G18 -> 485 | H19: Calc then SUM | I19: WEIGHTED margin uses this | N19: =IF(C23>0,C24/C23,NA()) -> 18
A20: Gross Margin % | B20: =IFERROR(B19/B17,0) -> 0.79166667 | C20: =IFERROR(C19/C17,0) -> 0.8125 | D20: =IFERROR(D19/D17,0) -> 0 | E20: =IFERROR(E19/E17,0) -> 0.80833333 | F20: =IFERROR(F19/F17,0) -> 0 | G20: =IFERROR(G19/G17,0) -> 0.80833333 | H20: WEIGHTED | I20: Portfolio E20 = E19/E17 NOT avg(B20:D20) | N20: =IF(D23>0,D24/D23,NA()) -> #N/A
A21: OpEx | B21: 80 | C21: 250 | D21: 0 | E21: =B21+C21+D21 -> 330 | F21: 120 | G21: =E21+F21 -> 450 | H21: SUM | I21: Firm OpEx only in col F
A22: Op. Income / EBITDA proxy | B22: =B19-B21 -> 15 | C22: =C19-C21 -> 140 | D22: =D19-D21 -> 0 | E22: =E19-E21 -> 155 | F22: =F19-F21 -> -120 | G22: =G19-G21 -> 35 | H22: Calc
A23: Net Burn | B23: 45 | C23: 30 | D23: 0 | E23: =B23+C23+D23 -> 75 | F23: 0 | G23: =E23+F23 -> 75 | H23: SUM | I23: → Portfolio Active Net Burn
A24: Ending Cash | B24: 630 | C24: 540 | D24: 0 | E24: =B24+C24+D24 -> 1170 | F24: 800 | G24: =E24+F24 -> 1970 | H24: SUM | I24: → Portfolio Active Cash; F24 = firm treasury
A25: Runway months | B25: =IF(B23<=0,"n/a",IFERROR(ROUND(B24/B23,1),"")) -> 14 | C25: =IF(C23<=0,"n/a",IFERROR(ROUND(C24/C23,1),"")) -> 18 | D25: =IF(D23<=0,"n/a",IFERROR(ROUND(D24/D23,1),"")) -> n/a | E25: =IF(COUNT(B25:D25)=0,"n/a",ROUND(MIN(B25:D25),1)) -> 14 | F25: — | G25: — | H25: MIN / FLAG | I25: E25 = MIN of burning entities only (not average)
A26: Runway <12 FLAG | B26: =IF(AND(ISNUMBER(B25),B25<12),"FLAG","ok") -> ok | C26: =IF(AND(ISNUMBER(C25),C25<12),"FLAG","ok") -> ok | D26: =IF(AND(ISNUMBER(D25),D25<12),"FLAG","ok") -> ok | E26: =IF(OR(B26="FLAG",C26="FLAG",D26="FLAG"),"REVIEW","ok") -> ok | H26: MIN / FLAG | I26: Any FLAG → escalate per Core health rules
A28: B · METHOD CHEAT SHEET (Core Structure §3A)
A29: Method | B29: Applies to | C29: On this sheet | D29: Never
A30: SUM | B30: Revenue, COGS, OpEx, Burn, Cash, Headcount | C30: Col E = B+C+D; Col G = E+F | D30: Put Firm costs in subsidiary cols
A31: WEIGHTED | B31: Gross Margin %, MoM Growth % | C31: E20 = E19/E17 (rebuild from sums) | D31: Average B20:D20
A32: MIN / FLAG
A33: COUNT | B33: Health | C33: Section C COUNTIF on Portfolio Active | D33: Score health 1–4 and average
A34: LIST / FLAG | B34: Top Risk; concentration | C34: Not in P&L grid — ops pack / Active filter | D34: Roll text into one total
A35: FLEX | B35: placements, NRR, fill time, etc. | C35: Not in cols E–G | D35: SUM into Portfolio Total
A37: C · HEALTH COUNTS (FROM PORTFOLIO ACTIVE)
A38: Status | B38: Count | C38: Feeds
A39: On Track | B39: =IFERROR(COUNTIF(TablePortfolio[Health],"On Track"),0) -> 3 | C39: Command Center portfolio health
A40: Watch | B40: =IFERROR(COUNTIF(TablePortfolio[Health],"Watch"),0) -> 0 | C40: COO watch list
A41: At Risk | B41: =IFERROR(COUNTIF(TablePortfolio[Health],"At Risk"),0) -> 0 | C41: Partner escalation
A42: Critical | B42: =IFERROR(COUNTIF(TablePortfolio[Health],"Critical"),0) -> 0 | C42: Visionary + war room
A43: Active companies | B43: =IFERROR(COUNTA(TablePortfolio[PF ID]),0) -> 3 | C43: Must match entity columns maintained
A45: D · FIRM VIEW (HOW COLS E / F / G WORK)
A46: Column | C46: Calculation
A47: B–D Subsidiaries | B47: Each portfolio company Core P&L inputs | C47: Blue from QBE pack for Period
A48: E Portfolio Total | B48: All subsidiaries combined (ops portfolio) | C48: SUM B:D (money); WEIGHTED % from E sums
A49: F Firm (mgmt only) | B49: Tage VC management company — not a sub | C49: Blue firm OpEx/cash only; revenue usually 0
A50: G Consolidated | B50: Full economic view portfolio + firm | C50: E + F
A51: Why E vs F vs G? | B51: E = all subsidiaries only (ops portfolio). F = Tage management company costs/cash only — never a sub. G = E+F full economic view for Visionary.
A52: Firm snapshot (for Visionary / monthly firm review)
A53: Portfolio revenue $k | B53: =E17 -> 600
A54: Portfolio gross margin % | B54: =E20 -> 0.80833333
A55: Portfolio net burn $k | B55: =E23 -> 75
A56: Portfolio cash $k | B56: =E24 -> 1170
A57: Firm-only cash $k | B57: =F24 -> 800
A58: Consolidated cash $k | B58: =G24 -> 1970
A59: Min runway (burning subs) | B59: =E25 -> 14
A60: Runway breach any sub? | B60: =E26 -> ok
A61: Connection: This tab proves numbers. Portfolio Active holds ops Health/Top Risk. Command Center reads health COUNTs (C) + snapshot (D) + deal funnel.
A62: E · MAP TO PORTFOLIO ACTIVE
A63: Portfolio Active field | B63: Source on this tab / process
A64: ARR ($k) | B64: Entity column Revenue row (e.g. B17) for that company
A65: MoM Growth | B65: Compute from this month vs prior period revenue (WEIGHTED at portfolio)
A66: Net Burn ($k) | B66: Entity Net Burn row
A67: Runway Mo | B67: Entity Runway row (n/a if not burning)
A68: Cash ($k) | B68: Entity Ending Cash row
A69: Health / Top Risk | B69: Set by COO on Portfolio Active (not calculated here); counts appear in §C
A71: F · MAINTAINER NOTES
A72: Add a company: insert column before E, copy B formulas pattern, add name in row 16, extend SUM ranges B:x.
A73: Prior period: keep a copy of this sheet or columns for t−1 to support MoM WEIGHTED at portfolio.
A74: Authority: Core Subsidiary Structure §3. Brand: Brand & Styling Guide.
A76: LINKS: Core Subsidiary Structure §3 · Portfolio Active · Command Center · Entity Master · Recruit 619 Alignment · Firm Operations · Shared Services Operating Model · Brand & Styling Guide

Sheet Shared Services Operating Model
A1: Tage VC — Shared Services Operating Model
A2: Practical cadences for Finance, Legal, HR, Tech, Marketing. Serves Firm + all Subsidiaries. Owner: COO (stack-rank); Service Leads execute. Blue = firm-specific inputs.
A4: 0 · GLOBAL RULES
A5: Intake: ticket (or close checklist for Finance). Priority: P0 firm/reg/closing → P1 live deal CP → P2 subsidiary ops → P3 projects.
A6: Escalate: Service Lead → COO → Visionary (capital/reputation only). SLA breach logged monthly to Firm Operations.
A7: Tools spine: Intuit Enterprise / QuickBooks Enterprise (QBE) + bank feeds · ticket system · this workbook · data room.
A9: 1 · ACCOUNTING & FINANCE
A10: Task / Activity | B10: Frequency | C10: Owner | D10: Automation Potential | E10: Notes / Tools
A11: Bank feed match & exception clear | B11: Weekly | C11: Finance Lead | D11: High | E11: QBE bank feeds; rules for recurring vendors
A12: AP bill entry + approval queue | B12: Weekly | C12: Finance + Sub approvers | D12: High | E12: Bill Pay / Bill.com or QBE Bill Pay; dual approval >threshold
A13: AR invoice send + collections touch | B13: Weekly | C13: Finance + Sub Lead | D13: High | E13: Recurring invoices in QBE; auto-reminders
A14: Cash position flash (firm + material subs) | B14: Weekly | C14: Finance Lead | D14: Medium | E14: QBE cash report → Command Center note
A15: Payroll journal import / review | B15: Per payroll | C15: Finance | D15: High | E15: Payroll sync to QBE (Intuit Payroll or Gusto→QBE)
A16: Month-end close checklist execute | B16: Monthly | C16: Finance Lead | D16: High | E16: QBE Close Management / checklist; target BD10
A17: Reconcile all balance sheet accounts | B17: Monthly | C17: Finance | D17: Medium | E17: QBE recon tools; bank + CC + loan
A18: Subsidiary monthly pack (P&L, BS, cash, burn, runway) | B18: Monthly | C18: Finance + Sub Lead | D18: High | E18: Memorized reports / management reports → Portfolio Active
A19: Firm consolidated view for Visionary | B19: Monthly | C19: Finance Lead | D19: Medium | E19: Classes/locations per entity in QBE; firm P&L
A20: Sales tax / nexus check (if applicable) | B20: Monthly / Quarterly | C20: Finance | D20: High | E20: Intuit sales tax or Avalara link
A21: Budget vs actual review with COO | B21: Monthly | C21: Finance + COO | D21: Medium | E21: Budgets in QBE; variance report
... A26: Finance annual audit items (see also Master Audit) | B26: Annual | C26: Finance Lead | D26: Medium | E26: Bank confirms, cutoff, related party, equity rollforward
A28: Finance automation (Intuit focus): bank rules · recurring bills/invoices · close checklist · memorized reports · payroll import · multi-entity classes · scheduled email reports to COO/Visionary.
A30: 2 · LEGAL & COMPLIANCE
A31: Task / Activity | B31: Frequency | C31: Owner | D31: Automation Potential | E31: Notes / Tools
A32: Ticket triage & SLA clock | B32: Weekly | C32: Counsel | D32: Medium | E32: Ticket tool; P0 closing/litigation first
A33: Live deal CP / PSA-SPA support queue | B33: Weekly | C33: Counsel | D33: Low | E33: Link Deal Tasks / M&A Tasks / RE Tasks
A34: Contract template hygiene check | B34: Monthly | C34: Counsel | D34: Low | E34: Version control in knowledge base
A35: Open matters & deadline calendar review | B35: Monthly | C35: Counsel | D35: Medium | E35: Calendar + matter list
A36: Entity good-standing / registered agent check | B36: Quarterly | C36: Counsel | D36: Medium | E36: Secretary of state alerts where available
A37: Insurance certificate & coverage gap review | B37: Quarterly | C37: Counsel + Ops | D37: Low | E37: Broker portal
A38: IP / trademark docket (if any) | B38: Semi-annual | C38: Counsel | D38: Medium | E38: Docketing tool
A39: Policy refresh (privacy, employee handbook legal) | B39: Annual | C39: Counsel + HR | D39: Low | E39: With HR annual cycle
A40: Litigation hold / dispute register update | B40: As needed + Annual | C40: Counsel | D40: Low | E40: Firm risk register input
A41: Legal annual audit items | B41: Annual | C41: Counsel | D41: Low | E41: Entities, contracts sample, IP, insurance, disputes
A43: Legal automation: intake forms · e-sign (DocuSign) · matter deadlines · template library · calendar holds. Not full legal judgment.
A45: 3 · HUMAN RESOURCES
A46: Task / Activity | B46: Frequency | C46: Owner | D46: Automation Potential | E46: Notes / Tools
A47: Open req / pipeline status with hiring managers | B47: Weekly | C47: HR Lead | D47: Medium | E47: ATS; subsidiary hiring playbook
A48: Onboarding checklist (firm + sub) | B48: Per hire | C48: HR + Manager | D48: High | E48: Checklist; auto IT access ticket
A49: Payroll change audit (new/term/comp) | B49: Per payroll | C49: HR + Finance | D49: High | E49: Payroll → QBE
A50: Headcount vs plan to COO | B50: Monthly | C50: HR Lead | D50: Medium | E50: Firm capacity KPI
A51: Performance cycle checkpoints | B51: Quarterly / Annual | C51: HR + Managers | D51: Medium | E51: Standard calendar
A52: Handbook acknowledgment | B52: Annual + hire | C52: HR | D52: High | E52: E-sign
A53: Benefits open enrollment | B53: Annual | C53: HR | D53: Medium | E53: Broker portal
A54: HR annual audit items | B54: Annual | C54: HR Lead | D54: Medium | E54: I-9, classification, files, claims
A55: HR automation: ATS · onboarding checklists · payroll sync QBE · e-sign policies.
A56: HR annual audit items | B56: Annual | C56: HR Lead | D56: Medium | E56: I-9, classification, files, handbooks, claims
A57: 4 · TECHNOLOGY / IT
A58: Task / Activity | B58: Frequency | C58: Owner | D58: Automation Potential | E58: Notes / Tools
A59: Ticket / incident triage | B59: Daily / Weekly | C59: Tech Lead | D59: Medium | E59: P0 security · P1 outage
A60: Joiners / movers / leavers access | B60: As needed | C60: Tech Lead | D60: High | E60: IdP; pair with HR term
A61: Backup / restore sample test | B61: Monthly | C61: Tech Lead | D61: High | E61: Cloud backup reports
A62: MFA / admin access review | B62: Monthly | C62: Tech Lead | D62: Medium | E62: IdP admin audit
A63: SaaS license & spend cleanup | B63: Monthly | C63: Tech + Finance | D63: Medium | E63: QBE vendor spend
A64: Device compliance / MDM | B64: Monthly | C64: Tech Lead | D64: High | E64: MDM console
A65: DR / incident tabletop | B65: Annual | C65: Tech + COO | D65: Low | E65: Lessons logged
A66: IT annual audit items | B66: Annual | C66: Tech Lead | D66: Medium | E66: Access, backups, vendors, incidents
A67: IT automation: IdP provisioning · MDM · backup alerts · ticket SLAs. Protect QBE admin.
A68: DR / incident tabletop | B68: Annual | C68: Tech Lead + COO | D68: Low | E68: Document lessons
A69: 5 · MARKETING (SHARED SUPPORT)
A70: Task / Activity | B70: Frequency | C70: Owner | D70: Automation Potential | E70: Notes / Tools
A71: Inbound routing to VC / M&A / RE track | B71: Weekly | C71: Marketing + Associate | D71: High | E71: Form → correct pipeline
A72: Content / SEO performance | B72: Monthly | C72: Marketing Lead | D72: Medium | E72: Analytics
A73: Brand & website hygiene | B73: Monthly | C73: Marketing Lead | D73: Low | E73: CMS
A74: Subsidiary campaign support queue | B74: Monthly | C74: Marketing Lead | D74: Medium | E74: Ticket + quarterly brief
A75: Quarterly plan vs firm priorities | B75: Quarterly | C75: Marketing + Visionary path | D75: Low | E75: Firm Ops strategy
A76: Marketing annual audit items | B76: Annual | C76: Marketing Lead | D76: Low | E76: Spend ROI, lead quality, claim compliance
A77: Marketing automation: form routing · CRM · email sequences. Human approve founder pass emails.
A78: Subsidiary campaign support queue | B78: Monthly | C78: Marketing Lead | D78: Medium | E78: Ticket + quarterly brief
A79: 6 · CROSS-LAYER LINKS
A80: Finance packs → Portfolio Active + Command Center runway flags | B80: Annual | C80: Visionary + Marketing | D80: Low | E80: With annual plan
A81: Legal on live deals → Deal / M&A / RE Tasks Evidence | B81: Annual | C81: Marketing Lead | D81: Low | E81: Brand consistency, spend ROI, lead quality, compliance claims
A82: HR headcount → Firm capacity KPI + Subsidiary hiring
A83: IT offboarding same day as HR term; lock QBE admin
A84: Marketing inbound → correct pipeline same day
A85: 6 · CROSS-LAYER LINKS
A86: LINKS: Firm Operations · Subsidiary Operating System · Portfolio Active · Command Center · How We Run · Annual Audit Master · §7 Grok+Cursor Ticketing
A87: Legal tickets on live deals → Deal / M&A / RE Tasks Evidence column
A88: HR headcount → Firm capacity KPI + Subsidiary hiring playbook
A89: IT offboarding → same day as HR termination; protect QBE admin access
A90: Marketing inbound → correct Pipeline (VC vs M&A vs RE) same day
A92: LINKS: Firm Operations · Sub OS · Portfolio Active · Command Center · How We Run · Annual Audit · §7 Grok+Cursor Ticketing & Automation
A94: 7 · GROK + CURSOR TICKETING & AUTOMATION
A95: Policy: COO · Domain: Service Leads · System: Admin. Implement bands + forbid-list server-side (not prompt-only). Day-to-day users: read At a Glance + Forbid-list. Builders: full section.
A97: AT A GLANCE (START HERE)
A98: Topic | B98: Rule | C98: Human always
A99: Flow | B99: Intake → Diagnose (band + confidence) → Act → Resolve → Learn | C99: Requester opens ticket
A100: AUTO | B100: Allow-listed only · confidence ≥90% · low risk · always logged | C100: Owns allow-list policy (COO)
A101: DRAFT | B101: Confidence 60–89% or medium complexity → draft + recommend | C101: Approve / Edit / Reject before side effects
A102: ESCALATE | B102: Confidence <60% · P0 · ambiguous · or forbid-list hit | C102: Service Lead / COO / Partner acts
A103: Never auto | B103: Wires · Health · capital DocuSign Send · CORE changes · external founder/investor email · IC · silent P0 close | C103: See Forbid-list table
A104: Growth | B104: v0 shadow → v1 allow-list AUTO → v2 expand (50+ drafts, ≤2% edits, COO sign-off) → v3 + monthly demote | C104: COO signs every AUTO expansion
A106: 7A · PURPOSE
A107: Cut repetitive ticket load and speed diagnosis while humans stay accountable. Never bypass capital, Health, or capital DocuSign controls.
A109: 7B · LIFECYCLE (COMPACT)
A110: Step | B110: Actor | C110: Does | D110: Must log
A111: 1 Intake | B111: Human | C111: Ticket: service, P0–P3, links, deadline, outcome | D111: ticket_id, who, priority, service
A112: 2 Diagnose | B112: Grok/Cursor | C112: Classify service + AUTO/DRAFT/ESCALATE; confidence %; context pull | D112: band, confidence, reasoning, refs
A113: 3 Act | B113: Agent ± human | C113: Execute / wait approve / escalate with recommendation | D113: action, payload hash, approval
A114: 4 Resolve | B114: Service Lead | C114: Close or take over with full pack | D114: resolution, override flag
A115: 5 Learn | B115: COO + Admin | C115: Monthly AUTO review; allow-list changes only in writing | D115: policy_version
...

Sheet Annual Audit Master Checklist
A1: Annual Audit Master Checklist — Firm + Subsidiaries | Z1: Not Started
A2: Master library. Copy block per Year and Scope (Firm or Company name). Status: Not Started | In Progress | Complete | N/A. Blue = inputs. | Z2: In Progress
Z3: Complete
A4: Year | B4: 2026 | C4: Scope (Firm or Company) | D4: Firm | E4: Lead auditor | F4: COO + Finance | Z4: N/A
A6: ID | B6: Domain | C6: Applies to | D6: Audit item | E6: Status | F6: Owner | G6: Evidence / finding | H6: Due
A7: AUD-F01 | B7: Finance | C7: Firm + Subs | D7: Bank reconciliations complete all material accounts | E7: Not Started | F7: Finance Lead
A8: AUD-F02 | B8: Finance | C8: Firm + Subs | D8: Dual control on wires; approval matrix current | E8: Not Started | F8: Finance Lead
A9: AUD-F03 | B9: Finance | C9: Firm + Subs | D9: Month close packs produced within BD10 SLA last 12 months | E9: Not Started | F9: Finance Lead
A10: AUD-F04 | B10: Finance | C10: Firm + Subs | D10: Related-party transactions disclosed and documented | E10: Not Started | F10: Finance + Counsel
A11: AUD-F05 | B11: Finance | C11: Firm + Subs | D11: 1099/W-2 and tax packages filed / with CPA | E11: Not Started | F11: Finance
A12: AUD-F06 | B12: Finance | C12: Subs | D12: Equity / cap table or membership rollforward ties to books | E12: Not Started | F12: Finance + Counsel
A13: AUD-L01 | B13: Legal | C13: Firm + Subs | D13: Entities in good standing; agents current | E13: Not Started | F13: Counsel
A14: AUD-L02 | B14: Legal | C14: Firm + Subs | D14: Material contracts inventory sample-tested | E14: Not Started | F14: Counsel
A15: AUD-L03 | B15: Legal | C15: Firm + Subs | D15: Litigation / dispute register complete | E15: Not Started | F15: Counsel
A16: AUD-L04 | B16: Legal | C16: Firm + Subs | D16: Insurance adequate (D&O, E&O, cyber, property) | E16: Not Started | F16: Counsel + Ops
A17: AUD-L05 | B17: Legal | C17: Subs | D17: IP ownership / assignments clean if product co | E17: Not Started | F17: Counsel
A18: AUD-H01 | B18: HR | C18: Firm + Subs | D18: I-9 / employment eligibility files complete | E18: Not Started | F18: HR Lead
... A30: AUD-O05 | B30: Firm Ops | C30: Firm | D30: Lessons learned log maintained for closed/walked deals | E30: Not Started | F30: Partners
A31: AUD-S01 | B31: Subsidiary | C31: Subs | D31: Run SA-01..SA-25 library from Subsidiary Operating System | E31: Not Started | F31: COO | G31: Per company
A32: AUD-S02 | B32: Subsidiary | C32: Subs | D32: Portfolio Active health accurate vs monthly pack | E32: Not Started | F32: COO
A34: How to use: set Year + Scope. Filter Applies to. Complete Status/Evidence. For each subsidiary, copy SA items from Subsidiary Operating System and paste below or duplicate sheet.
A35: LINKS: Shared Services Operating Model · Firm Operations · Subsidiary Operating System · Portfolio Active · Command Center

Sheet Firm Operations
A1: Firm Operations
A2: Layer 3 of 3: running Tage as a firm. Visionary owns direction + capital. COO owns Shared Services + subsidiary performance system.
A4: 1 · FIRM-LEVEL OPERATING RHYTHM
A5: Cadence | B5: Meeting | C5: Owner | D5: Purpose | E5: Output
A6: Weekly | B6: Command Center Review | C6: Partner | D6: Firm pulse, pipeline health, blockers | E6: Action items
A7: Bi-weekly | B7: Capital Allocation Review | C7: Visionary + Partners | D7: Capital across VC / M&A / RE | E7: Updated allocation view
A8: Monthly | B8: Firm Performance Review | C8: Visionary + COO | D8: Firm health, shared services, team | E8: Monthly firm report
A9: Quarterly | B9: Strategy & Priorities | C9: Visionary | D9: Direction, resources, new initiatives | E9: Quarterly priorities
A10: Annual | B10: Firm Review & Planning | C10: Visionary | D10: Full year + next year plan | E10: Annual operating plan
A12: 2 · CAPITAL ALLOCATION FRAMEWORK
A13: Track | B13: Target % | C13: Min % | D13: Max % | E13: Primary scoreboard | F13: Book owner
A14: VC Invest | B14: 0.4 | C14: 0.25 | D14: 0.55 | E14: Command Center deal $ + Pipeline | F14: Partners
A15: M&A Buy | B15: 0.35 | C15: 0.2 | D15: 0.5 | E15: M&A Pipeline EV + Closed Acquired | F15: Partners + COO
A16: RE Buy | B16: 0.25 | C16: 0.1 | D16: 0.4 | E16: RE Pipeline + RE Portfolio basis | F16: RE Sourcers + Partner
A17: Total target | B17: =SUM(B14:B16) -> 1 | C17: =IF(ABS(B17-1)>0.001,"Fix targets to 100%","OK") -> OK
A19: Deployment thresholds (set firm $ in blue)
A20: Band | B20: Amount (define) | C20: Approver | D20: Required docs | E20: Logged where
A21: Sourcer / associate authority | B21: $0 — propose only | C21: — | D21: Pipeline row + underwrite draft | E21: Pipeline / M&A / RE Active
A22: Partner band | B22: Up to $X (set) | C22: Partner | D22: Scorecard + model; IC lite if edge case | E22: Deal/MA/RE Active + IC log
A23: Partner + Visionary band | B23: Above $X to $Y | C23: Partner + Visionary | D23: Full IC memo + scorecard + model | E23: IC package archive
A24: Exception / outside allocation range | B24: Any size outside min–max track % | C24: Visionary | D24: Capital memo + rationale vs quarterly plan | E24: Quarterly capital memo
A25: 3 · SHARED SERVICES OPERATING MODEL
A26: Tracking: Bi-weekly Capital Allocation Review uses Command Center $ in flight + closed deploys. Rebalance if a track > Max % for 2 quarters without Visionary exception.
A27: Accounting & Finance | B27: Firm + All Subsidiaries | C27: Ticket or direct request | D27: Define per service | E27: Finance Lead
A28: 3 · SHARED SERVICES OPERATING SYSTEM
A29: Service | B29: Owner | C29: Users | D29: Intake | E29: Prioritization | F29: SLA examples | G29: Escalate
A30: Accounting & Finance | B30: Finance Lead | C30: Firm + all subs | D30: Close checklist + ticket | E30: P0 cash/wire · P1 close · P2 projects | F30: Close BD10; wires same-day if dual-ok | G30: COO → Visionary
A31: Legal | B31: Counsel | C31: Firm + all subs | D31: Ticket + deadline + docs | E31: P0 litigation/closing · P1 deals · P2 templates | F31: Std 5 bd; rush 48h | G31: Partner on deal risk
A32: Marketing | B32: Marketing Lead | C32: Firm + subs as needed | D32: Quarterly brief + ticket | E32: Firm brand first · then revenue campaigns | F32: Quarterly plan locked | G32: COO
A33: Technology | B33: Tech Lead | C33: Firm + all subs | D33: Ticket (incident/access/project) | E33: P0 security · P1 outage · P2 projects | F33: P1 4h; access 2 bd | G33: COO on security
A34: Human Resources | B34: HR Lead | C34: Firm + all subs | D34: Ticket + role brief | E34: Open roles by firm priority list | F34: Offer pack 5 bd post-decision | G34: COO / Visionary hiring
A35: New deal / investment approval | B35: Partner + Visionary | C35: IC | D35: Deal Scorecard + IC memo
A36: Prioritization rule: Firm closing / regulatory > live deal CPs > subsidiary P1 ops > projects. COO holds weekly Shared Services triage if backlog > SLA.
A37: New subsidiary or major initiative | B37: Visionary | C37: Partners + COO | D37: Strategy document
A38: 4 · GOVERNANCE — VISIONARY · PARTNERS · COO
A39: Decision | B39: Visionary | C39: Partners | D39: COO Subsidiaries | E39: Documentation
A40: Firm strategy & annual plan | B40: Decides | C40: Consulted | D40: Consulted (ops capacity) | E40: Annual operating plan
A41: Capital allocation across tracks | B41: Decides | C41: Consulted + data | D41: Consulted (sub cash needs) | E41: Quarterly capital memo
A42: New VC / M&A / RE deal approve | B42: Co-approves above band | C42: Leads IC + sponsor | D42: Consulted if integration load | E42: Scorecard + IC memo
A43: Subsidiary performance / health | B43: Informed | C43: Board / thesis owner | D43: Owns system + outcomes | E43: Portfolio Active + monthly pack
A44: Shared Services priorities | B44: Breaks ties | C44: Requestors | D44: Decides stack-rank | E44: Quarterly SS priorities
A45: Firm hiring (leadership) | B45: Decides | C45: Consulted | D45: Consulted | E45: Offer approval
A46: Major brand / public positions | B46: Decides | C46: Consulted | D46: Informed | E46: Comms note
A47: Documentation standards | B47: All | C47: Canonical Company name; archive don’t delete; blue=inputs
A48: Conflict rule: If Partner deal urgency conflicts with subsidiary capacity, COO flags; Visionary decides resource or timing tradeoff.
A49: 6 · FIRM-LEVEL RISK & COMPLIANCE
A50: 5 · FIRM-LEVEL REPORTING & KPIs
A51: KPI / view | B51: Audience | C51: Cadence | D51: Source tab | E51: Owner to produce
A52: Funnel: leads, Ready for DD, open tasks, blocked | B52: Partners | C52: Weekly | D52: Command Center | E52: Partner / Associate
A53: Capital in flight by track (VC/M&A/RE) | B53: Visionary + Partners | C53: Bi-weekly | D53: Command Center + allocation table | E53: Partner
A54: Conversion: Advanced to DD / Pass; RE purchased rate | B54: Partners | C54: Monthly | D54: Command Center closed logs | E54: Associate
A55: Portfolio health distribution + At Risk list | B55: Visionary + COO | C55: Monthly | D55: Portfolio Active · RE Portfolio | E55: COO
A56: Shared Services SLA breach count | E56: Service owners
A57: Cash at firm + subsidiary runway flags | E57: Finance Lead
A58: Team capacity vs open Critical work | E58: COO / Partners
A59: 4. COO of Subsidiaries owns subsidiary performance; Visionary owns firm direction and capital allocation.
A60: 6 · KNOWLEDGE MANAGEMENT & INTERNAL PROCESSES
A61: Artifact
A62: This workbook (OS) | B62: Pipelines, libraries, scorecards, ops models | C62: Partners + COO | D62: Live
A63: How We Run | B63: One-page wall chart — three layers | C63: Visionary | D63: When process changes
A64: Playbooks folder | B64: Subsidiary + firm SOPs; IC memo template | C64: COO / Ops | D64: Quarterly review
A65: Lessons learned log | B65: Pass reasons, failed deals, integration misses | C65: Partners + COO | D65: After each close/walk
A66: Deal / property archives | B66: Data rooms, executed docs, models | C66: Counsel + Associate | D66: At close
A67: Standards | B67: Canonical names; enums; archive≠delete; blue inputs | C67: All | D67: Always
A69: 7 · FIRM RISK, COMPLIANCE & GOVERNANCE CALENDAR
A70: Item | B70: Cadence | C70: Owner | D70: Month / trigger | E70: Last done | F70: Next due
A71: Entity annual report / franchise tax | B71: Annual | C71: Counsel / Finance | D71: Per jurisdiction
A72: Federal / state tax filings (firm) | B72: Annual / quarterly | C72: Finance | D72: Tax calendar
A73: Insurance renewals (D&O, E&O, cyber, property) | B73: Annual | C73: Ops / Finance | D73: Renewal month
A74: Firm risk register review | B74: Annual + ad hoc | C74: Visionary + COO | D74: Q4 or after major event
A75: Key person / succession plan update | B75: Annual | C75: Visionary | D75: With annual plan
A76: Cybersecurity / access review | B76: Semi-annual | C76: Tech Lead | D76: H1 / H2
A77: Subsidiary audit cycle kickoff | B77: Annual per co | C77: COO | D77: Per Portfolio Active anniversary
A78: Capital allocation reset | B78: Quarterly | C78: Visionary | D78: Each quarter start
A80: 8 · GOLDEN RULES
A81: 1. Deal flow ≠ portfolio ops ≠ firm ops — three layers, clear owners.
A82: 2. Shared Services serve firm and subsidiaries; COO stack-ranks; Visionary breaks ties.
A83: 3. Capital allocation is firm-level with VC / M&A / RE visibility via Command Center.
A84: 4. COO owns subsidiary performance system; Visionary owns direction and capital.
A85: 5. No capital deploy without docs matching the threshold band.
A87: LINKS
A88: Deal Flow: How We Run · Process Map · Command Center · all pipelines
A89: Subsidiaries: Subsidiary Operating System · Portfolio Handoff · Portfolio Active · RE Portfolio
A90: Build: Data Dictionary · Platform Spec · Cursor Brief
A92: 9 · TREASURY & CASH CONTROLS (FIRM)
A93: Activity | B93: Frequency | C93: Owner | D93: Automation / QBE
A94: Firm cash flash vs commitments | B94: Weekly | C94: Finance Lead | D94: Bank feeds + cash report
A95: Deploy schedule (approved deals not yet wired) | B95: Weekly | C95: Partner + Finance | D95: Deal Active / M&A / RE check sizes
A96: Intercompany / parent support tracking | B96: Monthly | C96: Finance | D96: QBE classes / JE policy
A97: Bank signatory & dual-control test | B97: Quarterly | C97: Finance + Visionary | D97: Bank portal review
A99: LINKS (updated): Shared Services Operating Model · Annual Audit Master Checklist · Command Center · Subsidiary Operating System · How We Run

Sheet Document Management & Workflow
A1: Document Management & DocuSign Workflow
A2: Central library structure + when docs fire in process + merge fields + DocuSign return path. Portal implements; workbook is the spec.
A4: 1 · LIBRARY STRUCTURE (by entity_id)
A5: Path pattern | B5: Contents | C5: Access
A6: /Firm/Corporate | B6: Formation, policies, insurance, tax | C6: Visionary, Counsel, Finance
A7: /Firm/IC_Memos | B7: IC packages by date | C7: Partners
A8: /Entities/{entity_id}/01_Corporate | B8: Charter, cap table, good standing | C8: Counsel, Partner, COO
A9: /Entities/{entity_id}/02_Deal | B9: TS/SPA/SAFE, side letters, wire | C9: Counsel, Partner
A10: /Entities/{entity_id}/03_DD | B10: Data room exports, QoE, reports | C10: Deal team
A11: /Entities/{entity_id}/04_Financials | B11: Monthly packs, audits, models | C11: Finance, COO, Partner
A12: /Entities/{entity_id}/05_HR | B12: Key employment (restricted) | C12: HR, Counsel
A13: /Entities/{entity_id}/06_Ops | B13: Playbooks, GTM maps, board decks | C13: COO, Sub Lead
A14: /Entities/{entity_id}/07_Signed | B14: DocuSign completed + certificates | C14: Counsel, system
A15: /Templates/ | B15: NDA, offer, TS, SPA riders, LOI | C15: Counsel edit; all read
A17: 2 · PROCESS EMBEDDING (when docs attach)
A18: Process step | B18: Document(s) | C18: Trigger | D18: Store to | E18: Task link
A19: VC First Call / NDA | B19: Mutual NDA | C19: Stage ≥ First Call | D19: …/02_Deal or pre-ENT holding | E19: Lead Tasks
A20: VC Term Sheet | B20: Term sheet PDF | C20: Deal stage Term Sheet | D20: …/02_Deal | E20: Deal Tasks
A21: VC / M&A Close | B21: SPA/APA/SAFE, IRA, consents | C21: Signing Ready | D21: …/07_Signed + 02_Deal | E21: Deal/M&A Tasks
A22: RE PSA | B22: Purchase agreement, addenda | C22: LOI/PSA stage | D22: …/02_Deal | E22: RE Tasks
A23: Portfolio Handoff | B23: Handoff pack PDF export | C23: Wire complete | D23: …/06_Ops | E23: Portfolio Handoff
A24: Employment offer | B24: Offer letter + PIIA | C24: HR hire approved | D24: …/05_HR | E24: HR ticket
A25: Vendor / SOW | B25: MSA/SOW from template | C25: Legal ticket | D25: …/02_Deal or Ops | E25: Legal ticket
A27: 3 · MERGE FIELDS (auto-populate from DB)
A28: Field token | B28: Source | C28: Example
A29: {{entity.canonical_name}} | B29: Entity Master | C29: Sample Closed Co
A30: {{entity.legal_name}} | B30: Entity Master | C30: Sample Closed Co Inc.
A31: {{deal.check_size}} | B31: Deal Active | C31: 4000
A32: {{deal.pre_money}} | B32: Deal Active / Financial Model | C32: 45
A33: {{deal.instrument}} | B33: Deal Active | C33: Priced Equity
A34: {{party.signatory_name}} | B34: Contacts table | C34: Jane Founder
A35: {{party.signatory_email}} | B35: Contacts | C35: jane@co.com
A36: {{firm.legal_name}} | B36: ENT-FIRM | C36: Tage Venture Capital LLC
A37: {{effective_date}} | B37: Workflow runtime | C37: 46103
A38: {{address}} / {{property}} | B38: RE Pipeline | C38: 1842 Maple St
A40: 4 · DOCUSIGN FLOW
A41: Step | B41: System action | C41: Human gate | D41: Output
A42: 1. Select template | B42: Load from /Templates + process step | C42: Counsel/Partner picks template | D42: Draft envelope
A43: 2. Merge fields | B43: Pull entity/deal/contact tokens | C43: User confirms field map | D43: Populated PDF/DOCX
A44: 3. Route signers | B44: Build routing order from roles | C44: Confirm emails/order | D44: Envelope definition
A45: 4. Send DocuSign | B45: API create+send envelope | C45: Click Send (never silent send on capital docs) | D45: envelope_id stored on task
A46: 5. Track status | B46: Webhook: sent/delivered/signed/declined | C46: Chase if stale >SLA | D46: Task status update
A47: 6. Complete | B47: Download PDF + certificate; hash store | C47: Counsel verifies package | D47: /07_Signed + audit_trail row
A48: 7. Post-process | B48: Mark task Complete; notify next step | C48: Owner advances stage if allowed | D48: Pipeline/Deal stage optional bump
A50: 5 · DOCUMENT RECORD (portal table docs)
A51: doc_id | entity_id | deal_or_task_id | doc_type | template_id | status | envelope_id | storage_uri | signed_at | created_by
A53: Automation: template merge High · send requires human on TS/SPA/wire docs · storage High · stage auto-advance Low (confirm).
A55: LINKS: Entity Master · Deal/M&A/RE Tasks · Portfolio Handoff · Shared Services Legal · Data Dictionary · Cursor Brief
